Workbook

Sheet Asumsi
B2: ASUMSI MODEL BISNIS — PRAKTIS (Direct-to-Market)
B3: Sumber asumsi: dokumen analisa-bisnis-praktis-direct.md + riset pasar 14 Agu 2026
B5: HARGA & PAKET
B6: Harga per transaksi (pay-per-use) | C6: 250 | D6: Rekomendasi: Rp150-500 (di atas rekeningkoran.com Rp400/halaman)
B7: Paket Starter — kuota transaksi | C7: 1000
B8: Paket Starter — harga | C8: 500000
B9: Paket Growth — kuota transaksi | C9: 3000
B10: Paket Growth — harga | C10: 1200000
B11: Paket Enterprise — kuota transaksi | C11: 10000
B12: Paket Enterprise — harga | C12: 3500000
B13: BIAYA VARIABEL
B14: AI cost per transaksi (model routing) | C14: 70 | D14: Asumsi GP 75-85% (MEMORY.md)
B15: Infra bulan 1-6 (Railway, dll) | C15: 2000000
B16: Infra bulan 7-12 (skala) | C16: 4000000
B17: ARPU & CHURN PER SKENARIO
B18: ARPU konservatif | C18: 600000
B19: ARPU moderat | C19: 800000
B20: ARPU optimis | C20: 1000000
B21: Churn konservatif (per bulan) | C21: 0.06
B22: Churn moderat (per bulan) | C22: 0.05
B23: Churn optimis (per bulan) | C23: 0.04
B24: PELANGGAN BARU PER BULAN
B25: Konservatif — konstan | C25: 3
B26: Moderat — b1-4 / b5-8 / b9-12 | C26: 5 | D26: Dialokasikan bertahap di sheet skenario
B27: Optimis — b1-4 / b5-8 / b9-12 | C27: 10
B28: MARKETING (Rp/bulan)
B29: Marketing fase 1 (b1-3) — konservatif | C29: 2000000
B30: Marketing fase 1 (b1-3) — moderat | C30: 2000000
B31: Marketing fase 1 (b1-3) — optimis | C31: 3000000
B32: Marketing fase 2 (b4-6) — konservatif | C32: 5000000
B33: Marketing fase 2 (b4-6) — moderat | C33: 10000000
B34: Marketing fase 2 (b4-6) — optimis | C34: 15000000
B35: Marketing fase 3 (b7-12) — konservatif | C35: 8000000
B36: Marketing fase 3 (b7-12) — moderat | C36: 16000000
B37: Marketing fase 3 (b7-12) — optimis | C37: 25000000
B38: INVESTASI AWAL (one-off)
B39: Fitur direct-market (dev 6-9 minggu) | C39: 25000000 | D39: Payment, self-serve, export CSV, landing page
B40: Domain, branding, tooling | C40: 5000000
B41: Dana cadangan (buffer) | C41: 10000000

Sheet Konservatif
A1: PROYEKSI 12 BULAN — KONSERVATIF
A3: Bulan | B3: Pelanggan Awal | C3: Pelanggan Baru | D3: Churn | E3: Pelanggan Akhir | F3: MRR | G3: Revenue | H3: AI Cost | I3: Infra | J3: Marketing | K3: Total Opex | L3: Net Cash Flow | M3: Kumulatif | N3: CAC Bulanan
A4: 1 | B4: 0 | C4: 3 | D4: =IF(B4=0,0,ROUND(B4*Asumsi!$C$21,0)) | E4: =B4+C4-D4 | F4: =E4*Asumsi!$C$18 | G4: =F4 | H4: =ROUND(G4*0.14,0) | I4: 2000000 | J4: 2000000 | K4: =H4+I4+J4 | L4: =G4-K4 | M4: =-SUM(Asumsi!$C$39:$C$41)+L4 | N4: =IF(C4=0,"-",J4/C4)
A5: 2 | B5: =L4 | C5: 3 | D5: =IF(B5=0,0,ROUND(B5*Asumsi!$C$21,0)) | E5: =B5+C5-D5 | F5: =E5*Asumsi!$C$18 | G5: =F5 | H5: =ROUND(G5*0.14,0) | I5: 2000000 | J5: 2000000 | K5: =H5+I5+J5 | L5: =G5-K5 | M5: =M4+L5 | N5: =IF(C5=0,"-",J5/C5)
A6: 3 | B6: =L5 | C6: 3 | D6: =IF(B6=0,0,ROUND(B6*Asumsi!$C$21,0)) | E6: =B6+C6-D6 | F6: =E6*Asumsi!$C$18 | G6: =F6 | H6: =ROUND(G6*0.14,0) | I6: 2000000 | J6: 2000000 | K6: =H6+I6+J6 | L6: =G6-K6 | M6: =M5+L6 | N6: =IF(C6=0,"-",J6/C6)
A7: 4 | B7: =L6 | C7: 3 | D7: =IF(B7=0,0,ROUND(B7*Asumsi!$C$21,0)) | E7: =B7+C7-D7 | F7: =E7*Asumsi!$C$18 | G7: =F7 | H7: =ROUND(G7*0.14,0) | I7: 2000000 | J7: 5000000 | K7: =H7+I7+J7 | L7: =G7-K7 | M7: =M6+L7 | N7: =IF(C7=0,"-",J7/C7)
A8: 5 | B8: =L7 | C8: 3 | D8: =IF(B8=0,0,ROUND(B8*Asumsi!$C$21,0)) | E8: =B8+C8-D8 | F8: =E8*Asumsi!$C$18 | G8: =F8 | H8: =ROUND(G8*0.14,0) | I8: 2000000 | J8: 5000000 | K8: =H8+I8+J8 | L8: =G8-K8 | M8: =M7+L8 | N8: =IF(C8=0,"-",J8/C8)
A9: 6 | B9: =L8 | C9: 3 | D9: =IF(B9=0,0,ROUND(B9*Asumsi!$C$21,0)) | E9: =B9+C9-D9 | F9: =E9*Asumsi!$C$18 | G9: =F9 | H9: =ROUND(G9*0.14,0) | I9: 2000000 | J9: 5000000 | K9: =H9+I9+J9 | L9: =G9-K9 | M9: =M8+L9 | N9: =IF(C9=0,"-",J9/C9)
A10: 7 | B10: =L9 | C10: 3 | D10: =IF(B10=0,0,ROUND(B10*Asumsi!$C$21,0)) | E10: =B10+C10-D10 | F10: =E10*Asumsi!$C$18 | G10: =F10 | H10: =ROUND(G10*0.14,0) | I10: 4000000 | J10: 8000000 | K10: =H10+I10+J10 | L10: =G10-K10 | M10: =M9+L10 | N10: =IF(C10=0,"-",J10/C10)
A11: 8 | B11: =L10 | C11: 3 | D11: =IF(B11=0,0,ROUND(B11*Asumsi!$C$21,0)) | E11: =B11+C11-D11 | F11: =E11*Asumsi!$C$18 | G11: =F11 | H11: =ROUND(G11*0.14,0) | I11: 4000000 | J11: 8000000 | K11: =H11+I11+J11 | L11: =G11-K11 | M11: =M10+L11 | N11: =IF(C11=0,"-",J11/C11)
A12: 9 | B12: =L11 | C12: 3 | D12: =IF(B12=0,0,ROUND(B12*Asumsi!$C$21,0)) | E12: =B12+C12-D12 | F12: =E12*Asumsi!$C$18 | G12: =F12 | H12: =ROUND(G12*0.14,0) | I12: 4000000 | J12: 8000000 | K12: =H12+I12+J12 | L12: =G12-K12 | M12: =M11+L12 | N12: =IF(C12=0,"-",J12/C12)
A13: 10 | B13: =L12 | C13: 3 | D13: =IF(B13=0,0,ROUND(B13*Asumsi!$C$21,0)) | E13: =B13+C13-D13 | F13: =E13*Asumsi!$C$18 | G13: =F13 | H13: =ROUND(G13*0.14,0) | I13: 4000000 | J13: 8000000 | K13: =H13+I13+J13 | L13: =G13-K13 | M13: =M12+L13 | N13: =IF(C13=0,"-",J13/C13)
A14: 11 | B14: =L13 | C14: 3 | D14: =IF(B14=0,0,ROUND(B14*Asumsi!$C$21,0)) | E14: =B14+C14-D14 | F14: =E14*Asumsi!$C$18 | G14: =F14 | H14: =ROUND(G14*0.14,0) | I14: 4000000 | J14: 8000000 | K14: =H14+I14+J14 | L14: =G14-K14 | M14: =M13+L14 | N14: =IF(C14=0,"-",J14/C14)
A15: 12 | B15: =L14 | C15: 3 | D15: =IF(B15=0,0,ROUND(B15*Asumsi!$C$21,0)) | E15: =B15+C15-D15 | F15: =E15*Asumsi!$C$18 | G15: =F15 | H15: =ROUND(G15*0.14,0) | I15: 4000000 | J15: 8000000 | K15: =H15+I15+J15 | L15: =G15-K15 | M15: =M14+L15 | N15: =IF(C15=0,"-",J15/C15)
A17: Break-even (kumulatif >= 0) | B17: =IFERROR(MATCH(TRUE,INDEX(M4:M15>=0,0),0),"-")
A18: Total pelanggan akhir (bulan 12) | B18: =E15
A19: Revenue kumulatif 12 bulan | B19: =SUM(G4:G15)
A20: Investasi awal (bulan 0) | B20: =SUM(Asumsi!C39:C41)

Sheet Moderat
A1: PROYEKSI 12 BULAN — MODERAT
A3: Bulan | B3: Pelanggan Awal | C3: Pelanggan Baru | D3: Churn | E3: Pelanggan Akhir | F3: MRR | G3: Revenue | H3: AI Cost | I3: Infra | J3: Marketing | K3: Total Opex | L3: Net Cash Flow | M3: Kumulatif | N3: CAC Bulanan
A4: 1 | B4: 0 | C4: 5 | D4: =IF(B4=0,0,ROUND(B4*Asumsi!$C$22,0)) | E4: =B4+C4-D4 | F4: =E4*Asumsi!$C$19 | G4: =F4 | H4: =ROUND(G4*0.14,0) | I4: 2000000 | J4: 2000000 | K4: =H4+I4+J4 | L4: =G4-K4 | M4: =-SUM(Asumsi!$C$39:$C$41)+L4 | N4: =IF(C4=0,"-",J4/C4)
A5: 2 | B5: =L4 | C5: 5 | D5: =IF(B5=0,0,ROUND(B5*Asumsi!$C$22,0)) | E5: =B5+C5-D5 | F5: =E5*Asumsi!$C$19 | G5: =F5 | H5: =ROUND(G5*0.14,0) | I5: 2000000 | J5: 2000000 | K5: =H5+I5+J5 | L5: =G5-K5 | M5: =M4+L5 | N5: =IF(C5=0,"-",J5/C5)
A6: 3 | B6: =L5 | C6: 5 | D6: =IF(B6=0,0,ROUND(B6*Asumsi!$C$22,0)) | E6: =B6+C6-D6 | F6: =E6*Asumsi!$C$19 | G6: =F6 | H6: =ROUND(G6*0.14,0) | I6: 2000000 | J6: 2000000 | K6: =H6+I6+J6 | L6: =G6-K6 | M6: =M5+L6 | N6: =IF(C6=0,"-",J6/C6)
A7: 4 | B7: =L6 | C7: 5 | D7: =IF(B7=0,0,ROUND(B7*Asumsi!$C$22,0)) | E7: =B7+C7-D7 | F7: =E7*Asumsi!$C$19 | G7: =F7 | H7: =ROUND(G7*0.14,0) | I7: 2000000 | J7: 10000000 | K7: =H7+I7+J7 | L7: =G7-K7 | M7: =M6+L7 | N7: =IF(C7=0,"-",J7/C7)
A8: 5 | B8: =L7 | C8: 8 | D8: =IF(B8=0,0,ROUND(B8*Asumsi!$C$22,0)) | E8: =B8+C8-D8 | F8: =E8*Asumsi!$C$19 | G8: =F8 | H8: =ROUND(G8*0.14,0) | I8: 2000000 | J8: 10000000 | K8: =H8+I8+J8 | L8: =G8-K8 | M8: =M7+L8 | N8: =IF(C8=0,"-",J8/C8)
A9: 6 | B9: =L8 | C9: 8 | D9: =IF(B9=0,0,ROUND(B9*Asumsi!$C$22,0)) | E9: =B9+C9-D9 | F9: =E9*Asumsi!$C$19 | G9: =F9 | H9: =ROUND(G9*0.14,0) | I9: 2000000 | J9: 10000000 | K9: =H9+I9+J9 | L9: =G9-K9 | M9: =M8+L9 | N9: =IF(C9=0,"-",J9/C9)
A10: 7 | B10: =L9 | C10: 8 | D10: =IF(B10=0,0,ROUND(B10*Asumsi!$C$22,0)) | E10: =B10+C10-D10 | F10: =E10*Asumsi!$C$19 | G10: =F10 | H10: =ROUND(G10*0.14,0) | I10: 4000000 | J10: 16000000 | K10: =H10+I10+J10 | L10: =G10-K10 | M10: =M9+L10 | N10: =IF(C10=0,"-",J10/C10)
A11: 8 | B11: =L10 | C11: 8 | D11: =IF(B11=0,0,ROUND(B11*Asumsi!$C$22,0)) | E11: =B11+C11-D11 | F11: =E11*Asumsi!$C$19 | G11: =F11 | H11: =ROUND(G11*0.14,0) | I11: 4000000 | J11: 16000000 | K11: =H11+I11+J11 | L11: =G11-K11 | M11: =M10+L11 | N11: =IF(C11=0,"-",J11/C11)
A12: 9 | B12: =L11 | C12: 12 | D12: =IF(B12=0,0,ROUND(B12*Asumsi!$C$22,0)) | E12: =B12+C12-D12 | F12: =E12*Asumsi!$C$19 | G12: =F12 | H12: =ROUND(G12*0.14,0) | I12: 4000000 | J12: 16000000 | K12: =H12+I12+J12 | L12: =G12-K12 | M12: =M11+L12 | N12: =IF(C12=0,"-",J12/C12)
A13: 10 | B13: =L12 | C13: 12 | D13: =IF(B13=0,0,ROUND(B13*Asumsi!$C$22,0)) | E13: =B13+C13-D13 | F13: =E13*Asumsi!$C$19 | G13: =F13 | H13: =ROUND(G13*0.14,0) | I13: 4000000 | J13: 16000000 | K13: =H13+I13+J13 | L13: =G13-K13 | M13: =M12+L13 | N13: =IF(C13=0,"-",J13/C13)
A14: 11 | B14: =L13 | C14: 12 | D14: =IF(B14=0,0,ROUND(B14*Asumsi!$C$22,0)) | E14: =B14+C14-D14 | F14: =E14*Asumsi!$C$19 | G14: =F14 | H14: =ROUND(G14*0.14,0) | I14: 4000000 | J14: 16000000 | K14: =H14+I14+J14 | L14: =G14-K14 | M14: =M13+L14 | N14: =IF(C14=0,"-",J14/C14)
A15: 12 | B15: =L14 | C15: 12 | D15: =IF(B15=0,0,ROUND(B15*Asumsi!$C$22,0)) | E15: =B15+C15-D15 | F15: =E15*Asumsi!$C$19 | G15: =F15 | H15: =ROUND(G15*0.14,0) | I15: 4000000 | J15: 16000000 | K15: =H15+I15+J15 | L15: =G15-K15 | M15: =M14+L15 | N15: =IF(C15=0,"-",J15/C15)
A17: Break-even (kumulatif >= 0) | B17: =IFERROR(MATCH(TRUE,INDEX(M4:M15>=0,0),0),"-")
A18: Total pelanggan akhir (bulan 12) | B18: =E15
A19: Revenue kumulatif 12 bulan | B19: =SUM(G4:G15)
A20: Investasi awal (bulan 0) | B20: =SUM(Asumsi!C39:C41)

Sheet Optimis
A1: PROYEKSI 12 BULAN — OPTIMIS
A3: Bulan | B3: Pelanggan Awal | C3: Pelanggan Baru | D3: Churn | E3: Pelanggan Akhir | F3: MRR | G3: Revenue | H3: AI Cost | I3: Infra | J3: Marketing | K3: Total Opex | L3: Net Cash Flow | M3: Kumulatif | N3: CAC Bulanan
A4: 1 | B4: 0 | C4: 10 | D4: =IF(B4=0,0,ROUND(B4*Asumsi!$C$23,0)) | E4: =B4+C4-D4 | F4: =E4*Asumsi!$C$20 | G4: =F4 | H4: =ROUND(G4*0.14,0) | I4: 2000000 | J4: 3000000 | K4: =H4+I4+J4 | L4: =G4-K4 | M4: =-SUM(Asumsi!$C$39:$C$41)+L4 | N4: =IF(C4=0,"-",J4/C4)
A5: 2 | B5: =L4 | C5: 10 | D5: =IF(B5=0,0,ROUND(B5*Asumsi!$C$23,0)) | E5: =B5+C5-D5 | F5: =E5*Asumsi!$C$20 | G5: =F5 | H5: =ROUND(G5*0.14,0) | I5: 2000000 | J5: 3000000 | K5: =H5+I5+J5 | L5: =G5-K5 | M5: =M4+L5 | N5: =IF(C5=0,"-",J5/C5)
A6: 3 | B6: =L5 | C6: 10 | D6: =IF(B6=0,0,ROUND(B6*Asumsi!$C$23,0)) | E6: =B6+C6-D6 | F6: =E6*Asumsi!$C$20 | G6: =F6 | H6: =ROUND(G6*0.14,0) | I6: 2000000 | J6: 3000000 | K6: =H6+I6+J6 | L6: =G6-K6 | M6: =M5+L6 | N6: =IF(C6=0,"-",J6/C6)
A7: 4 | B7: =L6 | C7: 10 | D7: =IF(B7=0,0,ROUND(B7*Asumsi!$C$23,0)) | E7: =B7+C7-D7 | F7: =E7*Asumsi!$C$20 | G7: =F7 | H7: =ROUND(G7*0.14,0) | I7: 2000000 | J7: 15000000 | K7: =H7+I7+J7 | L7: =G7-K7 | M7: =M6+L7 | N7: =IF(C7=0,"-",J7/C7)
A8: 5 | B8: =L7 | C8: 18 | D8: =IF(B8=0,0,ROUND(B8*Asumsi!$C$23,0)) | E8: =B8+C8-D8 | F8: =E8*Asumsi!$C$20 | G8: =F8 | H8: =ROUND(G8*0.14,0) | I8: 2000000 | J8: 15000000 | K8: =H8+I8+J8 | L8: =G8-K8 | M8: =M7+L8 | N8: =IF(C8=0,"-",J8/C8)
A9: 6 | B9: =L8 | C9: 18 | D9: =IF(B9=0,0,ROUND(B9*Asumsi!$C$23,0)) | E9: =B9+C9-D9 | F9: =E9*Asumsi!$C$20 | G9: =F9 | H9: =ROUND(G9*0.14,0) | I9: 2000000 | J9: 15000000 | K9: =H9+I9+J9 | L9: =G9-K9 | M9: =M8+L9 | N9: =IF(C9=0,"-",J9/C9)
A10: 7 | B10: =L9 | C10: 18 | D10: =IF(B10=0,0,ROUND(B10*Asumsi!$C$23,0)) | E10: =B10+C10-D10 | F10: =E10*Asumsi!$C$20 | G10: =F10 | H10: =ROUND(G10*0.14,0) | I10: 4000000 | J10: 25000000 | K10: =H10+I10+J10 | L10: =G10-K10 | M10: =M9+L10 | N10: =IF(C10=0,"-",J10/C10)
A11: 8 | B11: =L10 | C11: 18 | D11: =IF(B11=0,0,ROUND(B11*Asumsi!$C$23,0)) | E11: =B11+C11-D11 | F11: =E11*Asumsi!$C$20 | G11: =F11 | H11: =ROUND(G11*0.14,0) | I11: 4000000 | J11: 25000000 | K11: =H11+I11+J11 | L11: =G11-K11 | M11: =M10+L11 | N11: =IF(C11=0,"-",J11/C11)
A12: 9 | B12: =L11 | C12: 25 | D12: =IF(B12=0,0,ROUND(B12*Asumsi!$C$23,0)) | E12: =B12+C12-D12 | F12: =E12*Asumsi!$C$20 | G12: =F12 | H12: =ROUND(G12*0.14,0) | I12: 4000000 | J12: 25000000 | K12: =H12+I12+J12 | L12: =G12-K12 | M12: =M11+L12 | N12: =IF(C12=0,"-",J12/C12)
A13: 10 | B13: =L12 | C13: 25 | D13: =IF(B13=0,0,ROUND(B13*Asumsi!$C$23,0)) | E13: =B13+C13-D13 | F13: =E13*Asumsi!$C$20 | G13: =F13 | H13: =ROUND(G13*0.14,0) | I13: 4000000 | J13: 25000000 | K13: =H13+I13+J13 | L13: =G13-K13 | M13: =M12+L13 | N13: =IF(C13=0,"-",J13/C13)
A14: 11 | B14: =L13 | C14: 25 | D14: =IF(B14=0,0,ROUND(B14*Asumsi!$C$23,0)) | E14: =B14+C14-D14 | F14: =E14*Asumsi!$C$20 | G14: =F14 | H14: =ROUND(G14*0.14,0) | I14: 4000000 | J14: 25000000 | K14: =H14+I14+J14 | L14: =G14-K14 | M14: =M13+L14 | N14: =IF(C14=0,"-",J14/C14)
A15: 12 | B15: =L14 | C15: 25 | D15: =IF(B15=0,0,ROUND(B15*Asumsi!$C$23,0)) | E15: =B15+C15-D15 | F15: =E15*Asumsi!$C$20 | G15: =F15 | H15: =ROUND(G15*0.14,0) | I15: 4000000 | J15: 25000000 | K15: =H15+I15+J15 | L15: =G15-K15 | M15: =M14+L15 | N15: =IF(C15=0,"-",J15/C15)
A17: Break-even (kumulatif >= 0) | B17: =IFERROR(MATCH(TRUE,INDEX(M4:M15>=0,0),0),"-")
A18: Total pelanggan akhir (bulan 12) | B18: =E15
A19: Revenue kumulatif 12 bulan | B19: =SUM(G4:G15)
A20: Investasi awal (bulan 0) | B20: =SUM(Asumsi!C39:C41)

Sheet Unit Economics
A1: UNIT ECONOMICS (SKENARIO MODERAT)
A3: Metrik | B3: Nilai | C3: Benchmark
A4: ARPU (Rp/bulan) | B4: =Asumsi!$C$19
A5: Churn bulanan | B5: =Asumsi!$C$22 | C5: Rp 600-800rb
A6: Gross margin (1 - AI cost %) | B6: =1-Asumsi!$C$15/(Asumsi!$C$8/Asumsi!$C$7) | C6: 3-6%
A7: CAC (Rp, rata-rata) | B7: =IFERROR(AVERAGE(Moderat!N4:N15),0) | C7: 70-85%
A8: LTV (Rp) | B8: =IFERROR(B4*B6/B5,0) | C8: Rp 400-800rb
A9: LTV : CAC | B9: =IFERROR(B8/B7,0)&"x" | C9: Rp 10-15 jt
A10: Payback (bulan) | B10: =IFERROR(B7/(B4*B6),0) | C10: > 3x
A11: MRR bulan 12 | B11: =Moderat!F15 | C11: 1-3 bln
A12: Revenue kumulatif 12 bln | B12: =Moderat!G16

Sheet Ringkasan
A1: RINGKASAN ANALISA BISNIS — PRAKTIS
A2: AI Bookkeeping: PDF/foto/Excel/CSV → draft jurnal + laporan keuangan · Agustus 2026
A4: Metrik Kunci | B4: Konservatif | C4: Moderat | D4: Optimis
A5: Investasi awal (Rp) | B5: =SUM(Asumsi!C39:C41) | C5: =SUM(Asumsi!C39:C41) | D5: =SUM(Asumsi!C39:C41)
A6: Pelanggan akhir (bln 12) | B6: =Konservatif!E15 | C6: =Moderat!E15 | D6: =Optimis!E15
A7: MRR bulan 12 (Rp) | B7: =Konservatif!F15 | C7: =Moderat!F15 | D7: =Optimis!F15
A8: Revenue kumulatif 12 bln | B8: =Konservatif!G16 | C8: =Moderat!G16 | D8: =Optimis!G16
A9: Net cash kumulatif (bln 12) | B9: =Konservatif!M15 | C9: =Moderat!M15 | D9: =Optimis!M15
A10: Break-even (bulan ke-) | B10: =Konservatif!B17 | C10: =Moderat!B17 | D10: =Optimis!B17
A11: CAC rata-rata (Rp) | B11: =IFERROR(AVERAGE(Konservatif!N4:N15),0) | C11: =IFERROR(AVERAGE(Moderat!N4:N15),0) | D11: =IFERROR(AVERAGE(Optimis!N4:N15),0)

Sheet Marketing Plan
A1: RENCANA PEMASARAN 12 BULAN (SKENARIO MODERAT)
A3: Fase | B3: Bulan | C3: Aktivitas | D3: Budget | E3: Target Pelanggan | F3: CAC Harapan | G3: Catatan
A4: Fase 1 | B4: 1-3 | C4: Konten edukasi (LinkedIn, blog), SEO tutorial rekening koran, komunitas akuntan/KAP, cold outreach 200 target | D4: 6000000 | E4: 10-15 | F4: Rp 400-500rb | G4: Validasi product-market fit, CAC rendah
A5: Fase 2 | B5: 4-6 | C5: Google Ads (keyword: rekening koran ke excel/jurnal), Meta Ads retargeting, referral program, webinar bulanan | D5: 30000000 | E5: 20 | F5: Rp 600-700rb | G5: Scale kanal berbayar
A6: Fase 3 | B6: 7-12 | C6: Google + Meta + YouTube, partnership KAP/komunitas/kampus, 1 sales AE | D6: 96000000 | E6: 50+ | F6: Rp 700-800rb | G6: Sales-assisted untuk enterprise
B7: TOTAL | D7: =SUM(D4:D6) | E7: 80-85 | G7: ≈ Rp 132 jt
