Workbook
Name \A: [1]Isian!#REF!
Name \B: [1]Isian!#REF!
Name \C: [1]Isian!#REF!
Name \D: [1]Isian!#REF!
Name \E: [1]Isian!#REF!
Name \F: [1]Isian!#REF!
Name \G: [1]Isian!#REF!
Name \H: [1]Isian!#REF!
Name \I: [1]Isian!#REF!
Name \J: [1]Isian!#REF!
Name \V: #REF!
Name \X: #REF!
Name \Z: #REF!
Name _____bpp1: [2]gl!$E$322
Name _____bpp2: #REF!
Name _____bpp3: #REF!
Name ____bpp1: [2]gl!$E$322
Name ____bpp2: #REF!
Name ____bpp3: #REF!
Name ___bpp1: [2]gl!$E$322
Name ___bpp2: #REF!
Name ___bpp3: #REF!
Name __bpp1: [2]gl!$E$322
Name __bpp2: #REF!
Name __bpp3: #REF!
Name _1: #REF!
Name _1195.A1: #REF!
Name _1195.A2: #REF!
Name _1195.A3: #REF!
Name _1195.B1: '[4]1195 B1'!#REF!
Name _1195.B11: '[5]1195 B1'!#REF!
Name _1195.B2: #REF!
Name _1195.B4: #REF!
Name _1195a: [6]Identitas!#REF!
Name _1195c: #REF!
Name _31_12_1993: #REF!
Name _Apr01: #REF!
Name _B_BNI.6064.Pro: #REF!
Name _bdn01: #REF!
Name _bp01: [7]BP1_23!#REF!
Name _bpp1: [2]gl!$E$322
Name _bpp2: #REF!
Name _bpp3: #REF!
Name _CTM13: #REF!
Name _CTM15: #REF!
Name _CTM18: #REF!
Name _CTM23: #REF!
Name _CTM26: #REF!
Name _CTM38: #REF!
Name _CTM7: #REF!
Name _DAF_ISI: #REF!
Name _Data.umum: #REF!
Name _DENGAN_PERBAND: [8]NERACA!#REF!
Name _fp01: #REF!
Name _HIT01: #REF!
Name _jan01: #REF!
Name _MTL13: #REF!
Name _MTL15: #REF!
Name _MTL18: #REF!
Name _MTL23: #REF!

Sheet User
C6: KODE | D6: GL-2468907531-XCL

Sheet Menu
B5: Nama Perusahaan | C5: ARYA USAHA TIRTA, CV
B6: Tahun | C6: 2026

Sheet Akun
A1: =NAMA -> ARYA USAHA TIRTA, CV
A2: DAFTAR AKUN
A3: ="Tahun : "&THN -> Tahun : 2026
A5: Kode | B5: Nama Akun | C5: Pos | D5: Pos | F5: Saldo Awal | G5: Saldo Awal
A6: Akun | C6: Saldo | D6: Laporan | F6: Debet | G6: Kredit
A7: 100000000 | B7: AKTIVA
A8: 1-100-000 | B8: AKTIVA LANCAR
A9: 1-101-000 | B9: Kas dan Bank | C9: Db | D9: NRC
A10: 1-101-001 | B10: Petty Cash | C10: Db | D10: NRC | F10: 0
A11: 1-101-010 | B11: CIMB Niaga - Acc. No: 800171592300 | C11: Db | D11: NRC | F11: 3043241
A12: 1-101-011 | B12: Bank 2 | C12: Db | D12: NRC | F12: 0
A13: 1-101-012 | B13: Bank 3 | C13: Db | D13: NRC | F13: 0
A14: 1-101-013 | B14: BAnk 4 | C14: Db | D14: NRC | F14: 0
A15: 1-101-100 | B15: Bank Deposit | C15: Db | D15: NRC | F15: 0
A16: 1-101-101 | B16: Others Deposit | C16: Db | D16: NRC | F16: 0
A17: 1-101-200 | B17: Cash In Transit | C17: Db | D17: NRC | F17: 0
A18: 1-102-000 | B18: Account Receivable | C18: Db | D18: NRC | F18: 0
A19: 1-102-001 | B19: Receivable - Trade | C19: Db | D19: NRC | F19: 13548978
A20: 1-102-002 | B20: Employee Receivable | C20: Db | D20: NRC | F20: 0
A21: 1-102-003 | B21: Prepayment / Uang Muka | C21: Db | D21: NRC | F21: 0
... A53: 1-120-999 | B53: Other Asset | C53: Db | D53: NRC | F53: 0
A54: 2-130-000 | B54: Account Payable | C54: Kr | D54: NRC | G54: 0
A55: 2-130-001 | B55: Account Payable - Trade | C55: Kr | D55: NRC | G55: 0
A56: 2-140-000 | B56: Other Payable | C56: Kr | D56: NRC | G56: 0
A57: 2-140-001 | B57: Salary Payable | C57: Kr | D57: NRC | G57: 0
A58: 2-140-010 | B58: BPJS Payable | C58: Kr | D58: NRC | G58: 0
A59: 2-140-020 | B59: Accrued Expenses - General | C59: Kr | D59: NRC | G59: 0
A60: 2-140-021 | B60: Accrued Expenses - Project | C60: Kr | D60: NRC | G60: 0
A61: 2-140-030 | B61: Tax Payable - PPh Ps 21/26 | C61: Kr | D61: NRC | G61: 0
A62: 2-140-031 | B62: Tax Payable - PPh Ps 23 | C62: Kr | D62: NRC | G62: 0
A63: 2-140-032 | B63: Tax Payable - PPh Ps 29 | C63: Kr | D63: NRC | G63: 0
A64: 2-140-033 | B64: Tax Payable - PPh Ps 4 (2) | C64: Kr | D64: NRC | G64: 0
A65: 2-140-040 | B65: Dividend Payable | C65: Kr | D65: NRC | G65: 0
... A88: 3-102-004 | B88: Ekuitas Lainnya | C88: Kr | D88: LR | G88: 19663808
A89: 4-100-000 | B89: Total Revenue | C89: Kr | D89: LR
A90: 4-101-000 | B90: Total Event Management Services Income | C90: Kr | D90: LR
A91: 4-101-001 | B91: Pendapatan Usaha | C91: Kr | D91: LR
A92: 4-101-002 | B92: Pendapatan .... | C92: Kr | D92: LR
A93: 4-101-003 | B93: Pendapatan .... | C93: Kr | D93: LR
A94: 4-101-004 | B94: Pendapatan .... | C94: Kr | D94: LR
A95: 4-101-005 | B95: Pendapatan .... | C95: Kr | D95: LR
A96: 4-101-006 | B96: Pendapatan .... | C96: Kr | D96: LR
A97: 4-101-007 | B97: Pendapatan .... | C97: Kr | D97: LR
A98: 4-101-008 | B98: Pendapatan .... | C98: Kr | D98: LR
A99: 4-101-020 | B99: Pendapatan .... | C99: Kr | D99: LR
A100: 4-101-100 | B100: Agency Service Fee | C100: Kr | D100: LR
... A201: 9-102-001 | B201: Dividend Expense | C201: Db | D201: LR
B202: Jumlah | F202: =SUM(F7:F201) -> 25666508 | G202: =SUM(G7:G201) -> 25666508

Sheet Kode
A1: =NAMA -> ARYA USAHA TIRTA, CV
A2: DAFTAR KODE PEMBANTU
A3: ="Tahun : "&THN -> Tahun : 2026
A5: Kode | B5: Piutang Dagang | C5: Status | D5: Saldo Awal
B14: Jumlah | D14: =SUM(D6:D13) -> 0
A17: Kode | B17: Piutang Lain-lain | C17: Status | D17: Saldo Awal
A18: CT-001 | B18: Jaya Impian Abadi | C18: Piutang | D18: 0
A19: CT-002 | B19: Arya Usaha Tirta | C19: Piutang | D19: 0
A20: CT-003 | C20: Piutang | D20: 0
A21: SH-001 | B21: Jilmi Astina Anif | C21: Piutang | D21: 0
A22: SH-002 | B22: Arief Yudo Wibowo | C22: Piutang | D22: 0
A23: SH-003 | B23: Djulianis | C23: Piutang | D23: 0
A24: SH-004 | B24: Yanita | C24: Piutang | D24: 0
C25: Piutang | D25: 0
C26: Piutang | D26: 0
B27: Jumlah | D27: =SUM(D18:D26) -> 0
A30: Kode | B30: Hutang Dagang | C30: Status | D30: Saldo Awal
A31: AP-001 | B31: KMK BRI | C31: Hutang | D31: 0
A32: AP-002 | B32: GIFTEE | C32: Hutang | D32: 0
C33: Hutang | D33: 0
C34: Hutang | D34: 0
C35: Hutang | D35: 0
B38: Jumlah | D38: =SUM(D31:D37) -> 0

Sheet Jurnal
F1: =NAMA -> ARYA USAHA TIRTA, CV
F2: JURNAL UMUM
F3: ="Tahun : "&THN -> Tahun : 2026
L4: =SUM(L7:L1000) -> 310838800 | M4: =SUM(M7:M1000) -> 310838800 | N4: =L4-M4 -> 0
F5: Tanggal | G5: Bukti | H5: Keterangan Transaksi | I5: Kode | J5: Nama Akun | K5: Kode | L5: Debet | M5: Kredit
A6: 1 | B6: 2 | C6: 3 | D6: 4 | I6: Akun | K6: Bantu
A7: =IF(I7=VALUE,VALUE,COUNTIF($B$7:B7,B7))&I7&IF(F7<>VALUE,TEXT(F7,"mmmm"),VALUE) -> 00 | B7: =I7&IF(F7<>VALUE,TEXT(F7,"mmmm"),VALUE) -> 0 | C7: =COUNTIF($K$7:K7,K7)&K7 -> 0 | D7: =IF(MONTH(F7)<MONTH(BLN),"1"&I7,VALUE) -> 1 | J7: =IF(ISNA(VLOOKUP(I7,DAF_AKUN,2,FALSE)),"-",VLOOKUP(I7,DAF_AKUN,2,FALSE)) -> -
A8: =IF(I8=VALUE,VALUE,COUNTIF($B$7:B8,B8))&I8&IF(F8<>VALUE,TEXT(F8,"mmmm"),VALUE) -> 00 | B8: =I8&IF(F8<>VALUE,TEXT(F8,"mmmm"),VALUE) -> 0 | C8: =COUNTIF($K$7:K8,K8)&K8 -> 0 | D8: =IF(MONTH(F8)<MONTH(BLN),"1"&I8,VALUE) -> 1 | H8: Sales | J8: =IF(ISNA(VLOOKUP(I8,DAF_AKUN,2,FALSE)),"-",VLOOKUP(I8,DAF_AKUN,2,FALSE)) -> -
A9: =IF(I9=VALUE,VALUE,COUNTIF($B$7:B9,B9))&I9&IF(F9<>VALUE,TEXT(F9,"mmmm"),VALUE) -> 11-102-001January | B9: =I9&IF(F9<>VALUE,TEXT(F9,"mmmm"),VALUE) -> 1-102-001January | C9: =COUNTIF($K$7:K9,K9)&K9 -> 0 | D9: =IF(MONTH(F9)<MONTH(BLN),"1"&I9,VALUE) -> 11-102-001 | F9: 46053 | H9: Sales Januari 2026 | I9: 1-102-001 | J9: =IF(ISNA(VLOOKUP(I9,DAF_AKUN,2,FALSE)),"-",VLOOKUP(I9,DAF_AKUN,2,FALSE)) -> Receivable - Trade | L9: =SUM(M10:M18) -> 20321000
A10: =IF(I10=VALUE,VALUE,COUNTIF($B$7:B10,B10))&I10&IF(F10<>VALUE,TEXT(F10,"mmmm"),VALUE) -> 14-101-001January | B10: =I10&IF(F10<>VALUE,TEXT(F10,"mmmm"),VALUE) -> 4-101-001January | C10: =COUNTIF($K$7:K10,K10)&K10 -> 0 | D10: =IF(MONTH(F10)<MONTH(BLN),"1"&I10,VALUE) -> 14-101-001 | F10: 46030 | G10: INV-00196 | H10: Paviliun Date 9-13 Jan | I10: 4-101-001 | J10: =IF(ISNA(VLOOKUP(I10,DAF_AKUN,2,FALSE)),"-",VLOOKUP(I10,DAF_AKUN,2,FALSE)) -> Pendapatan Usaha | M10: 1960000
A11: =IF(I11=VALUE,VALUE,COUNTIF($B$7:B11,B11))&I11&IF(F11<>VALUE,TEXT(F11,"mmmm"),VALUE) -> 24-101-001January | B11: =I11&IF(F11<>VALUE,TEXT(F11,"mmmm"),VALUE) -> 4-101-001January | C11: =COUNTIF($K$7:K11,K11)&K11 -> 0 | D11: =IF(MONTH(F11)<MONTH(BLN),"1"&I11,VALUE) -> 14-101-001 | F11: 46034 | G11: INV-001100 | H11: Surfing Lesson | I11: 4-101-001 | J11: =IF(ISNA(VLOOKUP(I11,DAF_AKUN,2,FALSE)),"-",VLOOKUP(I11,DAF_AKUN,2,FALSE)) -> Pendapatan Usaha | M11: 4060000
A12: =IF(I12=VALUE,VALUE,COUNTIF($B$7:B12,B12))&I12&IF(F12<>VALUE,TEXT(F12,"mmmm"),VALUE) -> 34-101-001January | B12: =I12&IF(F12<>VALUE,TEXT(F12,"mmmm"),VALUE) -> 4-101-001January | C12: =COUNTIF($K$7:K12,K12)&K12 -> 0 | D12: =IF(MONTH(F12)<MONTH(BLN),"1"&I12,VALUE) -> 14-101-001 | F12: 46034 | G12: INV-001101 | H12: Room 3 | I12: 4-101-001 | J12: =IF(ISNA(VLOOKUP(I12,DAF_AKUN,2,FALSE)),"-",VLOOKUP(I12,DAF_AKUN,2,FALSE)) -> Pendapatan Usaha | M12: 2500000
A13: =IF(I13=VALUE,VALUE,COUNTIF($B$7:B13,B13))&I13&IF(F13<>VALUE,TEXT(F13,"mmmm"),VALUE) -> 44-101-001January | B13: =I13&IF(F13<>VALUE,TEXT(F13,"mmmm"),VALUE) -> 4-101-001January | C13: =COUNTIF($K$7:K13,K13)&K13 -> 0 | D13: =IF(MONTH(F13)<MONTH(BLN),"1"&I13,VALUE) -> 14-101-001 | F13: 46036 | G13: INV-001102 | H13: Room 2 | I13: 4-101-001 | J13: =IF(ISNA(VLOOKUP(I13,DAF_AKUN,2,FALSE)),"-",VLOOKUP(I13,DAF_AKUN,2,FALSE)) -> Pendapatan Usaha | M13: 1400000
A14: =IF(I14=VALUE,VALUE,COUNTIF($B$7:B14,B14))&I14&IF(F14<>VALUE,TEXT(F14,"mmmm"),VALUE) -> 54-101-001January | B14: =I14&IF(F14<>VALUE,TEXT(F14,"mmmm"),VALUE) -> 4-101-001January | C14: =COUNTIF($K$7:K14,K14)&K14 -> 0 | D14: =IF(MONTH(F14)<MONTH(BLN),"1"&I14,VALUE) -> 14-101-001 | F14: 46036 | G14: INV-001102 | H14: Room 2 | I14: 4-101-001 | J14: =IF(ISNA(VLOOKUP(I14,DAF_AKUN,2,FALSE)),"-",VLOOKUP(I14,DAF_AKUN,2,FALSE)) -> Pendapatan Usaha | M14: 721000
A15: =IF(I15=VALUE,VALUE,COUNTIF($B$7:B775,B15))&I15&IF(F15<>VALUE,TEXT(F15,"mmmm"),VALUE) -> 104-101-001January | B15: =I15&IF(F15<>VALUE,TEXT(F15,"mmmm"),VALUE) -> 4-101-001January | C15: =COUNTIF($K$7:K775,K15)&K15 -> 0 | D15: =IF(MONTH(F15)<MONTH(BLN),"1"&I15,VALUE) -> 14-101-001 | F15: 46041 | G15: INV-001104 | H15: Bike Rent | I15: 4-101-001 | J15: =IF(ISNA(VLOOKUP(I15,DAF_AKUN,2,FALSE)),"-",VLOOKUP(I15,DAF_AKUN,2,FALSE)) -> Pendapatan Usaha | M15: 560000
A16: =IF(I16=VALUE,VALUE,COUNTIF($B$7:B16,B16))&I16&IF(F16<>VALUE,TEXT(F16,"mmmm"),VALUE) -> 74-101-001January | B16: =I16&IF(F16<>VALUE,TEXT(F16,"mmmm"),VALUE) -> 4-101-001January | C16: =COUNTIF($K$7:K16,K16)&K16 -> 0 | D16: =IF(MONTH(F16)<MONTH(BLN),"1"&I16,VALUE) -> 14-101-001 | F16: 46041 | G16: INV-001103 | H16: Room 3 | I16: 4-101-001 | J16: =IF(ISNA(VLOOKUP(I16,DAF_AKUN,2,FALSE)),"-",VLOOKUP(I16,DAF_AKUN,2,FALSE)) -> Pendapatan Usaha | M16: 4120000
A17: =IF(I17=VALUE,VALUE,COUNTIF($B$7:B775,B17))&I17&IF(F17<>VALUE,TEXT(F17,"mmmm"),VALUE) -> 104-101-001January | B17: =I17&IF(F17<>VALUE,TEXT(F17,"mmmm"),VALUE) -> 4-101-001January | C17: =COUNTIF($K$7:K775,K17)&K17 -> 0 | D17: =IF(MONTH(F17)<MONTH(BLN),"1"&I17,VALUE) -> 14-101-001 | F17: 46041 | G17: INV-001105 | H17: Room 2 | I17: 4-101-001 | J17: =IF(ISNA(VLOOKUP(I17,DAF_AKUN,2,FALSE)),"-",VLOOKUP(I17,DAF_AKUN,2,FALSE)) -> Pendapatan Usaha | M17: 1500000
A18: =IF(I18=VALUE,VALUE,COUNTIF($B$7:B163,B18))&I18&IF(F18<>VALUE,TEXT(F18,"mmmm"),VALUE) -> 104-101-001January | B18: =I18&IF(F18<>VALUE,TEXT(F18,"mmmm"),VALUE) -> 4-101-001January | C18: =COUNTIF($K$7:K163,K18)&K18 -> 0 | D18: =IF(MONTH(F18)<MONTH(BLN),"1"&I18,VALUE) -> 14-101-001 | F18: 46042 | G18: INV-001106 | H18: Room 1 | I18: 4-101-001 | J18: =IF(ISNA(VLOOKUP(I18,DAF_AKUN,2,FALSE)),"-",VLOOKUP(I18,DAF_AKUN,2,FALSE)) -> Pendapatan Usaha | M18: 3500000
A19: =IF(I19=VALUE,VALUE,COUNTIF($B$7:B19,B19))&I19&IF(F19<>VALUE,TEXT(F19,"mmmm"),VALUE) -> 11-102-001February | B19: =I19&IF(F19<>VALUE,TEXT(F19,"mmmm"),VALUE) -> 1-102-001February | C19: =COUNTIF($K$7:K19,K19)&K19 -> 0 | D19: =IF(MONTH(F19)<MONTH(BLN),"1"&I19,VALUE) -> 11-102-001 | F19: 46081 | H19: Sales Februari 2026 | I19: 1-102-001 | J19: =IF(ISNA(VLOOKUP(I19,DAF_AKUN,2,FALSE)),"-",VLOOKUP(I19,DAF_AKUN,2,FALSE)) -> Receivable - Trade | L19: =SUM(M20:M26) -> 16850000
A20: =IF(I20=VALUE,VALUE,COUNTIF($B$7:B20,B20))&I20&IF(F20<>VALUE,TEXT(F20,"mmmm"),VALUE) -> 14-101-001February | B20: =I20&IF(F20<>VALUE,TEXT(F20,"mmmm"),VALUE) -> 4-101-001February | C20: =COUNTIF($K$7:K20,K20)&K20 -> 0 | D20: =IF(MONTH(F20)<MONTH(BLN),"1"&I20,VALUE) -> 14-101-001 | F20: 46058 | G20: INV-00113 | H20: Room 4 | I20: 4-101-001 | J20: =IF(ISNA(VLOOKUP(I20,DAF_AKUN,2,FALSE)),"-",VLOOKUP(I20,DAF_AKUN,2,FALSE)) -> Pendapatan Usaha | M20: 4500000
A21: =IF(I21=VALUE,VALUE,COUNTIF($B$7:B21,B21))&I21&IF(F21<>VALUE,TEXT(F21,"mmmm"),VALUE) -> 24-101-001February | B21: =I21&IF(F21<>VALUE,TEXT(F21,"mmmm"),VALUE) -> 4-101-001February | C21: =COUNTIF($K$7:K21,K21)&K21 -> 0 | D21: =IF(MONTH(F21)<MONTH(BLN),"1"&I21,VALUE) -> 14-101-001 | F21: 46058 | G21: INV-00114 | H21: Room 6 | I21: 4-101-001 | J21: =IF(ISNA(VLOOKUP(I21,DAF_AKUN,2,FALSE)),"-",VLOOKUP(I21,DAF_AKUN,2,FALSE)) -> Pendapatan Usaha | M21: 1600000
A22: =IF(I22=VALUE,VALUE,COUNTIF($B$7:B22,B22))&I22&IF(F22<>VALUE,TEXT(F22,"mmmm"),VALUE) -> 34-101-001February | B22: =I22&IF(F22<>VALUE,TEXT(F22,"mmmm"),VALUE) -> 4-101-001February | C22: =COUNTIF($K$7:K22,K22)&K22 -> 0 | D22: =IF(MONTH(F22)<MONTH(BLN),"1"&I22,VALUE) -> 14-101-001 | F22: 46062 | G22: INV-00114 | H22: Drop Of Cimaja | I22: 4-101-001 | J22: =IF(ISNA(VLOOKUP(I22,DAF_AKUN,2,FALSE)),"-",VLOOKUP(I22,DAF_AKUN,2,FALSE)) -> Pendapatan Usaha | M22: 1300000
A23: =IF(I23=VALUE,VALUE,COUNTIF($B$7:B23,B23))&I23&IF(F23<>VALUE,TEXT(F23,"mmmm"),VALUE) -> 44-101-001February | B23: =I23&IF(F23<>VALUE,TEXT(F23,"mmmm"),VALUE) -> 4-101-001February | C23: =COUNTIF($K$7:K23,K23)&K23 -> 0 | D23: =IF(MONTH(F23)<MONTH(BLN),"1"&I23,VALUE) -> 14-101-001 | F23: 46062 | G23: INV-00114 | H23: Room 3, Room Ibu, Surfing Board & Drop of Bandung | I23: 4-101-001 | J23: =IF(ISNA(VLOOKUP(I23,DAF_AKUN,2,FALSE)),"-",VLOOKUP(I23,DAF_AKUN,2,FALSE)) -> Pendapatan Usaha | M23: 4950000
A24: =IF(I24=VALUE,VALUE,COUNTIF($B$7:B24,B24))&I24&IF(F24<>VALUE,TEXT(F24,"mmmm"),VALUE) -> 54-101-001February | B24: =I24&IF(F24<>VALUE,TEXT(F24,"mmmm"),VALUE) -> 4-101-001February | C24: =COUNTIF($K$7:K24,K24)&K24 -> 0 | D24: =IF(MONTH(F24)<MONTH(BLN),"1"&I24,VALUE) -> 14-101-001 | F24: 46064 | G24: INV-00115 | H24: Room 4 | I24: 4-101-001 | J24: =IF(ISNA(VLOOKUP(I24,DAF_AKUN,2,FALSE)),"-",VLOOKUP(I24,DAF_AKUN,2,FALSE)) -> Pendapatan Usaha | M24: 500000
A25: =IF(I25=VALUE,VALUE,COUNTIF($B$7:B25,B25))&I25&IF(F25<>VALUE,TEXT(F25,"mmmm"),VALUE) -> 64-101-001February | B25: =I25&IF(F25<>VALUE,TEXT(F25,"mmmm"),VALUE) -> 4-101-001February | C25: =COUNTIF($K$7:K25,K25)&K25 -> 0 | D25: =IF(MONTH(F25)<MONTH(BLN),"1"&I25,VALUE) -> 14-101-001 | F25: 46068 | G25: INV-00117 | H25: Room 3 | I25: 4-101-001 | J25: =IF(ISNA(VLOOKUP(I25,DAF_AKUN,2,FALSE)),"-",VLOOKUP(I25,DAF_AKUN,2,FALSE)) -> Pendapatan Usaha | M25: 500000
A26: =IF(I26=VALUE,VALUE,COUNTIF($B$7:B26,B26))&I26&IF(F26<>VALUE,TEXT(F26,"mmmm"),VALUE) -> 74-101-001February | B26: =I26&IF(F26<>VALUE,TEXT(F26,"mmmm"),VALUE) -> 4-101-001February | C26: =COUNTIF($K$7:K26,K26)&K26 -> 0 | D26: =IF(MONTH(F26)<MONTH(BLN),"1"&I26,VALUE) -> 14-101-001 | F26: 46072 | G26: INV-00118 | H26: Surfing Board & Lesson | I26: 4-101-001 | J26: =IF(ISNA(VLOOKUP(I26,DAF_AKUN,2,FALSE)),"-",VLOOKUP(I26,DAF_AKUN,2,FALSE)) -> Pendapatan Usaha | M26: 3500000
A27: =IF(I27=VALUE,VALUE,COUNTIF($B$7:B27,B27))&I27&IF(F27<>VALUE,TEXT(F27,"mmmm"),VALUE) -> 11-102-001March | B27: =I27&IF(F27<>VALUE,TEXT(F27,"mmmm"),VALUE) -> 1-102-001March | C27: =COUNTIF($K$7:K27,K27)&K27 -> 0 | D27: =IF(MONTH(F27)<MONTH(BLN),"1"&I27,VALUE) -> 11-102-001 | F27: 46112 | H27: Sales Maret 2026 | I27: 1-102-001 | J27: =IF(ISNA(VLOOKUP(I27,DAF_AKUN,2,FALSE)),"-",VLOOKUP(I27,DAF_AKUN,2,FALSE)) -> Receivable - Trade | L27: =SUM(M28:M34) -> 5625000
A28: =IF(I28=VALUE,VALUE,COUNTIF($B$7:B28,B28))&I28&IF(F28<>VALUE,TEXT(F28,"mmmm"),VALUE) -> 14-101-001March | B28: =I28&IF(F28<>VALUE,TEXT(F28,"mmmm"),VALUE) -> 4-101-001March | C28: =COUNTIF($K$7:K28,K28)&K28 -> 0 | D28: =IF(MONTH(F28)<MONTH(BLN),"1"&I28,VALUE) -> 14-101-001 | F28: 46089 | G28: INV-00124 | H28: Room 3 | I28: 4-101-001 | J28: =IF(ISNA(VLOOKUP(I28,DAF_AKUN,2,FALSE)),"-",VLOOKUP(I28,DAF_AKUN,2,FALSE)) -> Pendapatan Usaha | M28: 1050000
A29: =IF(I29=VALUE,VALUE,COUNTIF($B$7:B29,B29))&I29&IF(F29<>VALUE,TEXT(F29,"mmmm"),VALUE) -> 24-101-001March | B29: =I29&IF(F29<>VALUE,TEXT(F29,"mmmm"),VALUE) -> 4-101-001March | C29: =COUNTIF($K$7:K29,K29)&K29 -> 0 | D29: =IF(MONTH(F29)<MONTH(BLN),"1"&I29,VALUE) -> 14-101-001 | F29: 46095 | G29: INV-00124 | H29: Room 2 | I29: 4-101-001 | J29: =IF(ISNA(VLOOKUP(I29,DAF_AKUN,2,FALSE)),"-",VLOOKUP(I29,DAF_AKUN,2,FALSE)) -> Pendapatan Usaha | M29: 275000
A30: =IF(I30=VALUE,VALUE,COUNTIF($B$7:B30,B30))&I30&IF(F30<>VALUE,TEXT(F30,"mmmm"),VALUE) -> 34-101-001March | B30: =I30&IF(F30<>VALUE,TEXT(F30,"mmmm"),VALUE) -> 4-101-001March | C30: =COUNTIF($K$7:K30,K30)&K30 -> 0 | D30: =IF(MONTH(F30)<MONTH(BLN),"1"&I30,VALUE) -> 14-101-001 | F30: 46101 | G30: INV-00130 | H30: Room 3 & 4 | I30: 4-101-001 | J30: =IF(ISNA(VLOOKUP(I30,DAF_AKUN,2,FALSE)),"-",VLOOKUP(I30,DAF_AKUN,2,FALSE)) -> Pendapatan Usaha | M30: 1575000
A31: =IF(I31=VALUE,VALUE,COUNTIF($B$7:B31,B31))&I31&IF(F31<>VALUE,TEXT(F31,"mmmm"),VALUE) -> 44-101-001March | B31: =I31&IF(F31<>VALUE,TEXT(F31,"mmmm"),VALUE) -> 4-101-001March | C31: =COUNTIF($K$7:K31,K31)&K31 -> 0 | D31: =IF(MONTH(F31)<MONTH(BLN),"1"&I31,VALUE) -> 14-101-001 | F31: 46101 | G31: INV-00130 | H31: Room 6 | I31: 4-101-001 | J31: =IF(ISNA(VLOOKUP(I31,DAF_AKUN,2,FALSE)),"-",VLOOKUP(I31,DAF_AKUN,2,FALSE)) -> Pendapatan Usaha | M31: 500000
A32: =IF(I32=VALUE,VALUE,COUNTIF($B$7:B32,B32))&I32&IF(F32<>VALUE,TEXT(F32,"mmmm"),VALUE) -> 54-101-001March | B32: =I32&IF(F32<>VALUE,TEXT(F32,"mmmm"),VALUE) -> 4-101-001March | C32: =COUNTIF($K$7:K32,K32)&K32 -> 0 | D32: =IF(MONTH(F32)<MONTH(BLN),"1"&I32,VALUE) -> 14-101-001 | F32: 46104 | G32: INV-00132 | H32: Room 5 | I32: 4-101-001 | J32: =IF(ISNA(VLOOKUP(I32,DAF_AKUN,2,FALSE)),"-",VLOOKUP(I32,DAF_AKUN,2,FALSE)) -> Pendapatan Usaha | M32: 275000
A33: =IF(I33=VALUE,VALUE,COUNTIF($B$7:B33,B33))&I33&IF(F33<>VALUE,TEXT(F33,"mmmm"),VALUE) -> 64-101-001March | B33: =I33&IF(F33<>VALUE,TEXT(F33,"mmmm"),VALUE) -> 4-101-001March | C33: =COUNTIF($K$7:K33,K33)&K33 -> 0 | D33: =IF(MONTH(F33)<MONTH(BLN),"1"&I33,VALUE) -> 14-101-001 | F33: 46104 | G33: INV-00131 | H33: Room 1, 4 & 5 | I33: 4-101-001 | J33: =IF(ISNA(VLOOKUP(I33,DAF_AKUN,2,FALSE)),"-",VLOOKUP(I33,DAF_AKUN,2,FALSE)) -> Pendapatan Usaha | M33: 1350000
A34: =IF(I34=VALUE,VALUE,COUNTIF($B$7:B34,B34))&I34&IF(F34<>VALUE,TEXT(F34,"mmmm"),VALUE) -> 74-101-001March | B34: =I34&IF(F34<>VALUE,TEXT(F34,"mmmm"),VALUE) -> 4-101-001March | C34: =COUNTIF($K$7:K34,K34)&K34 -> 0 | D34: =IF(MONTH(F34)<MONTH(BLN),"1"&I34,VALUE) -> 14-101-001 | F34: 46109 | G34: INV-00135 | H34: Room 3 | I34: 4-101-001 | J34: =IF(ISNA(VLOOKUP(I34,DAF_AKUN,2,FALSE)),"-",VLOOKUP(I34,DAF_AKUN,2,FALSE)) -> Pendapatan Usaha | M34: 600000
A35: =IF(I35=VALUE,VALUE,COUNTIF($B$7:B35,B35))&I35&IF(F35<>VALUE,TEXT(F35,"mmmm"),VALUE) -> 11-102-001April | B35: =I35&IF(F35<>VALUE,TEXT(F35,"mmmm"),VALUE) -> 1-102-001April | C35: =COUNTIF($K$7:K35,K35)&K35 -> 0 | D35: =IF(MONTH(F35)<MONTH(BLN),"1"&I35,VALUE) -> 11-102-001 | F35: 46113 | G35: INV-00135 | H35: Room 3 | I35: 1-102-001 | J35: =IF(ISNA(VLOOKUP(I35,DAF_AKUN,2,FALSE)),"-",VLOOKUP(I35,DAF_AKUN,2,FALSE)) -> Receivable - Trade | L35: 3850000
A36: =IF(I36=VALUE,VALUE,COUNTIF($B$7:B36,B36))&I36&IF(F36<>VALUE,TEXT(F36,"mmmm"),VALUE) -> 14-101-001April | B36: =I36&IF(F36<>VALUE,TEXT(F36,"mmmm"),VALUE) -> 4-101-001April | C36: =COUNTIF($K$7:K36,K36)&K36 -> 0 | D36: =IF(MONTH(F36)<MONTH(BLN),"1"&I36,VALUE) -> 14-101-001 | F36: 46113 | G36: INV-00135 | H36: Room 3 | I36: 4-101-001 | J36: =IF(ISNA(VLOOKUP(I36,DAF_AKUN,2,FALSE)),"-",VLOOKUP(I36,DAF_AKUN,2,FALSE)) -> Pendapatan Usaha | M36: 3850000
A37: =IF(I37=VALUE,VALUE,COUNTIF($B$7:B37,B37))&I37&IF(F37<>VALUE,TEXT(F37,"mmmm"),VALUE) -> 11-102-001June | B37: =I37&IF(F37<>VALUE,TEXT(F37,"mmmm"),VALUE) -> 1-102-001June | C37: =COUNTIF($K$7:K37,K37)&K37 -> 0 | D37: =IF(MONTH(F37)<MONTH(BLN),"1"&I37,VALUE) -> 11-102-001 | F37: 46203 | H37: Sales Juni 2026 | I37: 1-102-001 | J37: =IF(ISNA(VLOOKUP(I37,DAF_AKUN,2,FALSE)),"-",VLOOKUP(I37,DAF_AKUN,2,FALSE)) -> Receivable - Trade | L37: =SUM(M38:M48) -> 23140000
A38: =IF(I38=VALUE,VALUE,COUNTIF($B$7:B38,B38))&I38&IF(F38<>VALUE,TEXT(F38,"mmmm"),VALUE) -> 14-101-001June | B38: =I38&IF(F38<>VALUE,TEXT(F38,"mmmm"),VALUE) -> 4-101-001June | C38: =COUNTIF($K$7:K38,K38)&K38 -> 0 | D38: =IF(MONTH(F38)<MONTH(BLN),"1"&I38,VALUE) -> 14-101-001 | F38: 46186 | G38: INV-00184 | H38: Room 1 | I38: 4-101-001 | J38: =IF(ISNA(VLOOKUP(I38,DAF_AKUN,2,FALSE)),"-",VLOOKUP(I38,DAF_AKUN,2,FALSE)) -> Pendapatan Usaha | M38: 2250000
A39: =IF(I39=VALUE,VALUE,COUNTIF($B$7:B39,B39))&I39&IF(F39<>VALUE,TEXT(F39,"mmmm"),VALUE) -> 24-101-001June | B39: =I39&IF(F39<>VALUE,TEXT(F39,"mmmm"),VALUE) -> 4-101-001June | C39: =COUNTIF($K$7:K39,K39)&K39 -> 0 | D39: =IF(MONTH(F39)<MONTH(BLN),"1"&I39,VALUE) -> 14-101-001 | F39: 46187 | G39: INV-00186 | H39: Room 2 | I39: 4-101-001 | J39: =IF(ISNA(VLOOKUP(I39,DAF_AKUN,2,FALSE)),"-",VLOOKUP(I39,DAF_AKUN,2,FALSE)) -> Pendapatan Usaha | M39: 1100000
A40: =IF(I40=VALUE,VALUE,COUNTIF($B$7:B40,B40))&I40&IF(F40<>VALUE,TEXT(F40,"mmmm"),VALUE) -> 34-101-001June | B40: =I40&IF(F40<>VALUE,TEXT(F40,"mmmm"),VALUE) -> 4-101-001June | C40: =COUNTIF($K$7:K40,K40)&K40 -> 0 | D40: =IF(MONTH(F40)<MONTH(BLN),"1"&I40,VALUE) -> 14-101-001 | F40: 46187 | G40: INV-00185 | H40: Room 3 | I40: 4-101-001 | J40: =IF(ISNA(VLOOKUP(I40,DAF_AKUN,2,FALSE)),"-",VLOOKUP(I40,DAF_AKUN,2,FALSE)) -> Pendapatan Usaha | M40: 700000
A41: =IF(I41=VALUE,VALUE,COUNTIF($B$7:B41,B41))&I41&IF(F41<>VALUE,TEXT(F41,"mmmm"),VALUE) -> 44-101-001June | B41: =I41&IF(F41<>VALUE,TEXT(F41,"mmmm"),VALUE) -> 4-101-001June | C41: =COUNTIF($K$7:K41,K41)&K41 -> 0 | D41: =IF(MONTH(F41)<MONTH(BLN),"1"&I41,VALUE) -> 14-101-001 | F41: 46188 | G41: INV-00189 | H41: Room 4 | I41: 4-101-001 | J41: =IF(ISNA(VLOOKUP(I41,DAF_AKUN,2,FALSE)),"-",VLOOKUP(I41,DAF_AKUN,2,FALSE)) -> Pendapatan Usaha | M41: 600000
A42: =IF(I42=VALUE,VALUE,COUNTIF($B$7:B42,B42))&I42&IF(F42<>VALUE,TEXT(F42,"mmmm"),VALUE) -> 54-101-001June | B42: =I42&IF(F42<>VALUE,TEXT(F42,"mmmm"),VALUE) -> 4-101-001June | C42: =COUNTIF($K$7:K42,K42)&K42 -> 0 | D42: =IF(MONTH(F42)<MONTH(BLN),"1"&I42,VALUE) -> 14-101-001 | F42: 46189 | G42: INV-00190 | H42: Room 3, Pick Up Jkt | I42: 4-101-001 | J42: =IF(ISNA(VLOOKUP(I42,DAF_AKUN,2,FALSE)),"-",VLOOKUP(I42,DAF_AKUN,2,FALSE)) -> Pendapatan Usaha | M42: 3650000
A43: =IF(I43=VALUE,VALUE,COUNTIF($B$7:B43,B43))&I43&IF(F43<>VALUE,TEXT(F43,"mmmm"),VALUE) -> 64-101-001June | B43: =I43&IF(F43<>VALUE,TEXT(F43,"mmmm"),VALUE) -> 4-101-001June | C43: =COUNTIF($K$7:K43,K43)&K43 -> 0 | D43: =IF(MONTH(F43)<MONTH(BLN),"1"&I43,VALUE) -> 14-101-001 | F43: 46190 | G43: INV-00193 | H43: Room 4 | I43: 4-101-001 | J43: =IF(ISNA(VLOOKUP(I43,DAF_AKUN,2,FALSE)),"-",VLOOKUP(I43,DAF_AKUN,2,FALSE)) -> Pendapatan Usaha | M43: 1500000
A44: =IF(I44=VALUE,VALUE,COUNTIF($B$7:B44,B44))&I44&IF(F44<>VALUE,TEXT(F44,"mmmm"),VALUE) -> 74-101-001June | B44: =I44&IF(F44<>VALUE,TEXT(F44,"mmmm"),VALUE) -> 4-101-001June | C44: =COUNTIF($K$7:K44,K44)&K44 -> 0 | D44: =IF(MONTH(F44)<MONTH(BLN),"1"&I44,VALUE) -> 14-101-001 | F44: 46190 | G44: INV-00192 | H44: Room 2 | I44: 4-101-001 | J44: =IF(ISNA(VLOOKUP(I44,DAF_AKUN,2,FALSE)),"-",VLOOKUP(I44,DAF_AKUN,2,FALSE)) -> Pendapatan Usaha | M44: 900000
A45: =IF(I45=VALUE,VALUE,COUNTIF($B$7:B45,B45))&I45&IF(F45<>VALUE,TEXT(F45,"mmmm"),VALUE) -> 84-101-001June | B45: =I45&IF(F45<>VALUE,TEXT(F45,"mmmm"),VALUE) -> 4-101-001June | C45: =COUNTIF($K$7:K45,K45)&K45 -> 0 | D45: =IF(MONTH(F45)<MONTH(BLN),"1"&I45,VALUE) -> 14-101-001 | F45: 46195 | G45: INV-00197 | H45: Room Arya's | I45: 4-101-001 | J45: =IF(ISNA(VLOOKUP(I45,DAF_AKUN,2,FALSE)),"-",VLOOKUP(I45,DAF_AKUN,2,FALSE)) -> Pendapatan Usaha | M45: 2000000
A46: =IF(I46=VALUE,VALUE,COUNTIF($B$7:B46,B46))&I46&IF(F46<>VALUE,TEXT(F46,"mmmm"),VALUE) -> 94-101-001June | B46: =I46&IF(F46<>VALUE,TEXT(F46,"mmmm"),VALUE) -> 4-101-001June | C46: =COUNTIF($K$7:K46,K46)&K46 -> 0 | D46: =IF(MONTH(F46)<MONTH(BLN),"1"&I46,VALUE) -> 14-101-001 | F46: 46197 | G46: INV-00198 | H46: Room 3 & 4 | I46: 4-101-001 | J46: =IF(ISNA(VLOOKUP(I46,DAF_AKUN,2,FALSE)),"-",VLOOKUP(I46,DAF_AKUN,2,FALSE)) -> Pendapatan Usaha | M46: 2940000
A47: =IF(I47=VALUE,VALUE,COUNTIF($B$7:B47,B47))&I47&IF(F47<>VALUE,TEXT(F47,"mmmm"),VALUE) -> 104-101-001June | B47: =I47&IF(F47<>VALUE,TEXT(F47,"mmmm"),VALUE) -> 4-101-001June | C47: =COUNTIF($K$7:K47,K47)&K47 -> 0 | D47: =IF(MONTH(F47)<MONTH(BLN),"1"&I47,VALUE) -> 14-101-001 | F47: 46198 | G47: INV-00199 | H47: Room Arya's (extend) & Surfing Lesson | I47: 4-101-001 | J47: =IF(ISNA(VLOOKUP(I47,DAF_AKUN,2,FALSE)),"-",VLOOKUP(I47,DAF_AKUN,2,FALSE)) -> Pendapatan Usaha | M47: 2500000
A48: =IF(I48=VALUE,VALUE,COUNTIF($B$7:B48,B48))&I48&IF(F48<>VALUE,TEXT(F48,"mmmm"),VALUE) -> 114-101-001June | B48: =I48&IF(F48<>VALUE,TEXT(F48,"mmmm"),VALUE) -> 4-101-001June | C48: =COUNTIF($K$7:K48,K48)&K48 -> 0 | D48: =IF(MONTH(F48)<MONTH(BLN),"1"&I48,VALUE) -> 14-101-001 | F48: 46202 | G48: INV-001103 | H48: Room Arya's & Surfing Lesson | I48: 4-101-001 | J48: =IF(ISNA(VLOOKUP(I48,DAF_AKUN,2,FALSE)),"-",VLOOKUP(I48,DAF_AKUN,2,FALSE)) -> Pendapatan Usaha | M48: 5000000
A49: =IF(I49=VALUE,VALUE,COUNTIF($B$7:B49,B49))&I49&IF(F49<>VALUE,TEXT(F49,"mmmm"),VALUE) -> 11-102-001July | B49: =I49&IF(F49<>VALUE,TEXT(F49,"mmmm"),VALUE) -> 1-102-001July | C49: =COUNTIF($K$7:K49,K49)&K49 -> 0 | D49: =IF(MONTH(F49)<MONTH(BLN),"1"&I49,VALUE) -> 0 | F49: 46234 | H49: Sales Juli 2026 | I49: 1-102-001 | J49: =IF(ISNA(VLOOKUP(I49,DAF_AKUN,2,FALSE)),"-",VLOOKUP(I49,DAF_AKUN,2,FALSE)) -> Receivable - Trade | L49: =SUM(M50:M66) -> 31074000
A50: =IF(I50=VALUE,VALUE,COUNTIF($B$7:B50,B50))&I50&IF(F50<>VALUE,TEXT(F50,"mmmm"),VALUE) -> 14-101-001July | B50: =I50&IF(F50<>VALUE,TEXT(F50,"mmmm"),VALUE) -> 4-101-001July | C50: =COUNTIF($K$7:K50,K50)&K50 -> 0 | D50: =IF(MONTH(F50)<MONTH(BLN),"1"&I50,VALUE) -> 0 | F50: 46204 | G50: INV-001104 | H50: Surfing Lesson incl photo vidio | I50: 4-101-001 | J50: =IF(ISNA(VLOOKUP(I50,DAF_AKUN,2,FALSE)),"-",VLOOKUP(I50,DAF_AKUN,2,FALSE)) -> Pendapatan Usaha | M50: 600000
A51: =IF(I51=VALUE,VALUE,COUNTIF($B$7:B51,B51))&I51&IF(F51<>VALUE,TEXT(F51,"mmmm"),VALUE) -> 24-101-001July | B51: =I51&IF(F51<>VALUE,TEXT(F51,"mmmm"),VALUE) -> 4-101-001July | C51: =COUNTIF($K$7:K51,K51)&K51 -> 0 | D51: =IF(MONTH(F51)<MONTH(BLN),"1"&I51,VALUE) -> 0 | F51: 46207 | G51: INV-001105 | H51: Room Arya's | I51: 4-101-001 | J51: =IF(ISNA(VLOOKUP(I51,DAF_AKUN,2,FALSE)),"-",VLOOKUP(I51,DAF_AKUN,2,FALSE)) -> Pendapatan Usaha | M51: 2800000
A52: =IF(I52=VALUE,VALUE,COUNTIF($B$7:B52,B52))&I52&IF(F52<>VALUE,TEXT(F52,"mmmm"),VALUE) -> 34-101-001July | B52: =I52&IF(F52<>VALUE,TEXT(F52,"mmmm"),VALUE) -> 4-101-001July | C52: =COUNTIF($K$7:K52,K52)&K52 -> 0 | D52: =IF(MONTH(F52)<MONTH(BLN),"1"&I52,VALUE) -> 0 | F52: 46207 | G52: INV-001105 | H52: Room 1 | I52: 4-101-001 | J52: =IF(ISNA(VLOOKUP(I52,DAF_AKUN,2,FALSE)),"-",VLOOKUP(I52,DAF_AKUN,2,FALSE)) -> Pendapatan Usaha | M52: 600000
A53: =IF(I53=VALUE,VALUE,COUNTIF($B$7:B53,B53))&I53&IF(F53<>VALUE,TEXT(F53,"mmmm"),VALUE) -> 44-101-001July | B53: =I53&IF(F53<>VALUE,TEXT(F53,"mmmm"),VALUE) -> 4-101-001July | C53: =COUNTIF($K$7:K53,K53)&K53 -> 0 | D53: =IF(MONTH(F53)<MONTH(BLN),"1"&I53,VALUE) -> 0 | F53: 46209 | G53: INV-001106 | H53: Meals | I53: 4-101-001 | J53: =IF(ISNA(VLOOKUP(I53,DAF_AKUN,2,FALSE)),"-",VLOOKUP(I53,DAF_AKUN,2,FALSE)) -> Pendapatan Usaha | M53: 75000
A54: =IF(I54=VALUE,VALUE,COUNTIF($B$7:B54,B54))&I54&IF(F54<>VALUE,TEXT(F54,"mmmm"),VALUE) -> 54-101-001July | B54: =I54&IF(F54<>VALUE,TEXT(F54,"mmmm"),VALUE) -> 4-101-001July | C54: =COUNTIF($K$7:K54,K54)&K54 -> 0 | D54: =IF(MONTH(F54)<MONTH(BLN),"1"&I54,VALUE) -> 0 | F54: 46209 | G54: INV-001107 | H54: Meals | I54: 4-101-001 | J54: =IF(ISNA(VLOOKUP(I54,DAF_AKUN,2,FALSE)),"-",VLOOKUP(I54,DAF_AKUN,2,FALSE)) -> Pendapatan Usaha | M54: 190000
A55: =IF(I55=VALUE,VALUE,COUNTIF($B$7:B55,B55))&I55&IF(F55<>VALUE,TEXT(F55,"mmmm"),VALUE) -> 64-101-001July | B55: =I55&IF(F55<>VALUE,TEXT(F55,"mmmm"),VALUE) -> 4-101-001July | C55: =COUNTIF($K$7:K55,K55)&K55 -> 0 | D55: =IF(MONTH(F55)<MONTH(BLN),"1"&I55,VALUE) -> 0 | F55: 46210 | G55: INV-001111 | H55: Pick up Cimaja-Sukabumi, Meals | I55: 4-101-001 | J55: =IF(ISNA(VLOOKUP(I55,DAF_AKUN,2,FALSE)),"-",VLOOKUP(I55,DAF_AKUN,2,FALSE)) -> Pendapatan Usaha | M55: 1630000
A56: =IF(I56=VALUE,VALUE,COUNTIF($B$7:B56,B56))&I56&IF(F56<>VALUE,TEXT(F56,"mmmm"),VALUE) -> 74-101-001July | B56: =I56&IF(F56<>VALUE,TEXT(F56,"mmmm"),VALUE) -> 4-101-001July | C56: =COUNTIF($K$7:K56,K56)&K56 -> 0 | D56: =IF(MONTH(F56)<MONTH(BLN),"1"&I56,VALUE) -> 0 | F56: 46210 | G56: INV-001110 | H56: Meals | I56: 4-101-001 | J56: =IF(ISNA(VLOOKUP(I56,DAF_AKUN,2,FALSE)),"-",VLOOKUP(I56,DAF_AKUN,2,FALSE)) -> Pendapatan Usaha | M56: 170000
A57: =IF(I57=VALUE,VALUE,COUNTIF($B$7:B57,B57))&I57&IF(F57<>VALUE,TEXT(F57,"mmmm"),VALUE) -> 84-101-001July | B57: =I57&IF(F57<>VALUE,TEXT(F57,"mmmm"),VALUE) -> 4-101-001July | C57: =COUNTIF($K$7:K57,K57)&K57 -> 0 | D57: =IF(MONTH(F57)<MONTH(BLN),"1"&I57,VALUE) -> 0 | F57: 46210 | G57: INV-011012 | H57: Meals | I57: 4-101-001 | J57: =IF(ISNA(VLOOKUP(I57,DAF_AKUN,2,FALSE)),"-",VLOOKUP(I57,DAF_AKUN,2,FALSE)) -> Pendapatan Usaha | M57: 40000
A58: =IF(I58=VALUE,VALUE,COUNTIF($B$7:B61,B58))&I58&IF(F58<>VALUE,TEXT(F58,"mmmm"),VALUE) -> 124-101-001July | B58: =I58&IF(F58<>VALUE,TEXT(F58,"mmmm"),VALUE) -> 4-101-001July | C58: =COUNTIF($K$7:K61,K58)&K58 -> 0 | D58: =IF(MONTH(F58)<MONTH(BLN),"1"&I58,VALUE) -> 0 | F58: 46210 | G58: INV-01109 | H58: Surf & Adventure Package | I58: 4-101-001 | J58: =IF(ISNA(VLOOKUP(I58,DAF_AKUN,2,FALSE)),"-",VLOOKUP(I58,DAF_AKUN,2,FALSE)) -> Pendapatan Usaha | M58: 12250000
A59: =IF(I59=VALUE,VALUE,COUNTIF($B$7:B59,B59))&I59&IF(F59<>VALUE,TEXT(F59,"mmmm"),VALUE) -> 104-101-001July | B59: =I59&IF(F59<>VALUE,TEXT(F59,"mmmm"),VALUE) -> 4-101-001July | C59: =COUNTIF($K$7:K59,K59)&K59 -> 0 | D59: =IF(MONTH(F59)<MONTH(BLN),"1"&I59,VALUE) -> 0 | F59: 46216 | G59: INV-01101e | H59: Surfing Board | I59: 4-101-001 | J59: =IF(ISNA(VLOOKUP(I59,DAF_AKUN,2,FALSE)),"-",VLOOKUP(I59,DAF_AKUN,2,FALSE)) -> Pendapatan Usaha | M59: 150000
A60: =IF(I60=VALUE,VALUE,COUNTIF($B$7:B60,B60))&I60&IF(F60<>VALUE,TEXT(F60,"mmmm"),VALUE) -> 114-101-001July | B60: =I60&IF(F60<>VALUE,TEXT(F60,"mmmm"),VALUE) -> 4-101-001July | C60: =COUNTIF($K$7:K60,K60)&K60 -> 0 | D60: =IF(MONTH(F60)<MONTH(BLN),"1"&I60,VALUE) -> 0 | F60: 46217 | G60: INV-011014 | H60: Meals | I60: 4-101-001 | J60: =IF(ISNA(VLOOKUP(I60,DAF_AKUN,2,FALSE)),"-",VLOOKUP(I60,DAF_AKUN,2,FALSE)) -> Pendapatan Usaha | M60: 145000
A61: =IF(I61=VALUE,VALUE,COUNTIF($B$7:B61,B61))&I61&IF(F61<>VALUE,TEXT(F61,"mmmm"),VALUE) -> 124-101-001July | B61: =I61&IF(F61<>VALUE,TEXT(F61,"mmmm"),VALUE) -> 4-101-001July | C61: =COUNTIF($K$7:K61,K61)&K61 -> 0 | D61: =IF(MONTH(F61)<MONTH(BLN),"1"&I61,VALUE) -> 0 | F61: 46220 | G61: INV-011016 | H61: Surfing Lesson | I61: 4-101-001 | J61: =IF(ISNA(VLOOKUP(I61,DAF_AKUN,2,FALSE)),"-",VLOOKUP(I61,DAF_AKUN,2,FALSE)) -> Pendapatan Usaha | M61: 550000
A62: =IF(I62=VALUE,VALUE,COUNTIF($B$7:B62,B62))&I62&IF(F62<>VALUE,TEXT(F62,"mmmm"),VALUE) -> 134-101-001July | B62: =I62&IF(F62<>VALUE,TEXT(F62,"mmmm"),VALUE) -> 4-101-001July | C62: =COUNTIF($K$7:K62,K62)&K62 -> 0 | D62: =IF(MONTH(F62)<MONTH(BLN),"1"&I62,VALUE) -> 0 | F62: 46223 | G62: INV-011018 | H62: Room Paviliun | I62: 4-101-001 | J62: =IF(ISNA(VLOOKUP(I62,DAF_AKUN,2,FALSE)),"-",VLOOKUP(I62,DAF_AKUN,2,FALSE)) -> Pendapatan Usaha | M62: 1200000
A63: =IF(I63=VALUE,VALUE,COUNTIF($B$7:B63,B63))&I63&IF(F63<>VALUE,TEXT(F63,"mmmm"),VALUE) -> 144-101-001July | B63: =I63&IF(F63<>VALUE,TEXT(F63,"mmmm"),VALUE) -> 4-101-001July | C63: =COUNTIF($K$7:K63,K63)&K63 -> 0 | D63: =IF(MONTH(F63)<MONTH(BLN),"1"&I63,VALUE) -> 0 | F63: 46226 | G63: INV-011019 | H63: Room Paviliun | I63: 4-101-001 | J63: =IF(ISNA(VLOOKUP(I63,DAF_AKUN,2,FALSE)),"-",VLOOKUP(I63,DAF_AKUN,2,FALSE)) -> Pendapatan Usaha | M63: 600000
A64: =IF(I64=VALUE,VALUE,COUNTIF($B$7:B64,B64))&I64&IF(F64<>VALUE,TEXT(F64,"mmmm"),VALUE) -> 154-101-001July | B64: =I64&IF(F64<>VALUE,TEXT(F64,"mmmm"),VALUE) -> 4-101-001July | C64: =COUNTIF($K$7:K64,K64)&K64 -> 0 | D64: =IF(MONTH(F64)<MONTH(BLN),"1"&I64,VALUE) -> 0 | F64: 46228 | G64: INV-011020 | H64: Room 2, Scooter | I64: 4-101-001 | J64: =IF(ISNA(VLOOKUP(I64,DAF_AKUN,2,FALSE)),"-",VLOOKUP(I64,DAF_AKUN,2,FALSE)) -> Pendapatan Usaha | M64: 1920000
A65: =IF(I65=VALUE,VALUE,COUNTIF($B$7:B65,B65))&I65&IF(F65<>VALUE,TEXT(F65,"mmmm"),VALUE) -> 164-101-001July | B65: =I65&IF(F65<>VALUE,TEXT(F65,"mmmm"),VALUE) -> 4-101-001July | C65: =COUNTIF($K$7:K65,K65)&K65 -> 0 | D65: =IF(MONTH(F65)<MONTH(BLN),"1"&I65,VALUE) -> 0 | F65: 46230 | G65: INV-011021 | H65: 3D2N Surf Package | I65: 4-101-001 | J65: =IF(ISNA(VLOOKUP(I65,DAF_AKUN,2,FALSE)),"-",VLOOKUP(I65,DAF_AKUN,2,FALSE)) -> Pendapatan Usaha | M65: 2180000
A66: =IF(I66=VALUE,VALUE,COUNTIF($B$7:B66,B66))&I66&IF(F66<>VALUE,TEXT(F66,"mmmm"),VALUE) -> 174-101-001July | B66: =I66&IF(F66<>VALUE,TEXT(F66,"mmmm"),VALUE) -> 4-101-001July | C66: =COUNTIF($K$7:K66,K66)&K66 -> 0 | D66: =IF(MONTH(F66)<MONTH(BLN),"1"&I66,VALUE) -> 0 | F66: 46232 | G66: INV-011023 | H66: Room Paviliun & Room 1 | I66: 4-101-001 | J66: =IF(ISNA(VLOOKUP(I66,DAF_AKUN,2,FALSE)),"-",VLOOKUP(I66,DAF_AKUN,2,FALSE)) -> Pendapatan Usaha | M66: 5974000
A67: =IF(I67=VALUE,VALUE,COUNTIF($B$7:B67,B67))&I67&IF(F67<>VALUE,TEXT(F67,"mmmm"),VALUE) -> 00 | B67: =I67&IF(F67<>VALUE,TEXT(F67,"mmmm"),VALUE) -> 0 | C67: =COUNTIF($K$7:K67,K67)&K67 -> 0 | D67: =IF(MONTH(F67)<MONTH(BLN),"1"&I67,VALUE) -> 1 | J67: =IF(ISNA(VLOOKUP(I67,DAF_AKUN,2,FALSE)),"-",VLOOKUP(I67,DAF_AKUN,2,FALSE)) -> -
A68: =IF(I68=VALUE,VALUE,COUNTIF($B$7:B68,B68))&I68&IF(F68<>VALUE,TEXT(F68,"mmmm"),VALUE) -> 15-101-003January | B68: =I68&IF(F68<>VALUE,TEXT(F68,"mmmm"),VALUE) -> 5-101-003January | C68: =COUNTIF($K$7:K68,K68)&K68 -> 0 | D68: =IF(MONTH(F68)<MONTH(BLN),"1"&I68,VALUE) -> 15-101-003 | F68: 46053 | G68: 1648205606 | H68: Biaya Layanan pembayaran | I68: 5-101-003 | J68: =IF(ISNA(VLOOKUP(I68,DAF_AKUN,2,FALSE)),"-",VLOOKUP(I68,DAF_AKUN,2,FALSE)) -> Transaction Cost | L68: 706193
A69: =IF(I69=VALUE,VALUE,COUNTIF($B$7:B69,B69))&I69&IF(F69<>VALUE,TEXT(F69,"mmmm"),VALUE) -> 25-101-003January | B69: =I69&IF(F69<>VALUE,TEXT(F69,"mmmm"),VALUE) -> 5-101-003January | C69: =COUNTIF($K$7:K69,K69)&K69 -> 0 | D69: =IF(MONTH(F69)<MONTH(BLN),"1"&I69,VALUE) -> 15-101-003 | F69: 46053 | G69: 1648205606 | H69: Biaya Reservasi | I69: 5-101-003 | J69: =IF(ISNA(VLOOKUP(I69,DAF_AKUN,2,FALSE)),"-",VLOOKUP(I69,DAF_AKUN,2,FALSE)) -> Transaction Cost | L69: 5526720
A70: =IF(I70=VALUE,VALUE,COUNTIF($B$7:B70,B70))&I70&IF(F70<>VALUE,TEXT(F70,"mmmm"),VALUE) -> 35-101-003January | B70: =I70&IF(F70<>VALUE,TEXT(F70,"mmmm"),VALUE) -> 5-101-003January | C70: =COUNTIF($K$7:K70,K70)&K70 -> 0 | D70: =IF(MONTH(F70)<MONTH(BLN),"1"&I70,VALUE) -> 15-101-003 | F70: 46053 | G70: 1648205606 | H70: Biaya PPN | I70: 5-101-003 | J70: =IF(ISNA(VLOOKUP(I70,DAF_AKUN,2,FALSE)),"-",VLOOKUP(I70,DAF_AKUN,2,FALSE)) -> Transaction Cost | L70: 685620
A71: =IF(I71=VALUE,VALUE,COUNTIF($B$7:B71,B71))&I71&IF(F71<>VALUE,TEXT(F71,"mmmm"),VALUE) -> 21-102-001January | B71: =I71&IF(F71<>VALUE,TEXT(F71,"mmmm"),VALUE) -> 1-102-001January | C71: =COUNTIF($K$7:K71,K71)&K71 -> 0 | D71: =IF(MONTH(F71)<MONTH(BLN),"1"&I71,VALUE) -> 11-102-001 | F71: 46053 | G71: 1648205606 | H71: Sales from Booking.com | I71: 1-102-001 | J71: =IF(ISNA(VLOOKUP(I71,DAF_AKUN,2,FALSE)),"-",VLOOKUP(I71,DAF_AKUN,2,FALSE)) -> Receivable - Trade | L71: =M72-L68-L69-L70 -> 23785467
A72: =IF(I72=VALUE,VALUE,COUNTIF($B$7:B72,B72))&I72&IF(F72<>VALUE,TEXT(F72,"mmmm"),VALUE) -> 104-101-001January | B72: =I72&IF(F72<>VALUE,TEXT(F72,"mmmm"),VALUE) -> 4-101-001January | C72: =COUNTIF($K$7:K72,K72)&K72 -> 0 | D72: =IF(MONTH(F72)<MONTH(BLN),"1"&I72,VALUE) -> 14-101-001 | F72: 46053 | G72: 1648205606 | H72: Sales from Booking.com | I72: 4-101-001 | J72: =IF(ISNA(VLOOKUP(I72,DAF_AKUN,2,FALSE)),"-",VLOOKUP(I72,DAF_AKUN,2,FALSE)) -> Pendapatan Usaha | M72: 30704000
A73: =IF(I73=VALUE,VALUE,COUNTIF($B$7:B73,B73))&I73&IF(F73<>VALUE,TEXT(F73,"mmmm"),VALUE) -> 00 | B73: =I73&IF(F73<>VALUE,TEXT(F73,"mmmm"),VALUE) -> 0 | C73: =COUNTIF($K$7:K73,K73)&K73 -> 0 | D73: =IF(MONTH(F73)<MONTH(BLN),"1"&I73,VALUE) -> 1 | J73: =IF(ISNA(VLOOKUP(I73,DAF_AKUN,2,FALSE)),"-",VLOOKUP(I73,DAF_AKUN,2,FALSE)) -> -
A74: =IF(I74=VALUE,VALUE,COUNTIF($B$7:B74,B74))&I74&IF(F74<>VALUE,TEXT(F74,"mmmm"),VALUE) -> 15-101-003February | B74: =I74&IF(F74<>VALUE,TEXT(F74,"mmmm"),VALUE) -> 5-101-003February | C74: =COUNTIF($K$7:K74,K74)&K74 -> 0 | D74: =IF(MONTH(F74)<MONTH(BLN),"1"&I74,VALUE) -> 15-101-003 | F74: 46081 | G74: 1649792884 | H74: Biaya Layanan pembayaran | I74: 5-101-003 | J74: =IF(ISNA(VLOOKUP(I74,DAF_AKUN,2,FALSE)),"-",VLOOKUP(I74,DAF_AKUN,2,FALSE)) -> Transaction Cost | L74: 529868
A75: =IF(I75=VALUE,VALUE,COUNTIF($B$7:B75,B75))&I75&IF(F75<>VALUE,TEXT(F75,"mmmm"),VALUE) -> 25-101-003February | B75: =I75&IF(F75<>VALUE,TEXT(F75,"mmmm"),VALUE) -> 5-101-003February | C75: =COUNTIF($K$7:K75,K75)&K75 -> 0 | D75: =IF(MONTH(F75)<MONTH(BLN),"1"&I75,VALUE) -> 15-101-003 | F75: 46081 | G75: 1649792884 | H75: Biaya Reservasi | I75: 5-101-003 | J75: =IF(ISNA(VLOOKUP(I75,DAF_AKUN,2,FALSE)),"-",VLOOKUP(I75,DAF_AKUN,2,FALSE)) -> Transaction Cost | L75: 4146795
A76: =IF(I76=VALUE,VALUE,COUNTIF($B$7:B76,B76))&I76&IF(F76<>VALUE,TEXT(F76,"mmmm"),VALUE) -> 35-101-003February | B76: =I76&IF(F76<>VALUE,TEXT(F76,"mmmm"),VALUE) -> 5-101-003February | C76: =COUNTIF($K$7:K76,K76)&K76 -> 0 | D76: =IF(MONTH(F76)<MONTH(BLN),"1"&I76,VALUE) -> 15-101-003 | F76: 46081 | G76: 1649792884 | H76: Biaya PPN | I76: 5-101-003 | J76: =IF(ISNA(VLOOKUP(I76,DAF_AKUN,2,FALSE)),"-",VLOOKUP(I76,DAF_AKUN,2,FALSE)) -> Transaction Cost | L76: 514432
A77: =IF(I77=VALUE,VALUE,COUNTIF($B$7:B77,B77))&I77&IF(F77<>VALUE,TEXT(F77,"mmmm"),VALUE) -> 21-102-001February | B77: =I77&IF(F77<>VALUE,TEXT(F77,"mmmm"),VALUE) -> 1-102-001February | C77: =COUNTIF($K$7:K77,K77)&K77 -> 0 | D77: =IF(MONTH(F77)<MONTH(BLN),"1"&I77,VALUE) -> 11-102-001 | F77: 46081 | G77: 1649792884 | H77: Sales from Booking.com | I77: 1-102-001 | J77: =IF(ISNA(VLOOKUP(I77,DAF_AKUN,2,FALSE)),"-",VLOOKUP(I77,DAF_AKUN,2,FALSE)) -> Receivable - Trade | L77: =M78-L74-L75-L76 -> 17846655
A78: =IF(I78=VALUE,VALUE,COUNTIF($B$7:B78,B78))&I78&IF(F78<>VALUE,TEXT(F78,"mmmm"),VALUE) -> 84-101-001February | B78: =I78&IF(F78<>VALUE,TEXT(F78,"mmmm"),VALUE) -> 4-101-001February | C78: =COUNTIF($K$7:K78,K78)&K78 -> 0 | D78: =IF(MONTH(F78)<MONTH(BLN),"1"&I78,VALUE) -> 14-101-001 | F78: 46081 | G78: 1649792884 | H78: Sales from Booking.com | I78: 4-101-001 | J78: =IF(ISNA(VLOOKUP(I78,DAF_AKUN,2,FALSE)),"-",VLOOKUP(I78,DAF_AKUN,2,FALSE)) -> Pendapatan Usaha | M78: 23037750
A79: =IF(I79=VALUE,VALUE,COUNTIF($B$7:B79,B79))&I79&IF(F79<>VALUE,TEXT(F79,"mmmm"),VALUE) -> 00 | B79: =I79&IF(F79<>VALUE,TEXT(F79,"mmmm"),VALUE) -> 0 | C79: =COUNTIF($K$7:K79,K79)&K79 -> 0 | D79: =IF(MONTH(F79)<MONTH(BLN),"1"&I79,VALUE) -> 1 | J79: =IF(ISNA(VLOOKUP(I79,DAF_AKUN,2,FALSE)),"-",VLOOKUP(I79,DAF_AKUN,2,FALSE)) -> -
A80: =IF(I80=VALUE,VALUE,COUNTIF($B$7:B80,B80))&I80&IF(F80<>VALUE,TEXT(F80,"mmmm"),VALUE) -> 15-101-003March | B80: =I80&IF(F80<>VALUE,TEXT(F80,"mmmm"),VALUE) -> 5-101-003March | C80: =COUNTIF($K$7:K80,K80)&K80 -> 0 | D80: =IF(MONTH(F80)<MONTH(BLN),"1"&I80,VALUE) -> 15-101-003 | F80: 46112 | G80: 1651102412 | H80: Biaya Layanan pembayaran | I80: 5-101-003 | J80: =IF(ISNA(VLOOKUP(I80,DAF_AKUN,2,FALSE)),"-",VLOOKUP(I80,DAF_AKUN,2,FALSE)) -> Transaction Cost | L80: 670056
A81: =IF(I81=VALUE,VALUE,COUNTIF($B$7:B81,B81))&I81&IF(F81<>VALUE,TEXT(F81,"mmmm"),VALUE) -> 25-101-003March | B81: =I81&IF(F81<>VALUE,TEXT(F81,"mmmm"),VALUE) -> 5-101-003March | C81: =COUNTIF($K$7:K81,K81)&K81 -> 0 | D81: =IF(MONTH(F81)<MONTH(BLN),"1"&I81,VALUE) -> 15-101-003 | F81: 46112 | G81: 1651102412 | H81: Biaya Reservasi | I81: 5-101-003 | J81: =IF(ISNA(VLOOKUP(I81,DAF_AKUN,2,FALSE)),"-",VLOOKUP(I81,DAF_AKUN,2,FALSE)) -> Transaction Cost | L81: 5243922
A82: =IF(I82=VALUE,VALUE,COUNTIF($B$7:B82,B82))&I82&IF(F82<>VALUE,TEXT(F82,"mmmm"),VALUE) -> 35-101-003March | B82: =I82&IF(F82<>VALUE,TEXT(F82,"mmmm"),VALUE) -> 5-101-003March | C82: =COUNTIF($K$7:K82,K82)&K82 -> 0 | D82: =IF(MONTH(F82)<MONTH(BLN),"1"&I82,VALUE) -> 15-101-003 | F82: 46112 | G82: 1651102412 | H82: Biaya PPN | I82: 5-101-003 | J82: =IF(ISNA(VLOOKUP(I82,DAF_AKUN,2,FALSE)),"-",VLOOKUP(I82,DAF_AKUN,2,FALSE)) -> Transaction Cost | L82: 650540
A83: =IF(I83=VALUE,VALUE,COUNTIF($B$7:B83,B83))&I83&IF(F83<>VALUE,TEXT(F83,"mmmm"),VALUE) -> 21-102-001March | B83: =I83&IF(F83<>VALUE,TEXT(F83,"mmmm"),VALUE) -> 1-102-001March | C83: =COUNTIF($K$7:K83,K83)&K83 -> 0 | D83: =IF(MONTH(F83)<MONTH(BLN),"1"&I83,VALUE) -> 11-102-001 | F83: 46112 | G83: 1651102412 | H83: Sales from Booking.com | I83: 1-102-001 | J83: =IF(ISNA(VLOOKUP(I83,DAF_AKUN,2,FALSE)),"-",VLOOKUP(I83,DAF_AKUN,2,FALSE)) -> Receivable - Trade | L83: =M84-L80-L81-L82 -> 22568382
A84: =IF(I84=VALUE,VALUE,COUNTIF($B$7:B84,B84))&I84&IF(F84<>VALUE,TEXT(F84,"mmmm"),VALUE) -> 84-101-001March | B84: =I84&IF(F84<>VALUE,TEXT(F84,"mmmm"),VALUE) -> 4-101-001March | C84: =COUNTIF($K$7:K84,K84)&K84 -> 0 | D84: =IF(MONTH(F84)<MONTH(BLN),"1"&I84,VALUE) -> 14-101-001 | F84: 46112 | G84: 1651102412 | H84: Sales from Booking.com | I84: 4-101-001 | J84: =IF(ISNA(VLOOKUP(I84,DAF_AKUN,2,FALSE)),"-",VLOOKUP(I84,DAF_AKUN,2,FALSE)) -> Pendapatan Usaha | M84: 29132900
A85: =IF(I85=VALUE,VALUE,COUNTIF($B$7:B85,B85))&I85&IF(F85<>VALUE,TEXT(F85,"mmmm"),VALUE) -> 00 | B85: =I85&IF(F85<>VALUE,TEXT(F85,"mmmm"),VALUE) -> 0 | C85: =COUNTIF($K$7:K85,K85)&K85 -> 0 | D85: =IF(MONTH(F85)<MONTH(BLN),"1"&I85,VALUE) -> 1 | J85: =IF(ISNA(VLOOKUP(I85,DAF_AKUN,2,FALSE)),"-",VLOOKUP(I85,DAF_AKUN,2,FALSE)) -> -
A86: =IF(I86=VALUE,VALUE,COUNTIF($B$7:B86,B86))&I86&IF(F86<>VALUE,TEXT(F86,"mmmm"),VALUE) -> 15-101-003April | B86: =I86&IF(F86<>VALUE,TEXT(F86,"mmmm"),VALUE) -> 5-101-003April | C86: =COUNTIF($K$7:K86,K86)&K86 -> 0 | D86: =IF(MONTH(F86)<MONTH(BLN),"1"&I86,VALUE) -> 15-101-003 | F86: 46142 | G86: 1653241482 | H86: Biaya Layanan pembayaran | I86: 5-101-003 | J86: =IF(ISNA(VLOOKUP(I86,DAF_AKUN,2,FALSE)),"-",VLOOKUP(I86,DAF_AKUN,2,FALSE)) -> Transaction Cost | L86: 692645
A87: =IF(I87=VALUE,VALUE,COUNTIF($B$7:B87,B87))&I87&IF(F87<>VALUE,TEXT(F87,"mmmm"),VALUE) -> 25-101-003April | B87: =I87&IF(F87<>VALUE,TEXT(F87,"mmmm"),VALUE) -> 5-101-003April | C87: =COUNTIF($K$7:K87,K87)&K87 -> 0 | D87: =IF(MONTH(F87)<MONTH(BLN),"1"&I87,VALUE) -> 15-101-003 | F87: 46142 | G87: 1653241482 | H87: Biaya Reservasi | I87: 5-101-003 | J87: =IF(ISNA(VLOOKUP(I87,DAF_AKUN,2,FALSE)),"-",VLOOKUP(I87,DAF_AKUN,2,FALSE)) -> Transaction Cost | L87: 5420700
A88: =IF(I88=VALUE,VALUE,COUNTIF($B$7:B88,B88))&I88&IF(F88<>VALUE,TEXT(F88,"mmmm"),VALUE) -> 35-101-003April | B88: =I88&IF(F88<>VALUE,TEXT(F88,"mmmm"),VALUE) -> 5-101-003April | C88: =COUNTIF($K$7:K88,K88)&K88 -> 0 | D88: =IF(MONTH(F88)<MONTH(BLN),"1"&I88,VALUE) -> 15-101-003 | F88: 46142 | G88: 1653241482 | H88: Biaya PPN | I88: 5-101-003 | J88: =IF(ISNA(VLOOKUP(I88,DAF_AKUN,2,FALSE)),"-",VLOOKUP(I88,DAF_AKUN,2,FALSE)) -> Transaction Cost | L88: 672469
A89: =IF(I89=VALUE,VALUE,COUNTIF($B$7:B89,B89))&I89&IF(F89<>VALUE,TEXT(F89,"mmmm"),VALUE) -> 21-102-001April | B89: =I89&IF(F89<>VALUE,TEXT(F89,"mmmm"),VALUE) -> 1-102-001April | C89: =COUNTIF($K$7:K89,K89)&K89 -> 0 | D89: =IF(MONTH(F89)<MONTH(BLN),"1"&I89,VALUE) -> 11-102-001 | F89: 46142 | G89: 1653241482 | H89: Sales from Booking.com | I89: 1-102-001 | J89: =IF(ISNA(VLOOKUP(I89,DAF_AKUN,2,FALSE)),"-",VLOOKUP(I89,DAF_AKUN,2,FALSE)) -> Receivable - Trade | L89: =M90-L86-L87-L88 -> 23329186
A90: =IF(I90=VALUE,VALUE,COUNTIF($B$7:B90,B90))&I90&IF(F90<>VALUE,TEXT(F90,"mmmm"),VALUE) -> 24-101-001April | B90: =I90&IF(F90<>VALUE,TEXT(F90,"mmmm"),VALUE) -> 4-101-001April | C90: =COUNTIF($K$7:K90,K90)&K90 -> 0 | D90: =IF(MONTH(F90)<MONTH(BLN),"1"&I90,VALUE) -> 14-101-001 | F90: 46142 | G90: 1653241482 | H90: Sales from Booking.com | I90: 4-101-001 | J90: =IF(ISNA(VLOOKUP(I90,DAF_AKUN,2,FALSE)),"-",VLOOKUP(I90,DAF_AKUN,2,FALSE)) -> Pendapatan Usaha | M90: 30115000
A91: =IF(I91=VALUE,VALUE,COUNTIF($B$7:B91,B91))&I91&IF(F91<>VALUE,TEXT(F91,"mmmm"),VALUE) -> 00 | B91: =I91&IF(F91<>VALUE,TEXT(F91,"mmmm"),VALUE) -> 0 | C91: =COUNTIF($K$7:K91,K91)&K91 -> 0 | D91: =IF(MONTH(F91)<MONTH(BLN),"1"&I91,VALUE) -> 1 | J91: =IF(ISNA(VLOOKUP(I91,DAF_AKUN,2,FALSE)),"-",VLOOKUP(I91,DAF_AKUN,2,FALSE)) -> -
A92: =IF(I92=VALUE,VALUE,COUNTIF($B$7:B92,B92))&I92&IF(F92<>VALUE,TEXT(F92,"mmmm"),VALUE) -> 15-101-003May | B92: =I92&IF(F92<>VALUE,TEXT(F92,"mmmm"),VALUE) -> 5-101-003May | C92: =COUNTIF($K$7:K92,K92)&K92 -> 0 | D92: =IF(MONTH(F92)<MONTH(BLN),"1"&I92,VALUE) -> 15-101-003 | F92: 46173 | G92: 1655511417 | H92: Biaya Layanan pembayaran | I92: 5-101-003 | J92: =IF(ISNA(VLOOKUP(I92,DAF_AKUN,2,FALSE)),"-",VLOOKUP(I92,DAF_AKUN,2,FALSE)) -> Transaction Cost | L92: 558785
A93: =IF(I93=VALUE,VALUE,COUNTIF($B$7:B93,B93))&I93&IF(F93<>VALUE,TEXT(F93,"mmmm"),VALUE) -> 25-101-003May | B93: =I93&IF(F93<>VALUE,TEXT(F93,"mmmm"),VALUE) -> 5-101-003May | C93: =COUNTIF($K$7:K93,K93)&K93 -> 0 | D93: =IF(MONTH(F93)<MONTH(BLN),"1"&I93,VALUE) -> 15-101-003 | F93: 46173 | G93: 1655511417 | H93: Biaya Reservasi | I93: 5-101-003 | J93: =IF(ISNA(VLOOKUP(I93,DAF_AKUN,2,FALSE)),"-",VLOOKUP(I93,DAF_AKUN,2,FALSE)) -> Transaction Cost | L93: 4373100
A94: =IF(I94=VALUE,VALUE,COUNTIF($B$7:B94,B94))&I94&IF(F94<>VALUE,TEXT(F94,"mmmm"),VALUE) -> 35-101-003May | B94: =I94&IF(F94<>VALUE,TEXT(F94,"mmmm"),VALUE) -> 5-101-003May | C94: =COUNTIF($K$7:K94,K94)&K94 -> 0 | D94: =IF(MONTH(F94)<MONTH(BLN),"1"&I94,VALUE) -> 15-101-003 | F94: 46173 | G94: 1655511417 | H94: Biaya PPN | I94: 5-101-003 | J94: =IF(ISNA(VLOOKUP(I94,DAF_AKUN,2,FALSE)),"-",VLOOKUP(I94,DAF_AKUN,2,FALSE)) -> Transaction Cost | L94: 542506
A95: =IF(I95=VALUE,VALUE,COUNTIF($B$7:B95,B95))&I95&IF(F95<>VALUE,TEXT(F95,"mmmm"),VALUE) -> 11-102-001May | B95: =I95&IF(F95<>VALUE,TEXT(F95,"mmmm"),VALUE) -> 1-102-001May | C95: =COUNTIF($K$7:K95,K95)&K95 -> 0 | D95: =IF(MONTH(F95)<MONTH(BLN),"1"&I95,VALUE) -> 11-102-001 | F95: 46173 | G95: 1655511417 | H95: Sales from Booking.com | I95: 1-102-001 | J95: =IF(ISNA(VLOOKUP(I95,DAF_AKUN,2,FALSE)),"-",VLOOKUP(I95,DAF_AKUN,2,FALSE)) -> Receivable - Trade | L95: =M96-L92-L93-L94 -> 18820609
A96: =IF(I96=VALUE,VALUE,COUNTIF($B$7:B96,B96))&I96&IF(F96<>VALUE,TEXT(F96,"mmmm"),VALUE) -> 14-101-001May | B96: =I96&IF(F96<>VALUE,TEXT(F96,"mmmm"),VALUE) -> 4-101-001May | C96: =COUNTIF($K$7:K96,K96)&K96 -> 0 | D96: =IF(MONTH(F96)<MONTH(BLN),"1"&I96,VALUE) -> 14-101-001 | F96: 46173 | G96: 1655511417 | H96: Sales from Booking.com | I96: 4-101-001 | J96: =IF(ISNA(VLOOKUP(I96,DAF_AKUN,2,FALSE)),"-",VLOOKUP(I96,DAF_AKUN,2,FALSE)) -> Pendapatan Usaha | M96: 24295000
A97: =IF(I97=VALUE,VALUE,COUNTIF($B$7:B97,B97))&I97&IF(F97<>VALUE,TEXT(F97,"mmmm"),VALUE) -> 00 | B97: =I97&IF(F97<>VALUE,TEXT(F97,"mmmm"),VALUE) -> 0 | C97: =COUNTIF($K$7:K97,K97)&K97 -> 0 | D97: =IF(MONTH(F97)<MONTH(BLN),"1"&I97,VALUE) -> 1 | J97: =IF(ISNA(VLOOKUP(I97,DAF_AKUN,2,FALSE)),"-",VLOOKUP(I97,DAF_AKUN,2,FALSE)) -> -
A98: =IF(I98=VALUE,VALUE,COUNTIF($B$7:B98,B98))&I98&IF(F98<>VALUE,TEXT(F98,"mmmm"),VALUE) -> 15-101-003June | B98: =I98&IF(F98<>VALUE,TEXT(F98,"mmmm"),VALUE) -> 5-101-003June | C98: =COUNTIF($K$7:K98,K98)&K98 -> 0 | D98: =IF(MONTH(F98)<MONTH(BLN),"1"&I98,VALUE) -> 15-101-003 | F98: 46203 | G98: 1656582425 | H98: Biaya Layanan pembayaran | I98: 5-101-003 | J98: =IF(ISNA(VLOOKUP(I98,DAF_AKUN,2,FALSE)),"-",VLOOKUP(I98,DAF_AKUN,2,FALSE)) -> Transaction Cost | L98: 558670
A99: =IF(I99=VALUE,VALUE,COUNTIF($B$7:B99,B99))&I99&IF(F99<>VALUE,TEXT(F99,"mmmm"),VALUE) -> 25-101-003June | B99: =I99&IF(F99<>VALUE,TEXT(F99,"mmmm"),VALUE) -> 5-101-003June | C99: =COUNTIF($K$7:K99,K99)&K99 -> 0 | D99: =IF(MONTH(F99)<MONTH(BLN),"1"&I99,VALUE) -> 15-101-003 | F99: 46203 | G99: 1656582425 | H99: Biaya Reservasi | I99: 5-101-003 | J99: =IF(ISNA(VLOOKUP(I99,DAF_AKUN,2,FALSE)),"-",VLOOKUP(I99,DAF_AKUN,2,FALSE)) -> Transaction Cost | L99: 4372200
A100: =IF(I100=VALUE,VALUE,COUNTIF($B$7:B100,B100))&I100&IF(F100<>VALUE,TEXT(F100,"mmmm"),VALUE) -> 35-101-003June | B100: =I100&IF(F100<>VALUE,TEXT(F100,"mmmm"),VALUE) -> 5-101-003June | C100: =COUNTIF($K$7:K100,K100)&K100 -> 0 | D100: =IF(MONTH(F100)<MONTH(BLN),"1"&I100,VALUE) -> 15-101-003 | F100: 46203 | G100: 1656582425 | H100: Biaya PPN | I100: 5-101-003 | J100: =IF(ISNA(VLOOKUP(I100,DAF_AKUN,2,FALSE)),"-",VLOOKUP(I100,DAF_AKUN,2,FALSE)) -> Transaction Cost | L100: 542397
...

Sheet Atur Laporan
C7: ="Tahun : "&THN -> Tahun : 2026
C9: Bulan | D9: 183

Sheet Buku Besar
A1: =NAMA -> ARYA USAHA TIRTA, CV
A2: BUKU BESAR
A3: ="Bulan : "&TEXT(TEXT(BLN,"mmmm"),"mmmm")&" "&THN -> Bulan : July 2026
A5: Kode Akun | C5: 1-120-005 | F5: Pos Saldo : | G5: =VLOOKUP(C5,DAF_AKUN,3,FALSE) -> Db
A6: Nama Akun | C6: =VLOOKUP(C5,DAF_AKUN,2,FALSE) -> Electronics & IT Equipment | F6: Saldo Awal : | G6: =IF(ISERROR=TRUE,IF(AND(ISERROR=TRUE,VLOOKUP(C5,DAF_AKUN,3,FALSE)="Db"),SUMIF(Akun!A:A,C5,Akun!F:F)+SUMIF(Jurnal!D:D,"1"&C5,Jurnal!L:L)-SUMIF(Jurnal!D:D,"1"&C5,Jurnal!M:M),SUMIF(Akun!A:A,C5,Akun!G:G)-SUMIF(Jurnal!D:D,"1"&C5,Jurnal!L:L)+SUMIF(Jurnal!D:D,"1"&C5,Jurnal!M:M)),VALUE) -> 9550321
A8: No | B8: Tanggal | C8: Bukti | D8: Keterangan | E8: Debet | F8: Kredit | G8: Saldo
A10: =A9+1 -> 1 | B10: =IF(OR(ISERROR=FALSE,ISERROR(VLOOKUP(A10&C$5&TEXT(BLN,"mmmm"),JU_AKUN,6,FALSE))=TRUE),TEXT,VLOOKUP(A10&C$5&TEXT(BLN,"mmmm"),JU_AKUN,6,FALSE)) -> - | C10: =IF(OR(ISERROR=FALSE,ISERROR(VLOOKUP(A10&C$5&TEXT(BLN,"mmmm"),JU_AKUN,7,FALSE))=TRUE),TEXT,VLOOKUP(A10&C$5&TEXT(BLN,"mmmm"),JU_AKUN,7,FALSE)) -> - | D10: =IF(OR(ISERROR=FALSE,ISERROR(VLOOKUP(A10&C$5&TEXT(BLN,"mmmm"),JU_AKUN,8,FALSE))=TRUE),TEXT,VLOOKUP(A10&C$5&TEXT(BLN,"mmmm"),JU_AKUN,8,FALSE)) -> - | E10: =IF(OR(ISERROR=FALSE,ISERROR(VLOOKUP(A10&C$5&TEXT(BLN,"mmmm"),JU_AKUN,12,FALSE))=TRUE),TEXT,VLOOKUP(A10&C$5&TEXT(BLN,"mmmm"),JU_AKUN,12,FALSE)) -> - | F10: =IF(OR(ISERROR=FALSE,ISERROR(VLOOKUP(A10&C$5&TEXT(BLN,"mmmm"),JU_AKUN,13,FALSE))=TRUE),TEXT,VLOOKUP(A10&C$5&TEXT(BLN,"mmmm"),JU_AKUN,13,FALSE)) -> - | G10: =IF(AND(E10=TEXT,F10=TEXT),VALUE,IF($G$5="Db",$G$6+SUM($E$10:E10)-SUM($F$10:F10),$G$6-SUM($E$10:E10)+SUM($F$10:F10))) -> 0
A11: =A10+1 -> 2 | B11: =IF(OR(ISERROR=FALSE,ISERROR(VLOOKUP(A11&C$5&TEXT(BLN,"mmmm"),JU_AKUN,6,FALSE))=TRUE),TEXT,VLOOKUP(A11&C$5&TEXT(BLN,"mmmm"),JU_AKUN,6,FALSE)) -> - | C11: =IF(OR(ISERROR=FALSE,ISERROR(VLOOKUP(A11&C$5&TEXT(BLN,"mmmm"),JU_AKUN,7,FALSE))=TRUE),TEXT,VLOOKUP(A11&C$5&TEXT(BLN,"mmmm"),JU_AKUN,7,FALSE)) -> - | D11: =IF(OR(ISERROR=FALSE,ISERROR(VLOOKUP(A11&C$5&TEXT(BLN,"mmmm"),JU_AKUN,8,FALSE))=TRUE),TEXT,VLOOKUP(A11&C$5&TEXT(BLN,"mmmm"),JU_AKUN,8,FALSE)) -> - | E11: =IF(OR(ISERROR=FALSE,ISERROR(VLOOKUP(A11&C$5&TEXT(BLN,"mmmm"),JU_AKUN,12,FALSE))=TRUE),TEXT,VLOOKUP(A11&C$5&TEXT(BLN,"mmmm"),JU_AKUN,12,FALSE)) -> - | F11: =IF(OR(ISERROR=FALSE,ISERROR(VLOOKUP(A11&C$5&TEXT(BLN,"mmmm"),JU_AKUN,13,FALSE))=TRUE),TEXT,VLOOKUP(A11&C$5&TEXT(BLN,"mmmm"),JU_AKUN,13,FALSE)) -> - | G11: =IF(AND(E11=TEXT,F11=TEXT),VALUE,IF($G$5="Db",$G$6+SUM($E$10:E11)-SUM($F$10:F11),$G$6-SUM($E$10:E11)+SUM($F$10:F11))) -> 0
A12: =A11+1 -> 3 | B12: =IF(OR(ISERROR=FALSE,ISERROR(VLOOKUP(A12&C$5&TEXT(BLN,"mmmm"),JU_AKUN,6,FALSE))=TRUE),TEXT,VLOOKUP(A12&C$5&TEXT(BLN,"mmmm"),JU_AKUN,6,FALSE)) -> - | C12: =IF(OR(ISERROR=FALSE,ISERROR(VLOOKUP(A12&C$5&TEXT(BLN,"mmmm"),JU_AKUN,7,FALSE))=TRUE),TEXT,VLOOKUP(A12&C$5&TEXT(BLN,"mmmm"),JU_AKUN,7,FALSE)) -> - | D12: =IF(OR(ISERROR=FALSE,ISERROR(VLOOKUP(A12&C$5&TEXT(BLN,"mmmm"),JU_AKUN,8,FALSE))=TRUE),TEXT,VLOOKUP(A12&C$5&TEXT(BLN,"mmmm"),JU_AKUN,8,FALSE)) -> - | E12: =IF(OR(ISERROR=FALSE,ISERROR(VLOOKUP(A12&C$5&TEXT(BLN,"mmmm"),JU_AKUN,12,FALSE))=TRUE),TEXT,VLOOKUP(A12&C$5&TEXT(BLN,"mmmm"),JU_AKUN,12,FALSE)) -> - | F12: =IF(OR(ISERROR=FALSE,ISERROR(VLOOKUP(A12&C$5&TEXT(BLN,"mmmm"),JU_AKUN,13,FALSE))=TRUE),TEXT,VLOOKUP(A12&C$5&TEXT(BLN,"mmmm"),JU_AKUN,13,FALSE)) -> - | G12: =IF(AND(E12=TEXT,F12=TEXT),VALUE,IF($G$5="Db",$G$6+SUM($E$10:E12)-SUM($F$10:F12),$G$6-SUM($E$10:E12)+SUM($F$10:F12))) -> 0
A13: =A12+1 -> 4 | B13: =IF(OR(ISERROR=FALSE,ISERROR(VLOOKUP(A13&C$5&TEXT(BLN,"mmmm"),JU_AKUN,6,FALSE))=TRUE),TEXT,VLOOKUP(A13&C$5&TEXT(BLN,"mmmm"),JU_AKUN,6,FALSE)) -> - | C13: =IF(OR(ISERROR=FALSE,ISERROR(VLOOKUP(A13&C$5&TEXT(BLN,"mmmm"),JU_AKUN,7,FALSE))=TRUE),TEXT,VLOOKUP(A13&C$5&TEXT(BLN,"mmmm"),JU_AKUN,7,FALSE)) -> - | D13: =IF(OR(ISERROR=FALSE,ISERROR(VLOOKUP(A13&C$5&TEXT(BLN,"mmmm"),JU_AKUN,8,FALSE))=TRUE),TEXT,VLOOKUP(A13&C$5&TEXT(BLN,"mmmm"),JU_AKUN,8,FALSE)) -> - | E13: =IF(OR(ISERROR=FALSE,ISERROR(VLOOKUP(A13&C$5&TEXT(BLN,"mmmm"),JU_AKUN,12,FALSE))=TRUE),TEXT,VLOOKUP(A13&C$5&TEXT(BLN,"mmmm"),JU_AKUN,12,FALSE)) -> - | F13: =IF(OR(ISERROR=FALSE,ISERROR(VLOOKUP(A13&C$5&TEXT(BLN,"mmmm"),JU_AKUN,13,FALSE))=TRUE),TEXT,VLOOKUP(A13&C$5&TEXT(BLN,"mmmm"),JU_AKUN,13,FALSE)) -> - | G13: =IF(AND(E13=TEXT,F13=TEXT),VALUE,IF($G$5="Db",$G$6+SUM($E$10:E13)-SUM($F$10:F13),$G$6-SUM($E$10:E13)+SUM($F$10:F13))) -> 0
A14: =A13+1 -> 5 | B14: =IF(OR(ISERROR=FALSE,ISERROR(VLOOKUP(A14&C$5&TEXT(BLN,"mmmm"),JU_AKUN,6,FALSE))=TRUE),TEXT,VLOOKUP(A14&C$5&TEXT(BLN,"mmmm"),JU_AKUN,6,FALSE)) -> - | C14: =IF(OR(ISERROR=FALSE,ISERROR(VLOOKUP(A14&C$5&TEXT(BLN,"mmmm"),JU_AKUN,7,FALSE))=TRUE),TEXT,VLOOKUP(A14&C$5&TEXT(BLN,"mmmm"),JU_AKUN,7,FALSE)) -> - | D14: =IF(OR(ISERROR=FALSE,ISERROR(VLOOKUP(A14&C$5&TEXT(BLN,"mmmm"),JU_AKUN,8,FALSE))=TRUE),TEXT,VLOOKUP(A14&C$5&TEXT(BLN,"mmmm"),JU_AKUN,8,FALSE)) -> - | E14: =IF(OR(ISERROR=FALSE,ISERROR(VLOOKUP(A14&C$5&TEXT(BLN,"mmmm"),JU_AKUN,12,FALSE))=TRUE),TEXT,VLOOKUP(A14&C$5&TEXT(BLN,"mmmm"),JU_AKUN,12,FALSE)) -> - | F14: =IF(OR(ISERROR=FALSE,ISERROR(VLOOKUP(A14&C$5&TEXT(BLN,"mmmm"),JU_AKUN,13,FALSE))=TRUE),TEXT,VLOOKUP(A14&C$5&TEXT(BLN,"mmmm"),JU_AKUN,13,FALSE)) -> - | G14: =IF(AND(E14=TEXT,F14=TEXT),VALUE,IF($G$5="Db",$G$6+SUM($E$10:E14)-SUM($F$10:F14),$G$6-SUM($E$10:E14)+SUM($F$10:F14))) -> 0
A15: =A14+1 -> 6 | B15: =IF(OR(ISERROR=FALSE,ISERROR(VLOOKUP(A15&C$5&TEXT(BLN,"mmmm"),JU_AKUN,6,FALSE))=TRUE),TEXT,VLOOKUP(A15&C$5&TEXT(BLN,"mmmm"),JU_AKUN,6,FALSE)) -> - | C15: =IF(OR(ISERROR=FALSE,ISERROR(VLOOKUP(A15&C$5&TEXT(BLN,"mmmm"),JU_AKUN,7,FALSE))=TRUE),TEXT,VLOOKUP(A15&C$5&TEXT(BLN,"mmmm"),JU_AKUN,7,FALSE)) -> - | D15: =IF(OR(ISERROR=FALSE,ISERROR(VLOOKUP(A15&C$5&TEXT(BLN,"mmmm"),JU_AKUN,8,FALSE))=TRUE),TEXT,VLOOKUP(A15&C$5&TEXT(BLN,"mmmm"),JU_AKUN,8,FALSE)) -> - | E15: =IF(OR(ISERROR=FALSE,ISERROR(VLOOKUP(A15&C$5&TEXT(BLN,"mmmm"),JU_AKUN,12,FALSE))=TRUE),TEXT,VLOOKUP(A15&C$5&TEXT(BLN,"mmmm"),JU_AKUN,12,FALSE)) -> - | F15: =IF(OR(ISERROR=FALSE,ISERROR(VLOOKUP(A15&C$5&TEXT(BLN,"mmmm"),JU_AKUN,13,FALSE))=TRUE),TEXT,VLOOKUP(A15&C$5&TEXT(BLN,"mmmm"),JU_AKUN,13,FALSE)) -> - | G15: =IF(AND(E15=TEXT,F15=TEXT),VALUE,IF($G$5="Db",$G$6+SUM($E$10:E15)-SUM($F$10:F15),$G$6-SUM($E$10:E15)+SUM($F$10:F15))) -> 0
A16: =A15+1 -> 7 | B16: =IF(OR(ISERROR=FALSE,ISERROR(VLOOKUP(A16&C$5&TEXT(BLN,"mmmm"),JU_AKUN,6,FALSE))=TRUE),TEXT,VLOOKUP(A16&C$5&TEXT(BLN,"mmmm"),JU_AKUN,6,FALSE)) -> - | C16: =IF(OR(ISERROR=FALSE,ISERROR(VLOOKUP(A16&C$5&TEXT(BLN,"mmmm"),JU_AKUN,7,FALSE))=TRUE),TEXT,VLOOKUP(A16&C$5&TEXT(BLN,"mmmm"),JU_AKUN,7,FALSE)) -> - | D16: =IF(OR(ISERROR=FALSE,ISERROR(VLOOKUP(A16&C$5&TEXT(BLN,"mmmm"),JU_AKUN,8,FALSE))=TRUE),TEXT,VLOOKUP(A16&C$5&TEXT(BLN,"mmmm"),JU_AKUN,8,FALSE)) -> - | E16: =IF(OR(ISERROR=FALSE,ISERROR(VLOOKUP(A16&C$5&TEXT(BLN,"mmmm"),JU_AKUN,12,FALSE))=TRUE),TEXT,VLOOKUP(A16&C$5&TEXT(BLN,"mmmm"),JU_AKUN,12,FALSE)) -> - | F16: =IF(OR(ISERROR=FALSE,ISERROR(VLOOKUP(A16&C$5&TEXT(BLN,"mmmm"),JU_AKUN,13,FALSE))=TRUE),TEXT,VLOOKUP(A16&C$5&TEXT(BLN,"mmmm"),JU_AKUN,13,FALSE)) -> - | G16: =IF(AND(E16=TEXT,F16=TEXT),VALUE,IF($G$5="Db",$G$6+SUM($E$10:E16)-SUM($F$10:F16),$G$6-SUM($E$10:E16)+SUM($F$10:F16))) -> 0
A17: =A16+1 -> 8 | B17: =IF(OR(ISERROR=FALSE,ISERROR(VLOOKUP(A17&C$5&TEXT(BLN,"mmmm"),JU_AKUN,6,FALSE))=TRUE),TEXT,VLOOKUP(A17&C$5&TEXT(BLN,"mmmm"),JU_AKUN,6,FALSE)) -> - | C17: =IF(OR(ISERROR=FALSE,ISERROR(VLOOKUP(A17&C$5&TEXT(BLN,"mmmm"),JU_AKUN,7,FALSE))=TRUE),TEXT,VLOOKUP(A17&C$5&TEXT(BLN,"mmmm"),JU_AKUN,7,FALSE)) -> - | D17: =IF(OR(ISERROR=FALSE,ISERROR(VLOOKUP(A17&C$5&TEXT(BLN,"mmmm"),JU_AKUN,8,FALSE))=TRUE),TEXT,VLOOKUP(A17&C$5&TEXT(BLN,"mmmm"),JU_AKUN,8,FALSE)) -> - | E17: =IF(OR(ISERROR=FALSE,ISERROR(VLOOKUP(A17&C$5&TEXT(BLN,"mmmm"),JU_AKUN,12,FALSE))=TRUE),TEXT,VLOOKUP(A17&C$5&TEXT(BLN,"mmmm"),JU_AKUN,12,FALSE)) -> - | F17: =IF(OR(ISERROR=FALSE,ISERROR(VLOOKUP(A17&C$5&TEXT(BLN,"mmmm"),JU_AKUN,13,FALSE))=TRUE),TEXT,VLOOKUP(A17&C$5&TEXT(BLN,"mmmm"),JU_AKUN,13,FALSE)) -> - | G17: =IF(AND(E17=TEXT,F17=TEXT),VALUE,IF($G$5="Db",$G$6+SUM($E$10:E17)-SUM($F$10:F17),$G$6-SUM($E$10:E17)+SUM($F$10:F17))) -> 0
A18: =A17+1 -> 9 | B18: =IF(OR(ISERROR=FALSE,ISERROR(VLOOKUP(A18&C$5&TEXT(BLN,"mmmm"),JU_AKUN,6,FALSE))=TRUE),TEXT,VLOOKUP(A18&C$5&TEXT(BLN,"mmmm"),JU_AKUN,6,FALSE)) -> - | C18: =IF(OR(ISERROR=FALSE,ISERROR(VLOOKUP(A18&C$5&TEXT(BLN,"mmmm"),JU_AKUN,7,FALSE))=TRUE),TEXT,VLOOKUP(A18&C$5&TEXT(BLN,"mmmm"),JU_AKUN,7,FALSE)) -> - | D18: =IF(OR(ISERROR=FALSE,ISERROR(VLOOKUP(A18&C$5&TEXT(BLN,"mmmm"),JU_AKUN,8,FALSE))=TRUE),TEXT,VLOOKUP(A18&C$5&TEXT(BLN,"mmmm"),JU_AKUN,8,FALSE)) -> - | E18: =IF(OR(ISERROR=FALSE,ISERROR(VLOOKUP(A18&C$5&TEXT(BLN,"mmmm"),JU_AKUN,12,FALSE))=TRUE),TEXT,VLOOKUP(A18&C$5&TEXT(BLN,"mmmm"),JU_AKUN,12,FALSE)) -> - | F18: =IF(OR(ISERROR=FALSE,ISERROR(VLOOKUP(A18&C$5&TEXT(BLN,"mmmm"),JU_AKUN,13,FALSE))=TRUE),TEXT,VLOOKUP(A18&C$5&TEXT(BLN,"mmmm"),JU_AKUN,13,FALSE)) -> - | G18: =IF(AND(E18=TEXT,F18=TEXT),VALUE,IF($G$5="Db",$G$6+SUM($E$10:E18)-SUM($F$10:F18),$G$6-SUM($E$10:E18)+SUM($F$10:F18))) -> 0
A19: =A18+1 -> 10 | B19: =IF(OR(ISERROR=FALSE,ISERROR(VLOOKUP(A19&C$5&TEXT(BLN,"mmmm"),JU_AKUN,6,FALSE))=TRUE),TEXT,VLOOKUP(A19&C$5&TEXT(BLN,"mmmm"),JU_AKUN,6,FALSE)) -> - | C19: =IF(OR(ISERROR=FALSE,ISERROR(VLOOKUP(A19&C$5&TEXT(BLN,"mmmm"),JU_AKUN,7,FALSE))=TRUE),TEXT,VLOOKUP(A19&C$5&TEXT(BLN,"mmmm"),JU_AKUN,7,FALSE)) -> - | D19: =IF(OR(ISERROR=FALSE,ISERROR(VLOOKUP(A19&C$5&TEXT(BLN,"mmmm"),JU_AKUN,8,FALSE))=TRUE),TEXT,VLOOKUP(A19&C$5&TEXT(BLN,"mmmm"),JU_AKUN,8,FALSE)) -> - | E19: =IF(OR(ISERROR=FALSE,ISERROR(VLOOKUP(A19&C$5&TEXT(BLN,"mmmm"),JU_AKUN,12,FALSE))=TRUE),TEXT,VLOOKUP(A19&C$5&TEXT(BLN,"mmmm"),JU_AKUN,12,FALSE)) -> - | F19: =IF(OR(ISERROR=FALSE,ISERROR(VLOOKUP(A19&C$5&TEXT(BLN,"mmmm"),JU_AKUN,13,FALSE))=TRUE),TEXT,VLOOKUP(A19&C$5&TEXT(BLN,"mmmm"),JU_AKUN,13,FALSE)) -> - | G19: =IF(AND(E19=TEXT,F19=TEXT),VALUE,IF($G$5="Db",$G$6+SUM($E$10:E19)-SUM($F$10:F19),$G$6-SUM($E$10:E19)+SUM($F$10:F19))) -> 0
A20: =A19+1 -> 11 | B20: =IF(OR(ISERROR=FALSE,ISERROR(VLOOKUP(A20&C$5&TEXT(BLN,"mmmm"),JU_AKUN,6,FALSE))=TRUE),TEXT,VLOOKUP(A20&C$5&TEXT(BLN,"mmmm"),JU_AKUN,6,FALSE)) -> - | C20: =IF(OR(ISERROR=FALSE,ISERROR(VLOOKUP(A20&C$5&TEXT(BLN,"mmmm"),JU_AKUN,7,FALSE))=TRUE),TEXT,VLOOKUP(A20&C$5&TEXT(BLN,"mmmm"),JU_AKUN,7,FALSE)) -> - | D20: =IF(OR(ISERROR=FALSE,ISERROR(VLOOKUP(A20&C$5&TEXT(BLN,"mmmm"),JU_AKUN,8,FALSE))=TRUE),TEXT,VLOOKUP(A20&C$5&TEXT(BLN,"mmmm"),JU_AKUN,8,FALSE)) -> - | E20: =IF(OR(ISERROR=FALSE,ISERROR(VLOOKUP(A20&C$5&TEXT(BLN,"mmmm"),JU_AKUN,12,FALSE))=TRUE),TEXT,VLOOKUP(A20&C$5&TEXT(BLN,"mmmm"),JU_AKUN,12,FALSE)) -> - | F20: =IF(OR(ISERROR=FALSE,ISERROR(VLOOKUP(A20&C$5&TEXT(BLN,"mmmm"),JU_AKUN,13,FALSE))=TRUE),TEXT,VLOOKUP(A20&C$5&TEXT(BLN,"mmmm"),JU_AKUN,13,FALSE)) -> - | G20: =IF(AND(E20=TEXT,F20=TEXT),VALUE,IF($G$5="Db",$G$6+SUM($E$10:E20)-SUM($F$10:F20),$G$6-SUM($E$10:E20)+SUM($F$10:F20))) -> 0
A21: =A20+1 -> 12 | B21: =IF(OR(ISERROR=FALSE,ISERROR(VLOOKUP(A21&C$5&TEXT(BLN,"mmmm"),JU_AKUN,6,FALSE))=TRUE),TEXT,VLOOKUP(A21&C$5&TEXT(BLN,"mmmm"),JU_AKUN,6,FALSE)) -> - | C21: =IF(OR(ISERROR=FALSE,ISERROR(VLOOKUP(A21&C$5&TEXT(BLN,"mmmm"),JU_AKUN,7,FALSE))=TRUE),TEXT,VLOOKUP(A21&C$5&TEXT(BLN,"mmmm"),JU_AKUN,7,FALSE)) -> - | D21: =IF(OR(ISERROR=FALSE,ISERROR(VLOOKUP(A21&C$5&TEXT(BLN,"mmmm"),JU_AKUN,8,FALSE))=TRUE),TEXT,VLOOKUP(A21&C$5&TEXT(BLN,"mmmm"),JU_AKUN,8,FALSE)) -> - | E21: =IF(OR(ISERROR=FALSE,ISERROR(VLOOKUP(A21&C$5&TEXT(BLN,"mmmm"),JU_AKUN,12,FALSE))=TRUE),TEXT,VLOOKUP(A21&C$5&TEXT(BLN,"mmmm"),JU_AKUN,12,FALSE)) -> - | F21: =IF(OR(ISERROR=FALSE,ISERROR(VLOOKUP(A21&C$5&TEXT(BLN,"mmmm"),JU_AKUN,13,FALSE))=TRUE),TEXT,VLOOKUP(A21&C$5&TEXT(BLN,"mmmm"),JU_AKUN,13,FALSE)) -> - | G21: =IF(AND(E21=TEXT,F21=TEXT),VALUE,IF($G$5="Db",$G$6+SUM($E$10:E21)-SUM($F$10:F21),$G$6-SUM($E$10:E21)+SUM($F$10:F21))) -> 0
... A108: =A107+1 -> 99 | B108: =IF(OR(ISERROR=FALSE,ISERROR(VLOOKUP(A108&C$5&TEXT(BLN,"mmmm"),JU_AKUN,6,FALSE))=TRUE),TEXT,VLOOKUP(A108&C$5&TEXT(BLN,"mmmm"),JU_AKUN,6,FALSE)) -> - | C108: =IF(OR(ISERROR=FALSE,ISERROR(VLOOKUP(A108&C$5&TEXT(BLN,"mmmm"),JU_AKUN,7,FALSE))=TRUE),TEXT,VLOOKUP(A108&C$5&TEXT(BLN,"mmmm"),JU_AKUN,7,FALSE)) -> - | D108: =IF(OR(ISERROR=FALSE,ISERROR(VLOOKUP(A108&C$5&TEXT(BLN,"mmmm"),JU_AKUN,8,FALSE))=TRUE),TEXT,VLOOKUP(A108&C$5&TEXT(BLN,"mmmm"),JU_AKUN,8,FALSE)) -> - | E108: =IF(OR(ISERROR=FALSE,ISERROR(VLOOKUP(A108&C$5&TEXT(BLN,"mmmm"),JU_AKUN,12,FALSE))=TRUE),TEXT,VLOOKUP(A108&C$5&TEXT(BLN,"mmmm"),JU_AKUN,12,FALSE)) -> - | F108: =IF(OR(ISERROR=FALSE,ISERROR(VLOOKUP(A108&C$5&TEXT(BLN,"mmmm"),JU_AKUN,13,FALSE))=TRUE),TEXT,VLOOKUP(A108&C$5&TEXT(BLN,"mmmm"),JU_AKUN,13,FALSE)) -> - | G108: =IF(AND(E108=TEXT,F108=TEXT),VALUE,IF($G$5="Db",$G$6+SUM($E$10:E108)-SUM($F$10:F108),$G$6-SUM($E$10:E108)+SUM($F$10:F108))) -> 0

Sheet Neraca Lajur
A1: =NAMA -> ARYA USAHA TIRTA, CV
A2: NERACA LAJUR
A3: ="S/D Bulan : "&TEXT(BLN,"mmmm")&" "&THN -> S/D Bulan : July 2026
A5: Kode | B5: Nama Akun | C5: Pos | D5: Neraca Saldo | F5: Pos | G5: Laba Rugi | I5: Neraca
A6: Akun | C6: Saldo | D6: Debet | E6: Kredit | F6: Laporan | G6: Debet | H6: Kredit | I6: Debet | J6: Kredit
A7: 100000000 | B7: =VLOOKUP(A7,DAF_AKUN,2,FALSE) -> AKTIVA | C7: =VLOOKUP(A7,DAF_AKUN,3,FALSE) -> 0 | D7: =IF(AND(ISERROR=TRUE,C7="Db"),SUMIF(AKUN1,A7,AKUN2)+SUMIF(JURN2,"1"&A7,JURN3)-SUMIF(JURN2,"1"&A7,JURN4)+SUMIF(JURN1,A7&TEXT(BLN,"mmmm"),JURN3)-SUMIF(JURN1,A7&TEXT(BLN,"mmmm"),JURN4),VALUE) -> 0 | E7: =IF(AND(ISERROR=TRUE,C7="Kr"),SUMIF(AKUN1,A7,AKUN3)-SUMIF(JURN2,"1"&A7,JURN3)+SUMIF(JURN2,"1"&A7,JURN4)+SUMIF(JURN1,A7&TEXT(BLN,"mmmm"),JURN4)-SUMIF(JURN1,A7&TEXT(BLN,"mmmm"),JURN3),VALUE) -> 0 | F7: =VLOOKUP(A7,DAF_AKUN,4,FALSE) -> 0 | G7: =IF(D7=TEXT,VALUE,IF(F7="LR",D7,0)) -> 0 | H7: =IF(E7=TEXT,VALUE,IF(F7="LR",E7,0)) -> 0 | I7: =IF(D7=TEXT,VALUE,IF(F7="NRC",D7,0)) -> 0 | J7: =IF(E7=TEXT,VALUE,IF(F7="NRC",E7,0)) -> 0
A8: 1-101-000 | B8: =VLOOKUP(A8,DAF_AKUN,2,FALSE) -> Kas dan Bank | C8: =VLOOKUP(A8,DAF_AKUN,3,FALSE) -> Db | D8: =IF(AND(ISERROR=TRUE,C8="Db"),SUMIF(AKUN1,A8,AKUN2)+SUMIF(JURN2,"1"&A8,JURN3)-SUMIF(JURN2,"1"&A8,JURN4)+SUMIF(JURN1,A8&TEXT(BLN,"mmmm"),JURN3)-SUMIF(JURN1,A8&TEXT(BLN,"mmmm"),JURN4),VALUE) -> 0 | E8: =IF(AND(ISERROR=TRUE,C8="Kr"),SUMIF(AKUN1,A8,AKUN3)-SUMIF(JURN2,"1"&A8,JURN3)+SUMIF(JURN2,"1"&A8,JURN4)+SUMIF(JURN1,A8&TEXT(BLN,"mmmm"),JURN4)-SUMIF(JURN1,A8&TEXT(BLN,"mmmm"),JURN3),VALUE) -> 0 | F8: =VLOOKUP(A8,DAF_AKUN,4,FALSE) -> NRC | G8: =IF(D8=TEXT,VALUE,IF(F8="LR",D8,0)) -> 0 | H8: =IF(E8=TEXT,VALUE,IF(F8="LR",E8,0)) -> 0 | I8: =IF(D8=TEXT,VALUE,IF(F8="NRC",D8,0)) -> 0 | J8: =IF(E8=TEXT,VALUE,IF(F8="NRC",E8,0)) -> 0
A9: 1-101-001 | B9: =VLOOKUP(A9,DAF_AKUN,2,FALSE) -> Petty Cash | C9: =VLOOKUP(A9,DAF_AKUN,3,FALSE) -> Db | D9: =IF(AND(ISERROR=TRUE,C9="Db"),SUMIF(AKUN1,A9,AKUN2)+SUMIF(JURN2,"1"&A9,JURN3)-SUMIF(JURN2,"1"&A9,JURN4)+SUMIF(JURN1,A9&TEXT(BLN,"mmmm"),JURN3)-SUMIF(JURN1,A9&TEXT(BLN,"mmmm"),JURN4),VALUE) -> 0 | E9: =IF(AND(ISERROR=TRUE,C9="Kr"),SUMIF(AKUN1,A9,AKUN3)-SUMIF(JURN2,"1"&A9,JURN3)+SUMIF(JURN2,"1"&A9,JURN4)+SUMIF(JURN1,A9&TEXT(BLN,"mmmm"),JURN4)-SUMIF(JURN1,A9&TEXT(BLN,"mmmm"),JURN3),VALUE) -> 0 | F9: =VLOOKUP(A9,DAF_AKUN,4,FALSE) -> NRC | G9: =IF(D9=TEXT,VALUE,IF(F9="LR",D9,0)) -> 0 | H9: =IF(E9=TEXT,VALUE,IF(F9="LR",E9,0)) -> 0 | I9: =IF(D9=TEXT,VALUE,IF(F9="NRC",D9,0)) -> 0 | J9: =IF(E9=TEXT,VALUE,IF(F9="NRC",E9,0)) -> 0
A10: 1-101-010 | B10: =VLOOKUP(A10,DAF_AKUN,2,FALSE) -> CIMB Niaga - Acc. No: 800171592300 | C10: =VLOOKUP(A10,DAF_AKUN,3,FALSE) -> Db | D10: =IF(AND(ISERROR=TRUE,C10="Db"),SUMIF(AKUN1,A10,AKUN2)+SUMIF(JURN2,"1"&A10,JURN3)-SUMIF(JURN2,"1"&A10,JURN4)+SUMIF(JURN1,A10&TEXT(BLN,"mmmm"),JURN3)-SUMIF(JURN1,A10&TEXT(BLN,"mmmm"),JURN4),VALUE) -> 3043241 | E10: =IF(AND(ISERROR=TRUE,C10="Kr"),SUMIF(AKUN1,A10,AKUN3)-SUMIF(JURN2,"1"&A10,JURN3)+SUMIF(JURN2,"1"&A10,JURN4)+SUMIF(JURN1,A10&TEXT(BLN,"mmmm"),JURN4)-SUMIF(JURN1,A10&TEXT(BLN,"mmmm"),JURN3),VALUE) -> 0 | F10: =VLOOKUP(A10,DAF_AKUN,4,FALSE) -> NRC | G10: =IF(D10=TEXT,VALUE,IF(F10="LR",D10,0)) -> 0 | H10: =IF(E10=TEXT,VALUE,IF(F10="LR",E10,0)) -> 0 | I10: =IF(D10=TEXT,VALUE,IF(F10="NRC",D10,0)) -> 3043241 | J10: =IF(E10=TEXT,VALUE,IF(F10="NRC",E10,0)) -> 0
A11: 1-101-011 | B11: =VLOOKUP(A11,DAF_AKUN,2,FALSE) -> Bank 2 | C11: =VLOOKUP(A11,DAF_AKUN,3,FALSE) -> Db | D11: =IF(AND(ISERROR=TRUE,C11="Db"),SUMIF(AKUN1,A11,AKUN2)+SUMIF(JURN2,"1"&A11,JURN3)-SUMIF(JURN2,"1"&A11,JURN4)+SUMIF(JURN1,A11&TEXT(BLN,"mmmm"),JURN3)-SUMIF(JURN1,A11&TEXT(BLN,"mmmm"),JURN4),VALUE) -> 0 | E11: =IF(AND(ISERROR=TRUE,C11="Kr"),SUMIF(AKUN1,A11,AKUN3)-SUMIF(JURN2,"1"&A11,JURN3)+SUMIF(JURN2,"1"&A11,JURN4)+SUMIF(JURN1,A11&TEXT(BLN,"mmmm"),JURN4)-SUMIF(JURN1,A11&TEXT(BLN,"mmmm"),JURN3),VALUE) -> 0 | F11: =VLOOKUP(A11,DAF_AKUN,4,FALSE) -> NRC | G11: =IF(D11=TEXT,VALUE,IF(F11="LR",D11,0)) -> 0 | H11: =IF(E11=TEXT,VALUE,IF(F11="LR",E11,0)) -> 0 | I11: =IF(D11=TEXT,VALUE,IF(F11="NRC",D11,0)) -> 0 | J11: =IF(E11=TEXT,VALUE,IF(F11="NRC",E11,0)) -> 0
A12: 1-101-012 | B12: =VLOOKUP(A12,DAF_AKUN,2,FALSE) -> Bank 3 | C12: =VLOOKUP(A12,DAF_AKUN,3,FALSE) -> Db | D12: =IF(AND(ISERROR=TRUE,C12="Db"),SUMIF(AKUN1,A12,AKUN2)+SUMIF(JURN2,"1"&A12,JURN3)-SUMIF(JURN2,"1"&A12,JURN4)+SUMIF(JURN1,A12&TEXT(BLN,"mmmm"),JURN3)-SUMIF(JURN1,A12&TEXT(BLN,"mmmm"),JURN4),VALUE) -> 0 | E12: =IF(AND(ISERROR=TRUE,C12="Kr"),SUMIF(AKUN1,A12,AKUN3)-SUMIF(JURN2,"1"&A12,JURN3)+SUMIF(JURN2,"1"&A12,JURN4)+SUMIF(JURN1,A12&TEXT(BLN,"mmmm"),JURN4)-SUMIF(JURN1,A12&TEXT(BLN,"mmmm"),JURN3),VALUE) -> 0 | F12: =VLOOKUP(A12,DAF_AKUN,4,FALSE) -> NRC | G12: =IF(D12=TEXT,VALUE,IF(F12="LR",D12,0)) -> 0 | H12: =IF(E12=TEXT,VALUE,IF(F12="LR",E12,0)) -> 0 | I12: =IF(D12=TEXT,VALUE,IF(F12="NRC",D12,0)) -> 0 | J12: =IF(E12=TEXT,VALUE,IF(F12="NRC",E12,0)) -> 0
A13: 1-101-013 | B13: =VLOOKUP(A13,DAF_AKUN,2,FALSE) -> BAnk 4 | C13: =VLOOKUP(A13,DAF_AKUN,3,FALSE) -> Db | D13: =IF(AND(ISERROR=TRUE,C13="Db"),SUMIF(AKUN1,A13,AKUN2)+SUMIF(JURN2,"1"&A13,JURN3)-SUMIF(JURN2,"1"&A13,JURN4)+SUMIF(JURN1,A13&TEXT(BLN,"mmmm"),JURN3)-SUMIF(JURN1,A13&TEXT(BLN,"mmmm"),JURN4),VALUE) -> 0 | E13: =IF(AND(ISERROR=TRUE,C13="Kr"),SUMIF(AKUN1,A13,AKUN3)-SUMIF(JURN2,"1"&A13,JURN3)+SUMIF(JURN2,"1"&A13,JURN4)+SUMIF(JURN1,A13&TEXT(BLN,"mmmm"),JURN4)-SUMIF(JURN1,A13&TEXT(BLN,"mmmm"),JURN3),VALUE) -> 0 | F13: =VLOOKUP(A13,DAF_AKUN,4,FALSE) -> NRC | G13: =IF(D13=TEXT,VALUE,IF(F13="LR",D13,0)) -> 0 | H13: =IF(E13=TEXT,VALUE,IF(F13="LR",E13,0)) -> 0 | I13: =IF(D13=TEXT,VALUE,IF(F13="NRC",D13,0)) -> 0 | J13: =IF(E13=TEXT,VALUE,IF(F13="NRC",E13,0)) -> 0
A14: 1-101-100 | B14: =VLOOKUP(A14,DAF_AKUN,2,FALSE) -> Bank Deposit | C14: =VLOOKUP(A14,DAF_AKUN,3,FALSE) -> Db | D14: =IF(AND(ISERROR=TRUE,C14="Db"),SUMIF(AKUN1,A14,AKUN2)+SUMIF(JURN2,"1"&A14,JURN3)-SUMIF(JURN2,"1"&A14,JURN4)+SUMIF(JURN1,A14&TEXT(BLN,"mmmm"),JURN3)-SUMIF(JURN1,A14&TEXT(BLN,"mmmm"),JURN4),VALUE) -> 0 | E14: =IF(AND(ISERROR=TRUE,C14="Kr"),SUMIF(AKUN1,A14,AKUN3)-SUMIF(JURN2,"1"&A14,JURN3)+SUMIF(JURN2,"1"&A14,JURN4)+SUMIF(JURN1,A14&TEXT(BLN,"mmmm"),JURN4)-SUMIF(JURN1,A14&TEXT(BLN,"mmmm"),JURN3),VALUE) -> 0 | F14: =VLOOKUP(A14,DAF_AKUN,4,FALSE) -> NRC | G14: =IF(D14=TEXT,VALUE,IF(F14="LR",D14,0)) -> 0 | H14: =IF(E14=TEXT,VALUE,IF(F14="LR",E14,0)) -> 0 | I14: =IF(D14=TEXT,VALUE,IF(F14="NRC",D14,0)) -> 0 | J14: =IF(E14=TEXT,VALUE,IF(F14="NRC",E14,0)) -> 0
A15: 1-101-101 | B15: =VLOOKUP(A15,DAF_AKUN,2,FALSE) -> Others Deposit | C15: =VLOOKUP(A15,DAF_AKUN,3,FALSE) -> Db | D15: =IF(AND(ISERROR=TRUE,C15="Db"),SUMIF(AKUN1,A15,AKUN2)+SUMIF(JURN2,"1"&A15,JURN3)-SUMIF(JURN2,"1"&A15,JURN4)+SUMIF(JURN1,A15&TEXT(BLN,"mmmm"),JURN3)-SUMIF(JURN1,A15&TEXT(BLN,"mmmm"),JURN4),VALUE) -> 0 | E15: =IF(AND(ISERROR=TRUE,C15="Kr"),SUMIF(AKUN1,A15,AKUN3)-SUMIF(JURN2,"1"&A15,JURN3)+SUMIF(JURN2,"1"&A15,JURN4)+SUMIF(JURN1,A15&TEXT(BLN,"mmmm"),JURN4)-SUMIF(JURN1,A15&TEXT(BLN,"mmmm"),JURN3),VALUE) -> 0 | F15: =VLOOKUP(A15,DAF_AKUN,4,FALSE) -> NRC | G15: =IF(D15=TEXT,VALUE,IF(F15="LR",D15,0)) -> 0 | H15: =IF(E15=TEXT,VALUE,IF(F15="LR",E15,0)) -> 0 | I15: =IF(D15=TEXT,VALUE,IF(F15="NRC",D15,0)) -> 0 | J15: =IF(E15=TEXT,VALUE,IF(F15="NRC",E15,0)) -> 0
A16: 1-101-200 | B16: =VLOOKUP(A16,DAF_AKUN,2,FALSE) -> Cash In Transit | C16: =VLOOKUP(A16,DAF_AKUN,3,FALSE) -> Db | D16: =IF(AND(ISERROR=TRUE,C16="Db"),SUMIF(AKUN1,A16,AKUN2)+SUMIF(JURN2,"1"&A16,JURN3)-SUMIF(JURN2,"1"&A16,JURN4)+SUMIF(JURN1,A16&TEXT(BLN,"mmmm"),JURN3)-SUMIF(JURN1,A16&TEXT(BLN,"mmmm"),JURN4),VALUE) -> 0 | E16: =IF(AND(ISERROR=TRUE,C16="Kr"),SUMIF(AKUN1,A16,AKUN3)-SUMIF(JURN2,"1"&A16,JURN3)+SUMIF(JURN2,"1"&A16,JURN4)+SUMIF(JURN1,A16&TEXT(BLN,"mmmm"),JURN4)-SUMIF(JURN1,A16&TEXT(BLN,"mmmm"),JURN3),VALUE) -> 0 | F16: =VLOOKUP(A16,DAF_AKUN,4,FALSE) -> NRC | G16: =IF(D16=TEXT,VALUE,IF(F16="LR",D16,0)) -> 0 | H16: =IF(E16=TEXT,VALUE,IF(F16="LR",E16,0)) -> 0 | I16: =IF(D16=TEXT,VALUE,IF(F16="NRC",D16,0)) -> 0 | J16: =IF(E16=TEXT,VALUE,IF(F16="NRC",E16,0)) -> 0
A17: 1-102-000 | B17: =VLOOKUP(A17,DAF_AKUN,2,FALSE) -> Account Receivable | C17: =VLOOKUP(A17,DAF_AKUN,3,FALSE) -> Db | D17: =IF(AND(ISERROR=TRUE,C17="Db"),SUMIF(AKUN1,A17,AKUN2)+SUMIF(JURN2,"1"&A17,JURN3)-SUMIF(JURN2,"1"&A17,JURN4)+SUMIF(JURN1,A17&TEXT(BLN,"mmmm"),JURN3)-SUMIF(JURN1,A17&TEXT(BLN,"mmmm"),JURN4),VALUE) -> 0 | E17: =IF(AND(ISERROR=TRUE,C17="Kr"),SUMIF(AKUN1,A17,AKUN3)-SUMIF(JURN2,"1"&A17,JURN3)+SUMIF(JURN2,"1"&A17,JURN4)+SUMIF(JURN1,A17&TEXT(BLN,"mmmm"),JURN4)-SUMIF(JURN1,A17&TEXT(BLN,"mmmm"),JURN3),VALUE) -> 0 | F17: =VLOOKUP(A17,DAF_AKUN,4,FALSE) -> NRC | G17: =IF(D17=TEXT,VALUE,IF(F17="LR",D17,0)) -> 0 | H17: =IF(E17=TEXT,VALUE,IF(F17="LR",E17,0)) -> 0 | I17: =IF(D17=TEXT,VALUE,IF(F17="NRC",D17,0)) -> 0 | J17: =IF(E17=TEXT,VALUE,IF(F17="NRC",E17,0)) -> 0
A18: 1-102-001 | B18: =VLOOKUP(A18,DAF_AKUN,2,FALSE) -> Receivable - Trade | C18: =VLOOKUP(A18,DAF_AKUN,3,FALSE) -> Db | D18: =IF(AND(ISERROR=TRUE,C18="Db"),SUMIF(AKUN1,A18,AKUN2)+SUMIF(JURN2,"1"&A18,JURN3)-SUMIF(JURN2,"1"&A18,JURN4)+SUMIF(JURN1,A18&TEXT(BLN,"mmmm"),JURN3)-SUMIF(JURN1,A18&TEXT(BLN,"mmmm"),JURN4),VALUE) -> 277134525 | E18: =IF(AND(ISERROR=TRUE,C18="Kr"),SUMIF(AKUN1,A18,AKUN3)-SUMIF(JURN2,"1"&A18,JURN3)+SUMIF(JURN2,"1"&A18,JURN4)+SUMIF(JURN1,A18&TEXT(BLN,"mmmm"),JURN4)-SUMIF(JURN1,A18&TEXT(BLN,"mmmm"),JURN3),VALUE) -> 0 | F18: =VLOOKUP(A18,DAF_AKUN,4,FALSE) -> NRC | G18: =IF(D18=TEXT,VALUE,IF(F18="LR",D18,0)) -> 0 | H18: =IF(E18=TEXT,VALUE,IF(F18="LR",E18,0)) -> 0 | I18: =IF(D18=TEXT,VALUE,IF(F18="NRC",D18,0)) -> 277134525 | J18: =IF(E18=TEXT,VALUE,IF(F18="NRC",E18,0)) -> 0
A19: 1-102-002 | B19: =VLOOKUP(A19,DAF_AKUN,2,FALSE) -> Employee Receivable | C19: =VLOOKUP(A19,DAF_AKUN,3,FALSE) -> Db | D19: =IF(AND(ISERROR=TRUE,C19="Db"),SUMIF(AKUN1,A19,AKUN2)+SUMIF(JURN2,"1"&A19,JURN3)-SUMIF(JURN2,"1"&A19,JURN4)+SUMIF(JURN1,A19&TEXT(BLN,"mmmm"),JURN3)-SUMIF(JURN1,A19&TEXT(BLN,"mmmm"),JURN4),VALUE) -> 0 | E19: =IF(AND(ISERROR=TRUE,C19="Kr"),SUMIF(AKUN1,A19,AKUN3)-SUMIF(JURN2,"1"&A19,JURN3)+SUMIF(JURN2,"1"&A19,JURN4)+SUMIF(JURN1,A19&TEXT(BLN,"mmmm"),JURN4)-SUMIF(JURN1,A19&TEXT(BLN,"mmmm"),JURN3),VALUE) -> 0 | F19: =VLOOKUP(A19,DAF_AKUN,4,FALSE) -> NRC | G19: =IF(D19=TEXT,VALUE,IF(F19="LR",D19,0)) -> 0 | H19: =IF(E19=TEXT,VALUE,IF(F19="LR",E19,0)) -> 0 | I19: =IF(D19=TEXT,VALUE,IF(F19="NRC",D19,0)) -> 0 | J19: =IF(E19=TEXT,VALUE,IF(F19="NRC",E19,0)) -> 0
... A86: 3-102-003 | B86: =VLOOKUP(A86,DAF_AKUN,2,FALSE) -> Current Year Profit/(Loss) | C86: =VLOOKUP(A86,DAF_AKUN,3,FALSE) -> Kr | D86: =IF(AND(ISERROR=TRUE,C86="Db"),SUMIF(AKUN1,A86,AKUN2)+SUMIF(JURN2,"1"&A86,JURN3)-SUMIF(JURN2,"1"&A86,JURN4)+SUMIF(JURN1,A86&TEXT(BLN,"mmmm"),JURN3)-SUMIF(JURN1,A86&TEXT(BLN,"mmmm"),JURN4),VALUE) -> 0 | E86: =IF(AND(ISERROR=TRUE,C86="Kr"),SUMIF(AKUN1,A86,AKUN3)-SUMIF(JURN2,"1"&A86,JURN3)+SUMIF(JURN2,"1"&A86,JURN4)+SUMIF(JURN1,A86&TEXT(BLN,"mmmm"),JURN4)-SUMIF(JURN1,A86&TEXT(BLN,"mmmm"),JURN3),VALUE) -> 0 | F86: =VLOOKUP(A86,DAF_AKUN,4,FALSE) -> NRC | G86: =IF(D86=TEXT,VALUE,IF(F86="LR",D86,0)) -> 0 | H86: =IF(E86=TEXT,VALUE,IF(F86="LR",E86,0)) -> 0 | I86: =IF(D86=TEXT,VALUE,IF(F86="NRC",D86,0)) -> 0 | J86: =IF(E86=TEXT,VALUE,IF(F86="NRC",E86,0)) -> 0
A87: 3-102-004 | B87: Ekuitas Lainnya | C87: Kr | D87: =IF(AND(ISERROR=TRUE,C87="Db"),SUMIF(AKUN1,A87,AKUN2)+SUMIF(JURN2,"1"&A87,JURN3)-SUMIF(JURN2,"1"&A87,JURN4)+SUMIF(JURN1,A87&TEXT(BLN,"mmmm"),JURN3)-SUMIF(JURN1,A87&TEXT(BLN,"mmmm"),JURN4),VALUE) -> 0 | E87: =IF(AND(ISERROR=TRUE,C87="Kr"),SUMIF(AKUN1,A87,AKUN3)-SUMIF(JURN2,"1"&A87,JURN3)+SUMIF(JURN2,"1"&A87,JURN4)+SUMIF(JURN1,A87&TEXT(BLN,"mmmm"),JURN4)-SUMIF(JURN1,A87&TEXT(BLN,"mmmm"),JURN3),VALUE) -> 19663808 | F87: NRC | G87: =IF(D87=TEXT,VALUE,IF(F87="LR",D87,0)) -> 0 | H87: =IF(E87=TEXT,VALUE,IF(F87="LR",E87,0)) -> 0 | I87: =IF(D87=TEXT,VALUE,IF(F87="NRC",D87,0)) -> 0 | J87: =IF(E87=TEXT,VALUE,IF(F87="NRC",E87,0)) -> 19663808
A88: 4-100-000 | B88: =VLOOKUP(A88,DAF_AKUN,2,FALSE) -> Total Revenue | C88: =VLOOKUP(A88,DAF_AKUN,3,FALSE) -> Kr | D88: =IF(AND(ISERROR=TRUE,C88="Db"),SUMIF(AKUN1,A88,AKUN2)+SUMIF(JURN2,"1"&A88,JURN3)-SUMIF(JURN2,"1"&A88,JURN4)+SUMIF(JURN1,A88&TEXT(BLN,"mmmm"),JURN3)-SUMIF(JURN1,A88&TEXT(BLN,"mmmm"),JURN4),VALUE) -> 0 | E88: =IF(AND(ISERROR=TRUE,C88="Kr"),SUMIF(AKUN1,A88,AKUN3)-SUMIF(JURN2,"1"&A88,JURN3)+SUMIF(JURN2,"1"&A88,JURN4)+SUMIF(JURN1,A88&TEXT(BLN,"mmmm"),JURN4)-SUMIF(JURN1,A88&TEXT(BLN,"mmmm"),JURN3),VALUE) -> 0 | F88: =VLOOKUP(A88,DAF_AKUN,4,FALSE) -> LR | G88: =IF(D88=TEXT,VALUE,IF(F88="LR",D88,0)) -> 0 | H88: =IF(E88=TEXT,VALUE,IF(F88="LR",E88,0)) -> 0 | I88: =IF(D88=TEXT,VALUE,IF(F88="NRC",D88,0)) -> 0 | J88: =IF(E88=TEXT,VALUE,IF(F88="NRC",E88,0)) -> 0
A89: 4-101-000 | B89: =VLOOKUP(A89,DAF_AKUN,2,FALSE) -> Total Event Management Services Income | C89: =VLOOKUP(A89,DAF_AKUN,3,FALSE) -> Kr | D89: =IF(AND(ISERROR=TRUE,C89="Db"),SUMIF(AKUN1,A89,AKUN2)+SUMIF(JURN2,"1"&A89,JURN3)-SUMIF(JURN2,"1"&A89,JURN4)+SUMIF(JURN1,A89&TEXT(BLN,"mmmm"),JURN3)-SUMIF(JURN1,A89&TEXT(BLN,"mmmm"),JURN4),VALUE) -> 0 | E89: =IF(AND(ISERROR=TRUE,C89="Kr"),SUMIF(AKUN1,A89,AKUN3)-SUMIF(JURN2,"1"&A89,JURN3)+SUMIF(JURN2,"1"&A89,JURN4)+SUMIF(JURN1,A89&TEXT(BLN,"mmmm"),JURN4)-SUMIF(JURN1,A89&TEXT(BLN,"mmmm"),JURN3),VALUE) -> 0 | F89: =VLOOKUP(A89,DAF_AKUN,4,FALSE) -> LR | G89: =IF(D89=TEXT,VALUE,IF(F89="LR",D89,0)) -> 0 | H89: =IF(E89=TEXT,VALUE,IF(F89="LR",E89,0)) -> 0 | I89: =IF(D89=TEXT,VALUE,IF(F89="NRC",D89,0)) -> 0 | J89: =IF(E89=TEXT,VALUE,IF(F89="NRC",E89,0)) -> 0
A90: 4-101-001 | B90: =VLOOKUP(A90,DAF_AKUN,2,FALSE) -> Pendapatan Usaha | C90: =VLOOKUP(A90,DAF_AKUN,3,FALSE) -> Kr | D90: =IF(AND(ISERROR=TRUE,C90="Db"),SUMIF(AKUN1,A90,AKUN2)+SUMIF(JURN2,"1"&A90,JURN3)-SUMIF(JURN2,"1"&A90,JURN4)+SUMIF(JURN1,A90&TEXT(BLN,"mmmm"),JURN3)-SUMIF(JURN1,A90&TEXT(BLN,"mmmm"),JURN4),VALUE) -> 0 | E90: =IF(AND(ISERROR=TRUE,C90="Kr"),SUMIF(AKUN1,A90,AKUN3)-SUMIF(JURN2,"1"&A90,JURN3)+SUMIF(JURN2,"1"&A90,JURN4)+SUMIF(JURN1,A90&TEXT(BLN,"mmmm"),JURN4)-SUMIF(JURN1,A90&TEXT(BLN,"mmmm"),JURN3),VALUE) -> 310838800 | F90: =VLOOKUP(A90,DAF_AKUN,4,FALSE) -> LR | G90: =IF(D90=TEXT,VALUE,IF(F90="LR",D90,0)) -> 0 | H90: =IF(E90=TEXT,VALUE,IF(F90="LR",E90,0)) -> 310838800 | I90: =IF(D90=TEXT,VALUE,IF(F90="NRC",D90,0)) -> 0 | J90: =IF(E90=TEXT,VALUE,IF(F90="NRC",E90,0)) -> 0
A91: 4-101-002 | B91: =VLOOKUP(A91,DAF_AKUN,2,FALSE) -> Pendapatan .... | C91: =VLOOKUP(A91,DAF_AKUN,3,FALSE) -> Kr | D91: =IF(AND(ISERROR=TRUE,C91="Db"),SUMIF(AKUN1,A91,AKUN2)+SUMIF(JURN2,"1"&A91,JURN3)-SUMIF(JURN2,"1"&A91,JURN4)+SUMIF(JURN1,A91&TEXT(BLN,"mmmm"),JURN3)-SUMIF(JURN1,A91&TEXT(BLN,"mmmm"),JURN4),VALUE) -> 0 | E91: =IF(AND(ISERROR=TRUE,C91="Kr"),SUMIF(AKUN1,A91,AKUN3)-SUMIF(JURN2,"1"&A91,JURN3)+SUMIF(JURN2,"1"&A91,JURN4)+SUMIF(JURN1,A91&TEXT(BLN,"mmmm"),JURN4)-SUMIF(JURN1,A91&TEXT(BLN,"mmmm"),JURN3),VALUE) -> 0 | F91: =VLOOKUP(A91,DAF_AKUN,4,FALSE) -> LR | G91: =IF(D91=TEXT,VALUE,IF(F91="LR",D91,0)) -> 0 | H91: =IF(E91=TEXT,VALUE,IF(F91="LR",E91,0)) -> 0 | I91: =IF(D91=TEXT,VALUE,IF(F91="NRC",D91,0)) -> 0 | J91: =IF(E91=TEXT,VALUE,IF(F91="NRC",E91,0)) -> 0
A92: 4-101-003 | B92: =VLOOKUP(A92,DAF_AKUN,2,FALSE) -> Pendapatan .... | C92: =VLOOKUP(A92,DAF_AKUN,3,FALSE) -> Kr | D92: =IF(AND(ISERROR=TRUE,C92="Db"),SUMIF(AKUN1,A92,AKUN2)+SUMIF(JURN2,"1"&A92,JURN3)-SUMIF(JURN2,"1"&A92,JURN4)+SUMIF(JURN1,A92&TEXT(BLN,"mmmm"),JURN3)-SUMIF(JURN1,A92&TEXT(BLN,"mmmm"),JURN4),VALUE) -> 0 | E92: =IF(AND(ISERROR=TRUE,C92="Kr"),SUMIF(AKUN1,A92,AKUN3)-SUMIF(JURN2,"1"&A92,JURN3)+SUMIF(JURN2,"1"&A92,JURN4)+SUMIF(JURN1,A92&TEXT(BLN,"mmmm"),JURN4)-SUMIF(JURN1,A92&TEXT(BLN,"mmmm"),JURN3),VALUE) -> 0 | F92: =VLOOKUP(A92,DAF_AKUN,4,FALSE) -> LR | G92: =IF(D92=TEXT,VALUE,IF(F92="LR",D92,0)) -> 0 | H92: =IF(E92=TEXT,VALUE,IF(F92="LR",E92,0)) -> 0 | I92: =IF(D92=TEXT,VALUE,IF(F92="NRC",D92,0)) -> 0 | J92: =IF(E92=TEXT,VALUE,IF(F92="NRC",E92,0)) -> 0
A93: 4-101-004 | B93: =VLOOKUP(A93,DAF_AKUN,2,FALSE) -> Pendapatan .... | C93: =VLOOKUP(A93,DAF_AKUN,3,FALSE) -> Kr | D93: =IF(AND(ISERROR=TRUE,C93="Db"),SUMIF(AKUN1,A93,AKUN2)+SUMIF(JURN2,"1"&A93,JURN3)-SUMIF(JURN2,"1"&A93,JURN4)+SUMIF(JURN1,A93&TEXT(BLN,"mmmm"),JURN3)-SUMIF(JURN1,A93&TEXT(BLN,"mmmm"),JURN4),VALUE) -> 0 | E93: =IF(AND(ISERROR=TRUE,C93="Kr"),SUMIF(AKUN1,A93,AKUN3)-SUMIF(JURN2,"1"&A93,JURN3)+SUMIF(JURN2,"1"&A93,JURN4)+SUMIF(JURN1,A93&TEXT(BLN,"mmmm"),JURN4)-SUMIF(JURN1,A93&TEXT(BLN,"mmmm"),JURN3),VALUE) -> 0 | F93: =VLOOKUP(A93,DAF_AKUN,4,FALSE) -> LR | G93: =IF(D93=TEXT,VALUE,IF(F93="LR",D93,0)) -> 0 | H93: =IF(E93=TEXT,VALUE,IF(F93="LR",E93,0)) -> 0 | I93: =IF(D93=TEXT,VALUE,IF(F93="NRC",D93,0)) -> 0 | J93: =IF(E93=TEXT,VALUE,IF(F93="NRC",E93,0)) -> 0
A94: 4-101-005 | B94: =VLOOKUP(A94,DAF_AKUN,2,FALSE) -> Pendapatan .... | C94: =VLOOKUP(A94,DAF_AKUN,3,FALSE) -> Kr | D94: =IF(AND(ISERROR=TRUE,C94="Db"),SUMIF(AKUN1,A94,AKUN2)+SUMIF(JURN2,"1"&A94,JURN3)-SUMIF(JURN2,"1"&A94,JURN4)+SUMIF(JURN1,A94&TEXT(BLN,"mmmm"),JURN3)-SUMIF(JURN1,A94&TEXT(BLN,"mmmm"),JURN4),VALUE) -> 0 | E94: =IF(AND(ISERROR=TRUE,C94="Kr"),SUMIF(AKUN1,A94,AKUN3)-SUMIF(JURN2,"1"&A94,JURN3)+SUMIF(JURN2,"1"&A94,JURN4)+SUMIF(JURN1,A94&TEXT(BLN,"mmmm"),JURN4)-SUMIF(JURN1,A94&TEXT(BLN,"mmmm"),JURN3),VALUE) -> 0 | F94: =VLOOKUP(A94,DAF_AKUN,4,FALSE) -> LR | G94: =IF(D94=TEXT,VALUE,IF(F94="LR",D94,0)) -> 0 | H94: =IF(E94=TEXT,VALUE,IF(F94="LR",E94,0)) -> 0 | I94: =IF(D94=TEXT,VALUE,IF(F94="NRC",D94,0)) -> 0 | J94: =IF(E94=TEXT,VALUE,IF(F94="NRC",E94,0)) -> 0
A95: 4-101-006 | B95: =VLOOKUP(A95,DAF_AKUN,2,FALSE) -> Pendapatan .... | C95: =VLOOKUP(A95,DAF_AKUN,3,FALSE) -> Kr | D95: =IF(AND(ISERROR=TRUE,C95="Db"),SUMIF(AKUN1,A95,AKUN2)+SUMIF(JURN2,"1"&A95,JURN3)-SUMIF(JURN2,"1"&A95,JURN4)+SUMIF(JURN1,A95&TEXT(BLN,"mmmm"),JURN3)-SUMIF(JURN1,A95&TEXT(BLN,"mmmm"),JURN4),VALUE) -> 0 | E95: =IF(AND(ISERROR=TRUE,C95="Kr"),SUMIF(AKUN1,A95,AKUN3)-SUMIF(JURN2,"1"&A95,JURN3)+SUMIF(JURN2,"1"&A95,JURN4)+SUMIF(JURN1,A95&TEXT(BLN,"mmmm"),JURN4)-SUMIF(JURN1,A95&TEXT(BLN,"mmmm"),JURN3),VALUE) -> 0 | F95: =VLOOKUP(A95,DAF_AKUN,4,FALSE) -> LR | G95: =IF(D95=TEXT,VALUE,IF(F95="LR",D95,0)) -> 0 | H95: =IF(E95=TEXT,VALUE,IF(F95="LR",E95,0)) -> 0 | I95: =IF(D95=TEXT,VALUE,IF(F95="NRC",D95,0)) -> 0 | J95: =IF(E95=TEXT,VALUE,IF(F95="NRC",E95,0)) -> 0
A96: 4-101-007 | B96: =VLOOKUP(A96,DAF_AKUN,2,FALSE) -> Pendapatan .... | C96: =VLOOKUP(A96,DAF_AKUN,3,FALSE) -> Kr | D96: =IF(AND(ISERROR=TRUE,C96="Db"),SUMIF(AKUN1,A96,AKUN2)+SUMIF(JURN2,"1"&A96,JURN3)-SUMIF(JURN2,"1"&A96,JURN4)+SUMIF(JURN1,A96&TEXT(BLN,"mmmm"),JURN3)-SUMIF(JURN1,A96&TEXT(BLN,"mmmm"),JURN4),VALUE) -> 0 | E96: =IF(AND(ISERROR=TRUE,C96="Kr"),SUMIF(AKUN1,A96,AKUN3)-SUMIF(JURN2,"1"&A96,JURN3)+SUMIF(JURN2,"1"&A96,JURN4)+SUMIF(JURN1,A96&TEXT(BLN,"mmmm"),JURN4)-SUMIF(JURN1,A96&TEXT(BLN,"mmmm"),JURN3),VALUE) -> 0 | F96: =VLOOKUP(A96,DAF_AKUN,4,FALSE) -> LR | G96: =IF(D96=TEXT,VALUE,IF(F96="LR",D96,0)) -> 0 | H96: =IF(E96=TEXT,VALUE,IF(F96="LR",E96,0)) -> 0 | I96: =IF(D96=TEXT,VALUE,IF(F96="NRC",D96,0)) -> 0 | J96: =IF(E96=TEXT,VALUE,IF(F96="NRC",E96,0)) -> 0
A97: 4-101-008 | B97: =VLOOKUP(A97,DAF_AKUN,2,FALSE) -> Pendapatan .... | C97: =VLOOKUP(A97,DAF_AKUN,3,FALSE) -> Kr | D97: =IF(AND(ISERROR=TRUE,C97="Db"),SUMIF(AKUN1,A97,AKUN2)+SUMIF(JURN2,"1"&A97,JURN3)-SUMIF(JURN2,"1"&A97,JURN4)+SUMIF(JURN1,A97&TEXT(BLN,"mmmm"),JURN3)-SUMIF(JURN1,A97&TEXT(BLN,"mmmm"),JURN4),VALUE) -> 0 | E97: =IF(AND(ISERROR=TRUE,C97="Kr"),SUMIF(AKUN1,A97,AKUN3)-SUMIF(JURN2,"1"&A97,JURN3)+SUMIF(JURN2,"1"&A97,JURN4)+SUMIF(JURN1,A97&TEXT(BLN,"mmmm"),JURN4)-SUMIF(JURN1,A97&TEXT(BLN,"mmmm"),JURN3),VALUE) -> 0 | F97: =VLOOKUP(A97,DAF_AKUN,4,FALSE) -> LR | G97: =IF(D97=TEXT,VALUE,IF(F97="LR",D97,0)) -> 0 | H97: =IF(E97=TEXT,VALUE,IF(F97="LR",E97,0)) -> 0 | I97: =IF(D97=TEXT,VALUE,IF(F97="NRC",D97,0)) -> 0 | J97: =IF(E97=TEXT,VALUE,IF(F97="NRC",E97,0)) -> 0
A98: 4-101-020 | B98: =VLOOKUP(A98,DAF_AKUN,2,FALSE) -> Pendapatan .... | C98: =VLOOKUP(A98,DAF_AKUN,3,FALSE) -> Kr | D98: =IF(AND(ISERROR=TRUE,C98="Db"),SUMIF(AKUN1,A98,AKUN2)+SUMIF(JURN2,"1"&A98,JURN3)-SUMIF(JURN2,"1"&A98,JURN4)+SUMIF(JURN1,A98&TEXT(BLN,"mmmm"),JURN3)-SUMIF(JURN1,A98&TEXT(BLN,"mmmm"),JURN4),VALUE) -> 0 | E98: =IF(AND(ISERROR=TRUE,C98="Kr"),SUMIF(AKUN1,A98,AKUN3)-SUMIF(JURN2,"1"&A98,JURN3)+SUMIF(JURN2,"1"&A98,JURN4)+SUMIF(JURN1,A98&TEXT(BLN,"mmmm"),JURN4)-SUMIF(JURN1,A98&TEXT(BLN,"mmmm"),JURN3),VALUE) -> 0 | F98: =VLOOKUP(A98,DAF_AKUN,4,FALSE) -> LR | G98: =IF(D98=TEXT,VALUE,IF(F98="LR",D98,0)) -> 0 | H98: =IF(E98=TEXT,VALUE,IF(F98="LR",E98,0)) -> 0 | I98: =IF(D98=TEXT,VALUE,IF(F98="NRC",D98,0)) -> 0 | J98: =IF(E98=TEXT,VALUE,IF(F98="NRC",E98,0)) -> 0
A99: 4-101-100 | B99: =VLOOKUP(A99,DAF_AKUN,2,FALSE) -> Agency Service Fee | C99: =VLOOKUP(A99,DAF_AKUN,3,FALSE) -> Kr | D99: =IF(AND(ISERROR=TRUE,C99="Db"),SUMIF(AKUN1,A99,AKUN2)+SUMIF(JURN2,"1"&A99,JURN3)-SUMIF(JURN2,"1"&A99,JURN4)+SUMIF(JURN1,A99&TEXT(BLN,"mmmm"),JURN3)-SUMIF(JURN1,A99&TEXT(BLN,"mmmm"),JURN4),VALUE) -> 0 | E99: =IF(AND(ISERROR=TRUE,C99="Kr"),SUMIF(AKUN1,A99,AKUN3)-SUMIF(JURN2,"1"&A99,JURN3)+SUMIF(JURN2,"1"&A99,JURN4)+SUMIF(JURN1,A99&TEXT(BLN,"mmmm"),JURN4)-SUMIF(JURN1,A99&TEXT(BLN,"mmmm"),JURN3),VALUE) -> 0 | F99: =VLOOKUP(A99,DAF_AKUN,4,FALSE) -> LR | G99: =IF(D99=TEXT,VALUE,IF(F99="LR",D99,0)) -> 0 | H99: =IF(E99=TEXT,VALUE,IF(F99="LR",E99,0)) -> 0 | I99: =IF(D99=TEXT,VALUE,IF(F99="NRC",D99,0)) -> 0 | J99: =IF(E99=TEXT,VALUE,IF(F99="NRC",E99,0)) -> 0
... A200: 9-102-001 | B200: =VLOOKUP(A200,DAF_AKUN,2,FALSE) -> Dividend Expense | C200: =VLOOKUP(A200,DAF_AKUN,3,FALSE) -> Db | D200: =IF(AND(ISERROR=TRUE,C200="Db"),SUMIF(AKUN1,A200,AKUN2)+SUMIF(JURN2,"1"&A200,JURN3)-SUMIF(JURN2,"1"&A200,JURN4)+SUMIF(JURN1,A200&TEXT(BLN,"mmmm"),JURN3)-SUMIF(JURN1,A200&TEXT(BLN,"mmmm"),JURN4),VALUE) -> 0 | E200: =IF(AND(ISERROR=TRUE,C200="Kr"),SUMIF(AKUN1,A200,AKUN3)-SUMIF(JURN2,"1"&A200,JURN3)+SUMIF(JURN2,"1"&A200,JURN4)+SUMIF(JURN1,A200&TEXT(BLN,"mmmm"),JURN4)-SUMIF(JURN1,A200&TEXT(BLN,"mmmm"),JURN3),VALUE) -> 0 | F200: =VLOOKUP(A200,DAF_AKUN,4,FALSE) -> LR | G200: =IF(D200=TEXT,VALUE,IF(F200="LR",D200,0)) -> 0 | H200: =IF(E200=TEXT,VALUE,IF(F200="LR",E200,0)) -> 0 | I200: =IF(D200=TEXT,VALUE,IF(F200="NRC",D200,0)) -> 0 | J200: =IF(E200=TEXT,VALUE,IF(F200="NRC",E200,0)) -> 0
B203: Jumlah | D203: =SUM(D7:D202) -> 336505308 | E203: =SUM(E7:E202) -> 336505308 | G203: =SUM(G7:G202) -> 47253253 | H203: =SUM(H7:H202) -> 310838800 | I203: =SUM(I7:I202) -> 289252055 | J203: =SUM(J7:J202) -> 25666508
B204: Laba (Rugi) Bersih | H204: =H203-G203 -> 263585547 | J204: =H204 -> 263585547
B205: Jumlah | I205: =SUM(I203:I204) -> 289252055 | J205: =SUM(J203:J204) -> 289252055
E206: =D203-E203 -> 0

Sheet Index
A1: =DATE(0,B1,1) -> 1 | B1: 1 | D1: =IF(User!D6=D4,0,"#") -> 0 | F1: =IF(OR(INDEX(Kode!C:C,0,1)="Piutang",INDEX(Kode!C:C,0,1)="Hutang"),INDEX(Kode!A:A,0,1),"") | G1: =IF(OR(INDEX(Akun!C:C,0,1)="Db",INDEX(Akun!C:C,0,1)="Kr"),INDEX(Akun!A:A,0,1),"")
A2: =DATE(0,B2,1) -> 32 | B2: 2 | D2: =User!D6=D4 -> TRUE | F2: =IF(OR(INDEX(Kode!C:C,0,1)="Piutang",INDEX(Kode!C:C,0,1)="Hutang"),INDEX(Kode!A:A,0,1),"") | G2: =IF(OR(INDEX(Akun!C:C,0,1)="Db",INDEX(Akun!C:C,0,1)="Kr"),INDEX(Akun!A:A,0,1),"")
A3: =DATE(0,B3,1) -> 61 | B3: 3 | D3: =IF(User!D6=D4,"-","#") -> - | F3: =IF(OR(INDEX(Kode!C:C,0,1)="Piutang",INDEX(Kode!C:C,0,1)="Hutang"),INDEX(Kode!A:A,0,1),"") | G3: =IF(OR(INDEX(Akun!C:C,0,1)="Db",INDEX(Akun!C:C,0,1)="Kr"),INDEX(Akun!A:A,0,1),"")
A4: =DATE(0,B4,1) -> 92 | B4: 4 | D4: GL-2468907531-XCL | F4: =IF(OR(INDEX(Kode!C:C,0,1)="Piutang",INDEX(Kode!C:C,0,1)="Hutang"),INDEX(Kode!A:A,0,1),"") | G4: =IF(OR(INDEX(Akun!C:C,0,1)="Db",INDEX(Akun!C:C,0,1)="Kr"),INDEX(Akun!A:A,0,1),"")
A5: =DATE(0,B5,1) -> 122 | B5: 5 | F5: =IF(OR(INDEX(Kode!C:C,0,1)="Piutang",INDEX(Kode!C:C,0,1)="Hutang"),INDEX(Kode!A:A,0,1),"") | G5: =IF(OR(INDEX(Akun!C:C,0,1)="Db",INDEX(Akun!C:C,0,1)="Kr"),INDEX(Akun!A:A,0,1),"")
A6: =DATE(0,B6,1) -> 153 | B6: 6 | F6: =IF(OR(INDEX(Kode!C:C,0,1)="Piutang",INDEX(Kode!C:C,0,1)="Hutang"),INDEX(Kode!A:A,0,1),"") | G6: =IF(OR(INDEX(Akun!C:C,0,1)="Db",INDEX(Akun!C:C,0,1)="Kr"),INDEX(Akun!A:A,0,1),"")
A7: =DATE(0,B7,1) -> 183 | B7: 7 | F7: =IF(OR(INDEX(Kode!C:C,0,1)="Piutang",INDEX(Kode!C:C,0,1)="Hutang"),INDEX(Kode!A:A,0,1),"") | G7: =IF(OR(INDEX(Akun!C:C,0,1)="Db",INDEX(Akun!C:C,0,1)="Kr"),INDEX(Akun!A:A,0,1),"")
A8: =DATE(0,B8,1) -> 214 | B8: 8 | F8: =IF(OR(INDEX(Kode!C:C,0,1)="Piutang",INDEX(Kode!C:C,0,1)="Hutang"),INDEX(Kode!A:A,0,1),"") | G8: =IF(OR(INDEX(Akun!C:C,0,1)="Db",INDEX(Akun!C:C,0,1)="Kr"),INDEX(Akun!A:A,0,1),"")
A9: =DATE(0,B9,1) -> 245 | B9: 9 | F9: =IF(OR(INDEX(Kode!C:C,0,1)="Piutang",INDEX(Kode!C:C,0,1)="Hutang"),INDEX(Kode!A:A,0,1),"") | G9: =IF(OR(INDEX(Akun!C:C,0,1)="Db",INDEX(Akun!C:C,0,1)="Kr"),INDEX(Akun!A:A,0,1),"") -> 1-101-000
A10: =DATE(0,B10,1) -> 275 | B10: 10 | F10: =IF(OR(INDEX(Kode!C:C,0,1)="Piutang",INDEX(Kode!C:C,0,1)="Hutang"),INDEX(Kode!A:A,0,1),"") | G10: =IF(OR(INDEX(Akun!C:C,0,1)="Db",INDEX(Akun!C:C,0,1)="Kr"),INDEX(Akun!A:A,0,1),"") -> 1-101-001
A11: =DATE(0,B11,1) -> 306 | B11: 11 | F11: =IF(OR(INDEX(Kode!C:C,0,1)="Piutang",INDEX(Kode!C:C,0,1)="Hutang"),INDEX(Kode!A:A,0,1),"") | G11: =IF(OR(INDEX(Akun!C:C,0,1)="Db",INDEX(Akun!C:C,0,1)="Kr"),INDEX(Akun!A:A,0,1),"") -> 1-101-010
A12: =DATE(0,B12,1) -> 336 | B12: 12 | F12: =IF(OR(INDEX(Kode!C:C,0,1)="Piutang",INDEX(Kode!C:C,0,1)="Hutang"),INDEX(Kode!A:A,0,1),"") | G12: =IF(OR(INDEX(Akun!C:C,0,1)="Db",INDEX(Akun!C:C,0,1)="Kr"),INDEX(Akun!A:A,0,1),"") -> 1-101-011
F13: =IF(OR(INDEX(Kode!C:C,0,1)="Piutang",INDEX(Kode!C:C,0,1)="Hutang"),INDEX(Kode!A:A,0,1),"") | G13: =IF(OR(INDEX(Akun!C:C,0,1)="Db",INDEX(Akun!C:C,0,1)="Kr"),INDEX(Akun!A:A,0,1),"") -> 1-101-012
F14: =IF(OR(INDEX(Kode!C:C,0,1)="Piutang",INDEX(Kode!C:C,0,1)="Hutang"),INDEX(Kode!A:A,0,1),"") | G14: =IF(OR(INDEX(Akun!C:C,0,1)="Db",INDEX(Akun!C:C,0,1)="Kr"),INDEX(Akun!A:A,0,1),"") -> 1-101-013
F15: =IF(OR(INDEX(Kode!C:C,0,1)="Piutang",INDEX(Kode!C:C,0,1)="Hutang"),INDEX(Kode!A:A,0,1),"") | G15: =IF(OR(INDEX(Akun!C:C,0,1)="Db",INDEX(Akun!C:C,0,1)="Kr"),INDEX(Akun!A:A,0,1),"") -> 1-101-100
F16: =IF(OR(INDEX(Kode!C:C,0,1)="Piutang",INDEX(Kode!C:C,0,1)="Hutang"),INDEX(Kode!A:A,0,1),"") | G16: =IF(OR(INDEX(Akun!C:C,0,1)="Db",INDEX(Akun!C:C,0,1)="Kr"),INDEX(Akun!A:A,0,1),"") -> 1-101-101
F17: =IF(OR(INDEX(Kode!C:C,0,1)="Piutang",INDEX(Kode!C:C,0,1)="Hutang"),INDEX(Kode!A:A,0,1),"") | G17: =IF(OR(INDEX(Akun!C:C,0,1)="Db",INDEX(Akun!C:C,0,1)="Kr"),INDEX(Akun!A:A,0,1),"") -> 1-101-200
F18: =IF(OR(INDEX(Kode!C:C,0,1)="Piutang",INDEX(Kode!C:C,0,1)="Hutang"),INDEX(Kode!A:A,0,1),"") -> CT-001 | G18: =IF(OR(INDEX(Akun!C:C,0,1)="Db",INDEX(Akun!C:C,0,1)="Kr"),INDEX(Akun!A:A,0,1),"") -> 1-102-000
F19: =IF(OR(INDEX(Kode!C:C,0,1)="Piutang",INDEX(Kode!C:C,0,1)="Hutang"),INDEX(Kode!A:A,0,1),"") -> CT-002 | G19: =IF(OR(INDEX(Akun!C:C,0,1)="Db",INDEX(Akun!C:C,0,1)="Kr"),INDEX(Akun!A:A,0,1),"") -> 1-102-001
F20: =IF(OR(INDEX(Kode!C:C,0,1)="Piutang",INDEX(Kode!C:C,0,1)="Hutang"),INDEX(Kode!A:A,0,1),"") -> CT-003 | G20: =IF(OR(INDEX(Akun!C:C,0,1)="Db",INDEX(Akun!C:C,0,1)="Kr"),INDEX(Akun!A:A,0,1),"") -> 1-102-002
F21: =IF(OR(INDEX(Kode!C:C,0,1)="Piutang",INDEX(Kode!C:C,0,1)="Hutang"),INDEX(Kode!A:A,0,1),"") -> SH-001 | G21: =IF(OR(INDEX(Akun!C:C,0,1)="Db",INDEX(Akun!C:C,0,1)="Kr"),INDEX(Akun!A:A,0,1),"") -> 1-102-003
F22: =IF(OR(INDEX(Kode!C:C,0,1)="Piutang",INDEX(Kode!C:C,0,1)="Hutang"),INDEX(Kode!A:A,0,1),"") -> SH-002 | G22: =IF(OR(INDEX(Akun!C:C,0,1)="Db",INDEX(Akun!C:C,0,1)="Kr"),INDEX(Akun!A:A,0,1),"") -> 1-102-004
F23: =IF(OR(INDEX(Kode!C:C,0,1)="Piutang",INDEX(Kode!C:C,0,1)="Hutang"),INDEX(Kode!A:A,0,1),"") -> SH-003 | G23: =IF(OR(INDEX(Akun!C:C,0,1)="Db",INDEX(Akun!C:C,0,1)="Kr"),INDEX(Akun!A:A,0,1),"") -> 1-103-000
F24: =IF(OR(INDEX(Kode!C:C,0,1)="Piutang",INDEX(Kode!C:C,0,1)="Hutang"),INDEX(Kode!A:A,0,1),"") -> SH-004 | G24: =IF(OR(INDEX(Akun!C:C,0,1)="Db",INDEX(Akun!C:C,0,1)="Kr"),INDEX(Akun!A:A,0,1),"") -> 1-104-000
... F300: =IF(OR(INDEX(Kode!C:C,0,1)="Piutang",INDEX(Kode!C:C,0,1)="Hutang"),INDEX(Kode!A:A,0,1),"") | G300: =IF(OR(INDEX(Akun!C:C,0,1)="Db",INDEX(Akun!C:C,0,1)="Kr"),INDEX(Akun!A:A,0,1),"")

Sheet Laba Rugi
A1: =NAMA -> ARYA USAHA TIRTA, CV
A2: LABA RUGI
A3: ="Bulan : "&TEXT(BLN,"mmmm")&" "&THN -> Bulan : July 2026
A5: Kode | B5: Nama Akun | C5: Saldo Bulan | D5: Bulan | E5: S/d Bulan
A6: Akun | C6: Lalu | D6: =BLN -> 183 | E6: =BLN -> 183
A8: 4-100-000 | B8: =VLOOKUP(A8,DAF_AKUN,2,FALSE) -> Total Revenue | C8: =IF(ISERROR=TRUE,IF(VLOOKUP(A8,DAF_AKUN,3,FALSE)="Db",SUMIF(AKUN1,A8,AKUN2)+SUMIF(JURN2,"1"&A8,JURN3)-SUMIF(JURN2,"1"&A8,JURN4),SUMIF(AKUN1,A8,AKUN3)-SUMIF(JURN2,"1"&A8,JURN3)+SUMIF(JURN2,"1"&A8,JURN4)),VALUE) -> 0 | D8: =IF(ISERROR=TRUE,IF(VLOOKUP(A8,DAF_AKUN,3,FALSE)="Db",SUMIF(JURN1,A8&TEXT(BLN,"mmmm"),JURN3)-SUMIF(JURN1,A8&TEXT(BLN,"mmmm"),JURN4),SUMIF(JURN1,A8&TEXT(BLN,"mmmm"),JURN4)-SUMIF(JURN1,A8&TEXT(BLN,"mmmm"),JURN3)),VALUE) -> 0 | E8: =C8+D8 -> 0
A9: 4-101-000 | B9: =VLOOKUP(A9,DAF_AKUN,2,FALSE) -> Total Event Management Services Income | C9: =IF(ISERROR=TRUE,IF(VLOOKUP(A9,DAF_AKUN,3,FALSE)="Db",SUMIF(AKUN1,A9,AKUN2)+SUMIF(JURN2,"1"&A9,JURN3)-SUMIF(JURN2,"1"&A9,JURN4),SUMIF(AKUN1,A9,AKUN3)-SUMIF(JURN2,"1"&A9,JURN3)+SUMIF(JURN2,"1"&A9,JURN4)),VALUE) -> 0 | D9: =IF(ISERROR=TRUE,IF(VLOOKUP(A9,DAF_AKUN,3,FALSE)="Db",SUMIF(JURN1,A9&TEXT(BLN,"mmmm"),JURN3)-SUMIF(JURN1,A9&TEXT(BLN,"mmmm"),JURN4),SUMIF(JURN1,A9&TEXT(BLN,"mmmm"),JURN4)-SUMIF(JURN1,A9&TEXT(BLN,"mmmm"),JURN3)),VALUE) -> 0 | E9: =C9+D9 -> 0
A10: 4-101-001 | B10: =VLOOKUP(A10,DAF_AKUN,2,FALSE) -> Pendapatan Usaha | C10: =IF(ISERROR=TRUE,IF(VLOOKUP(A10,DAF_AKUN,3,FALSE)="Db",SUMIF(AKUN1,A10,AKUN2)+SUMIF(JURN2,"1"&A10,JURN3)-SUMIF(JURN2,"1"&A10,JURN4),SUMIF(AKUN1,A10,AKUN3)-SUMIF(JURN2,"1"&A10,JURN3)+SUMIF(JURN2,"1"&A10,JURN4)),VALUE) -> 231360650 | D10: =IF(ISERROR=TRUE,IF(VLOOKUP(A10,DAF_AKUN,3,FALSE)="Db",SUMIF(JURN1,A10&TEXT(BLN,"mmmm"),JURN3)-SUMIF(JURN1,A10&TEXT(BLN,"mmmm"),JURN4),SUMIF(JURN1,A10&TEXT(BLN,"mmmm"),JURN4)-SUMIF(JURN1,A10&TEXT(BLN,"mmmm"),JURN3)),VALUE) -> 79478150 | E10: =C10+D10 -> 310838800
A11: 4-101-002 | B11: =VLOOKUP(A11,DAF_AKUN,2,FALSE) -> Pendapatan .... | C11: =IF(ISERROR=TRUE,IF(VLOOKUP(A11,DAF_AKUN,3,FALSE)="Db",SUMIF(AKUN1,A11,AKUN2)+SUMIF(JURN2,"1"&A11,JURN3)-SUMIF(JURN2,"1"&A11,JURN4),SUMIF(AKUN1,A11,AKUN3)-SUMIF(JURN2,"1"&A11,JURN3)+SUMIF(JURN2,"1"&A11,JURN4)),VALUE) -> 0 | D11: =IF(ISERROR=TRUE,IF(VLOOKUP(A11,DAF_AKUN,3,FALSE)="Db",SUMIF(JURN1,A11&TEXT(BLN,"mmmm"),JURN3)-SUMIF(JURN1,A11&TEXT(BLN,"mmmm"),JURN4),SUMIF(JURN1,A11&TEXT(BLN,"mmmm"),JURN4)-SUMIF(JURN1,A11&TEXT(BLN,"mmmm"),JURN3)),VALUE) -> 0 | E11: =C11+D11 -> 0
A12: 4-101-003 | B12: =VLOOKUP(A12,DAF_AKUN,2,FALSE) -> Pendapatan .... | C12: =IF(ISERROR=TRUE,IF(VLOOKUP(A12,DAF_AKUN,3,FALSE)="Db",SUMIF(AKUN1,A12,AKUN2)+SUMIF(JURN2,"1"&A12,JURN3)-SUMIF(JURN2,"1"&A12,JURN4),SUMIF(AKUN1,A12,AKUN3)-SUMIF(JURN2,"1"&A12,JURN3)+SUMIF(JURN2,"1"&A12,JURN4)),VALUE) -> 0 | D12: =IF(ISERROR=TRUE,IF(VLOOKUP(A12,DAF_AKUN,3,FALSE)="Db",SUMIF(JURN1,A12&TEXT(BLN,"mmmm"),JURN3)-SUMIF(JURN1,A12&TEXT(BLN,"mmmm"),JURN4),SUMIF(JURN1,A12&TEXT(BLN,"mmmm"),JURN4)-SUMIF(JURN1,A12&TEXT(BLN,"mmmm"),JURN3)),VALUE) -> 0 | E12: =C12+D12 -> 0
A13: 4-101-004 | B13: =VLOOKUP(A13,DAF_AKUN,2,FALSE) -> Pendapatan .... | C13: =IF(ISERROR=TRUE,IF(VLOOKUP(A13,DAF_AKUN,3,FALSE)="Db",SUMIF(AKUN1,A13,AKUN2)+SUMIF(JURN2,"1"&A13,JURN3)-SUMIF(JURN2,"1"&A13,JURN4),SUMIF(AKUN1,A13,AKUN3)-SUMIF(JURN2,"1"&A13,JURN3)+SUMIF(JURN2,"1"&A13,JURN4)),VALUE) -> 0 | D13: =IF(ISERROR=TRUE,IF(VLOOKUP(A13,DAF_AKUN,3,FALSE)="Db",SUMIF(JURN1,A13&TEXT(BLN,"mmmm"),JURN3)-SUMIF(JURN1,A13&TEXT(BLN,"mmmm"),JURN4),SUMIF(JURN1,A13&TEXT(BLN,"mmmm"),JURN4)-SUMIF(JURN1,A13&TEXT(BLN,"mmmm"),JURN3)),VALUE) -> 0 | E13: =C13+D13 -> 0
A14: 4-101-005 | B14: =VLOOKUP(A14,DAF_AKUN,2,FALSE) -> Pendapatan .... | C14: =IF(ISERROR=TRUE,IF(VLOOKUP(A14,DAF_AKUN,3,FALSE)="Db",SUMIF(AKUN1,A14,AKUN2)+SUMIF(JURN2,"1"&A14,JURN3)-SUMIF(JURN2,"1"&A14,JURN4),SUMIF(AKUN1,A14,AKUN3)-SUMIF(JURN2,"1"&A14,JURN3)+SUMIF(JURN2,"1"&A14,JURN4)),VALUE) -> 0 | D14: =IF(ISERROR=TRUE,IF(VLOOKUP(A14,DAF_AKUN,3,FALSE)="Db",SUMIF(JURN1,A14&TEXT(BLN,"mmmm"),JURN3)-SUMIF(JURN1,A14&TEXT(BLN,"mmmm"),JURN4),SUMIF(JURN1,A14&TEXT(BLN,"mmmm"),JURN4)-SUMIF(JURN1,A14&TEXT(BLN,"mmmm"),JURN3)),VALUE) -> 0 | E14: =C14+D14 -> 0
A15: 4-101-006 | B15: =VLOOKUP(A15,DAF_AKUN,2,FALSE) -> Pendapatan .... | C15: =IF(ISERROR=TRUE,IF(VLOOKUP(A15,DAF_AKUN,3,FALSE)="Db",SUMIF(AKUN1,A15,AKUN2)+SUMIF(JURN2,"1"&A15,JURN3)-SUMIF(JURN2,"1"&A15,JURN4),SUMIF(AKUN1,A15,AKUN3)-SUMIF(JURN2,"1"&A15,JURN3)+SUMIF(JURN2,"1"&A15,JURN4)),VALUE) -> 0 | D15: =IF(ISERROR=TRUE,IF(VLOOKUP(A15,DAF_AKUN,3,FALSE)="Db",SUMIF(JURN1,A15&TEXT(BLN,"mmmm"),JURN3)-SUMIF(JURN1,A15&TEXT(BLN,"mmmm"),JURN4),SUMIF(JURN1,A15&TEXT(BLN,"mmmm"),JURN4)-SUMIF(JURN1,A15&TEXT(BLN,"mmmm"),JURN3)),VALUE) -> 0 | E15: =C15+D15 -> 0
A16: 4-101-007 | B16: =VLOOKUP(A16,DAF_AKUN,2,FALSE) -> Pendapatan .... | C16: =IF(ISERROR=TRUE,IF(VLOOKUP(A16,DAF_AKUN,3,FALSE)="Db",SUMIF(AKUN1,A16,AKUN2)+SUMIF(JURN2,"1"&A16,JURN3)-SUMIF(JURN2,"1"&A16,JURN4),SUMIF(AKUN1,A16,AKUN3)-SUMIF(JURN2,"1"&A16,JURN3)+SUMIF(JURN2,"1"&A16,JURN4)),VALUE) -> 0 | D16: =IF(ISERROR=TRUE,IF(VLOOKUP(A16,DAF_AKUN,3,FALSE)="Db",SUMIF(JURN1,A16&TEXT(BLN,"mmmm"),JURN3)-SUMIF(JURN1,A16&TEXT(BLN,"mmmm"),JURN4),SUMIF(JURN1,A16&TEXT(BLN,"mmmm"),JURN4)-SUMIF(JURN1,A16&TEXT(BLN,"mmmm"),JURN3)),VALUE) -> 0 | E16: =C16+D16 -> 0
A17: 4-101-008 | B17: =VLOOKUP(A17,DAF_AKUN,2,FALSE) -> Pendapatan .... | C17: =IF(ISERROR=TRUE,IF(VLOOKUP(A17,DAF_AKUN,3,FALSE)="Db",SUMIF(AKUN1,A17,AKUN2)+SUMIF(JURN2,"1"&A17,JURN3)-SUMIF(JURN2,"1"&A17,JURN4),SUMIF(AKUN1,A17,AKUN3)-SUMIF(JURN2,"1"&A17,JURN3)+SUMIF(JURN2,"1"&A17,JURN4)),VALUE) -> 0 | D17: =IF(ISERROR=TRUE,IF(VLOOKUP(A17,DAF_AKUN,3,FALSE)="Db",SUMIF(JURN1,A17&TEXT(BLN,"mmmm"),JURN3)-SUMIF(JURN1,A17&TEXT(BLN,"mmmm"),JURN4),SUMIF(JURN1,A17&TEXT(BLN,"mmmm"),JURN4)-SUMIF(JURN1,A17&TEXT(BLN,"mmmm"),JURN3)),VALUE) -> 0 | E17: =C17+D17 -> 0
A18: 4-101-020 | B18: =VLOOKUP(A18,DAF_AKUN,2,FALSE) -> Pendapatan .... | C18: =IF(ISERROR=TRUE,IF(VLOOKUP(A18,DAF_AKUN,3,FALSE)="Db",SUMIF(AKUN1,A18,AKUN2)+SUMIF(JURN2,"1"&A18,JURN3)-SUMIF(JURN2,"1"&A18,JURN4),SUMIF(AKUN1,A18,AKUN3)-SUMIF(JURN2,"1"&A18,JURN3)+SUMIF(JURN2,"1"&A18,JURN4)),VALUE) -> 0 | D18: =IF(ISERROR=TRUE,IF(VLOOKUP(A18,DAF_AKUN,3,FALSE)="Db",SUMIF(JURN1,A18&TEXT(BLN,"mmmm"),JURN3)-SUMIF(JURN1,A18&TEXT(BLN,"mmmm"),JURN4),SUMIF(JURN1,A18&TEXT(BLN,"mmmm"),JURN4)-SUMIF(JURN1,A18&TEXT(BLN,"mmmm"),JURN3)),VALUE) -> 0 | E18: =C18+D18 -> 0
A19: 4-101-100 | B19: =VLOOKUP(A19,DAF_AKUN,2,FALSE) -> Agency Service Fee | C19: =IF(ISERROR=TRUE,IF(VLOOKUP(A19,DAF_AKUN,3,FALSE)="Db",SUMIF(AKUN1,A19,AKUN2)+SUMIF(JURN2,"1"&A19,JURN3)-SUMIF(JURN2,"1"&A19,JURN4),SUMIF(AKUN1,A19,AKUN3)-SUMIF(JURN2,"1"&A19,JURN3)+SUMIF(JURN2,"1"&A19,JURN4)),VALUE) -> 0 | D19: =IF(ISERROR=TRUE,IF(VLOOKUP(A19,DAF_AKUN,3,FALSE)="Db",SUMIF(JURN1,A19&TEXT(BLN,"mmmm"),JURN3)-SUMIF(JURN1,A19&TEXT(BLN,"mmmm"),JURN4),SUMIF(JURN1,A19&TEXT(BLN,"mmmm"),JURN4)-SUMIF(JURN1,A19&TEXT(BLN,"mmmm"),JURN3)),VALUE) -> 0 | E19: =C19+D19 -> 0
... A35: 4-402-001 | B35: =VLOOKUP(A35,DAF_AKUN,2,FALSE) -> Pendapatan Belum Ditagih | C35: =IF(ISERROR=TRUE,IF(VLOOKUP(A35,DAF_AKUN,3,FALSE)="Db",SUMIF(AKUN1,A35,AKUN2)+SUMIF(JURN2,"1"&A35,JURN3)-SUMIF(JURN2,"1"&A35,JURN4),SUMIF(AKUN1,A35,AKUN3)-SUMIF(JURN2,"1"&A35,JURN3)+SUMIF(JURN2,"1"&A35,JURN4)),VALUE) -> 0 | D35: =IF(ISERROR=TRUE,IF(VLOOKUP(A35,DAF_AKUN,3,FALSE)="Db",SUMIF(JURN1,A35&TEXT(BLN,"mmmm"),JURN3)-SUMIF(JURN1,A35&TEXT(BLN,"mmmm"),JURN4),SUMIF(JURN1,A35&TEXT(BLN,"mmmm"),JURN4)-SUMIF(JURN1,A35&TEXT(BLN,"mmmm"),JURN3)),VALUE) -> 0 | E35: =C35+D35 -> 0
B36: Jumlah Pendapatan | C36: =SUM(C8:C35) -> 231360650 | D36: =SUM(D8:D35) -> 79478150 | E36: =SUM(E8:E35) -> 310838800
A38: 5-100-000 | B38: =VLOOKUP(A38,DAF_AKUN,2,FALSE) -> Total Sales Cost | C38: =IF(ISERROR=TRUE,IF(VLOOKUP(A38,DAF_AKUN,3,FALSE)="Db",SUMIF(AKUN1,A38,AKUN2)+SUMIF(JURN2,"1"&A38,JURN3)-SUMIF(JURN2,"1"&A38,JURN4),SUMIF(AKUN1,A38,AKUN3)-SUMIF(JURN2,"1"&A38,JURN3)+SUMIF(JURN2,"1"&A38,JURN4)),VALUE) -> 0 | D38: =IF(ISERROR=TRUE,IF(VLOOKUP(A38,DAF_AKUN,3,FALSE)="Db",SUMIF(JURN1,A38&TEXT(BLN,"mmmm"),JURN3)-SUMIF(JURN1,A38&TEXT(BLN,"mmmm"),JURN4),SUMIF(JURN1,A38&TEXT(BLN,"mmmm"),JURN4)-SUMIF(JURN1,A38&TEXT(BLN,"mmmm"),JURN3)),VALUE) -> 0 | E38: =C38+D38 -> 0
A39: 5-101-000 | B39: =VLOOKUP(A39,DAF_AKUN,2,FALSE) -> Total Sales Cost ASC | C39: =IF(ISERROR=TRUE,IF(VLOOKUP(A39,DAF_AKUN,3,FALSE)="Db",SUMIF(AKUN1,A39,AKUN2)+SUMIF(JURN2,"1"&A39,JURN3)-SUMIF(JURN2,"1"&A39,JURN4),SUMIF(AKUN1,A39,AKUN3)-SUMIF(JURN2,"1"&A39,JURN3)+SUMIF(JURN2,"1"&A39,JURN4)),VALUE) -> 0 | D39: =IF(ISERROR=TRUE,IF(VLOOKUP(A39,DAF_AKUN,3,FALSE)="Db",SUMIF(JURN1,A39&TEXT(BLN,"mmmm"),JURN3)-SUMIF(JURN1,A39&TEXT(BLN,"mmmm"),JURN4),SUMIF(JURN1,A39&TEXT(BLN,"mmmm"),JURN4)-SUMIF(JURN1,A39&TEXT(BLN,"mmmm"),JURN3)),VALUE) -> 0 | E39: =C39+D39 -> 0
A40: 5-101-001 | B40: =VLOOKUP(A40,DAF_AKUN,2,FALSE) -> Operational Cost | C40: =IF(ISERROR=TRUE,IF(VLOOKUP(A40,DAF_AKUN,3,FALSE)="Db",SUMIF(AKUN1,A40,AKUN2)+SUMIF(JURN2,"1"&A40,JURN3)-SUMIF(JURN2,"1"&A40,JURN4),SUMIF(AKUN1,A40,AKUN3)-SUMIF(JURN2,"1"&A40,JURN3)+SUMIF(JURN2,"1"&A40,JURN4)),VALUE) -> 0 | D40: =IF(ISERROR=TRUE,IF(VLOOKUP(A40,DAF_AKUN,3,FALSE)="Db",SUMIF(JURN1,A40&TEXT(BLN,"mmmm"),JURN3)-SUMIF(JURN1,A40&TEXT(BLN,"mmmm"),JURN4),SUMIF(JURN1,A40&TEXT(BLN,"mmmm"),JURN4)-SUMIF(JURN1,A40&TEXT(BLN,"mmmm"),JURN3)),VALUE) -> 0 | E40: =C40+D40 -> 0
A41: 5-101-002 | B41: =VLOOKUP(A41,DAF_AKUN,2,FALSE) -> Tour & Surfing Cost | C41: =IF(ISERROR=TRUE,IF(VLOOKUP(A41,DAF_AKUN,3,FALSE)="Db",SUMIF(AKUN1,A41,AKUN2)+SUMIF(JURN2,"1"&A41,JURN3)-SUMIF(JURN2,"1"&A41,JURN4),SUMIF(AKUN1,A41,AKUN3)-SUMIF(JURN2,"1"&A41,JURN3)+SUMIF(JURN2,"1"&A41,JURN4)),VALUE) -> 0 | D41: =IF(ISERROR=TRUE,IF(VLOOKUP(A41,DAF_AKUN,3,FALSE)="Db",SUMIF(JURN1,A41&TEXT(BLN,"mmmm"),JURN3)-SUMIF(JURN1,A41&TEXT(BLN,"mmmm"),JURN4),SUMIF(JURN1,A41&TEXT(BLN,"mmmm"),JURN4)-SUMIF(JURN1,A41&TEXT(BLN,"mmmm"),JURN3)),VALUE) -> 0 | E41: =C41+D41 -> 0
A42: 5-101-003 | B42: =VLOOKUP(A42,DAF_AKUN,2,FALSE) -> Transaction Cost | C42: =IF(ISERROR=TRUE,IF(VLOOKUP(A42,DAF_AKUN,3,FALSE)="Db",SUMIF(AKUN1,A42,AKUN2)+SUMIF(JURN2,"1"&A42,JURN3)-SUMIF(JURN2,"1"&A42,JURN4),SUMIF(AKUN1,A42,AKUN3)-SUMIF(JURN2,"1"&A42,JURN3)+SUMIF(JURN2,"1"&A42,JURN4)),VALUE) -> 36407618 | D42: =IF(ISERROR=TRUE,IF(VLOOKUP(A42,DAF_AKUN,3,FALSE)="Db",SUMIF(JURN1,A42&TEXT(BLN,"mmmm"),JURN3)-SUMIF(JURN1,A42&TEXT(BLN,"mmmm"),JURN4),SUMIF(JURN1,A42&TEXT(BLN,"mmmm"),JURN4)-SUMIF(JURN1,A42&TEXT(BLN,"mmmm"),JURN3)),VALUE) -> 10845635 | E42: =C42+D42 -> 47253253
A43: 5-101-004 | B43: =VLOOKUP(A43,DAF_AKUN,2,FALSE) -> Licence & Permit Cost | C43: =IF(ISERROR=TRUE,IF(VLOOKUP(A43,DAF_AKUN,3,FALSE)="Db",SUMIF(AKUN1,A43,AKUN2)+SUMIF(JURN2,"1"&A43,JURN3)-SUMIF(JURN2,"1"&A43,JURN4),SUMIF(AKUN1,A43,AKUN3)-SUMIF(JURN2,"1"&A43,JURN3)+SUMIF(JURN2,"1"&A43,JURN4)),VALUE) -> 0 | D43: =IF(ISERROR=TRUE,IF(VLOOKUP(A43,DAF_AKUN,3,FALSE)="Db",SUMIF(JURN1,A43&TEXT(BLN,"mmmm"),JURN3)-SUMIF(JURN1,A43&TEXT(BLN,"mmmm"),JURN4),SUMIF(JURN1,A43&TEXT(BLN,"mmmm"),JURN4)-SUMIF(JURN1,A43&TEXT(BLN,"mmmm"),JURN3)),VALUE) -> 0 | E43: =C43+D43 -> 0
A44: 5-101-005 | B44: =VLOOKUP(A44,DAF_AKUN,2,FALSE) -> Product Purchase Cost | C44: =IF(ISERROR=TRUE,IF(VLOOKUP(A44,DAF_AKUN,3,FALSE)="Db",SUMIF(AKUN1,A44,AKUN2)+SUMIF(JURN2,"1"&A44,JURN3)-SUMIF(JURN2,"1"&A44,JURN4),SUMIF(AKUN1,A44,AKUN3)-SUMIF(JURN2,"1"&A44,JURN3)+SUMIF(JURN2,"1"&A44,JURN4)),VALUE) -> 0 | D44: =IF(ISERROR=TRUE,IF(VLOOKUP(A44,DAF_AKUN,3,FALSE)="Db",SUMIF(JURN1,A44&TEXT(BLN,"mmmm"),JURN3)-SUMIF(JURN1,A44&TEXT(BLN,"mmmm"),JURN4),SUMIF(JURN1,A44&TEXT(BLN,"mmmm"),JURN4)-SUMIF(JURN1,A44&TEXT(BLN,"mmmm"),JURN3)),VALUE) -> 0 | E44: =C44+D44 -> 0
A45: 5-101-006 | B45: =VLOOKUP(A45,DAF_AKUN,2,FALSE) -> Other Operating Cost | C45: =IF(ISERROR=TRUE,IF(VLOOKUP(A45,DAF_AKUN,3,FALSE)="Db",SUMIF(AKUN1,A45,AKUN2)+SUMIF(JURN2,"1"&A45,JURN3)-SUMIF(JURN2,"1"&A45,JURN4),SUMIF(AKUN1,A45,AKUN3)-SUMIF(JURN2,"1"&A45,JURN3)+SUMIF(JURN2,"1"&A45,JURN4)),VALUE) -> 0 | D45: =IF(ISERROR=TRUE,IF(VLOOKUP(A45,DAF_AKUN,3,FALSE)="Db",SUMIF(JURN1,A45&TEXT(BLN,"mmmm"),JURN3)-SUMIF(JURN1,A45&TEXT(BLN,"mmmm"),JURN4),SUMIF(JURN1,A45&TEXT(BLN,"mmmm"),JURN4)-SUMIF(JURN1,A45&TEXT(BLN,"mmmm"),JURN3)),VALUE) -> 0 | E45: =C45+D45 -> 0
A46: 5-111-000 | B46: =VLOOKUP(A46,DAF_AKUN,2,FALSE) -> Total Exhibition & Conference Cost | C46: =IF(ISERROR=TRUE,IF(VLOOKUP(A46,DAF_AKUN,3,FALSE)="Db",SUMIF(AKUN1,A46,AKUN2)+SUMIF(JURN2,"1"&A46,JURN3)-SUMIF(JURN2,"1"&A46,JURN4),SUMIF(AKUN1,A46,AKUN3)-SUMIF(JURN2,"1"&A46,JURN3)+SUMIF(JURN2,"1"&A46,JURN4)),VALUE) -> 0 | D46: =IF(ISERROR=TRUE,IF(VLOOKUP(A46,DAF_AKUN,3,FALSE)="Db",SUMIF(JURN1,A46&TEXT(BLN,"mmmm"),JURN3)-SUMIF(JURN1,A46&TEXT(BLN,"mmmm"),JURN4),SUMIF(JURN1,A46&TEXT(BLN,"mmmm"),JURN4)-SUMIF(JURN1,A46&TEXT(BLN,"mmmm"),JURN3)),VALUE) -> 0 | E46: =C46+D46 -> 0
A47: 5-111-001 | B47: =VLOOKUP(A47,DAF_AKUN,2,FALSE) -> Space Rental - Exhibition | C47: =IF(ISERROR=TRUE,IF(VLOOKUP(A47,DAF_AKUN,3,FALSE)="Db",SUMIF(AKUN1,A47,AKUN2)+SUMIF(JURN2,"1"&A47,JURN3)-SUMIF(JURN2,"1"&A47,JURN4),SUMIF(AKUN1,A47,AKUN3)-SUMIF(JURN2,"1"&A47,JURN3)+SUMIF(JURN2,"1"&A47,JURN4)),VALUE) -> 0 | D47: =IF(ISERROR=TRUE,IF(VLOOKUP(A47,DAF_AKUN,3,FALSE)="Db",SUMIF(JURN1,A47&TEXT(BLN,"mmmm"),JURN3)-SUMIF(JURN1,A47&TEXT(BLN,"mmmm"),JURN4),SUMIF(JURN1,A47&TEXT(BLN,"mmmm"),JURN4)-SUMIF(JURN1,A47&TEXT(BLN,"mmmm"),JURN3)),VALUE) -> 0 | E47: =C47+D47 -> 0
A48: 5-111-002 | B48: =VLOOKUP(A48,DAF_AKUN,2,FALSE) -> Shell Scheme Rental - Exhibition | C48: =IF(ISERROR=TRUE,IF(VLOOKUP(A48,DAF_AKUN,3,FALSE)="Db",SUMIF(AKUN1,A48,AKUN2)+SUMIF(JURN2,"1"&A48,JURN3)-SUMIF(JURN2,"1"&A48,JURN4),SUMIF(AKUN1,A48,AKUN3)-SUMIF(JURN2,"1"&A48,JURN3)+SUMIF(JURN2,"1"&A48,JURN4)),VALUE) -> 0 | D48: =IF(ISERROR=TRUE,IF(VLOOKUP(A48,DAF_AKUN,3,FALSE)="Db",SUMIF(JURN1,A48&TEXT(BLN,"mmmm"),JURN3)-SUMIF(JURN1,A48&TEXT(BLN,"mmmm"),JURN4),SUMIF(JURN1,A48&TEXT(BLN,"mmmm"),JURN4)-SUMIF(JURN1,A48&TEXT(BLN,"mmmm"),JURN3)),VALUE) -> 0 | E48: =C48+D48 -> 0
A49: 5-111-003 | B49: =VLOOKUP(A49,DAF_AKUN,2,FALSE) -> Conference Cost | C49: =IF(ISERROR=TRUE,IF(VLOOKUP(A49,DAF_AKUN,3,FALSE)="Db",SUMIF(AKUN1,A49,AKUN2)+SUMIF(JURN2,"1"&A49,JURN3)-SUMIF(JURN2,"1"&A49,JURN4),SUMIF(AKUN1,A49,AKUN3)-SUMIF(JURN2,"1"&A49,JURN3)+SUMIF(JURN2,"1"&A49,JURN4)),VALUE) -> 0 | D49: =IF(ISERROR=TRUE,IF(VLOOKUP(A49,DAF_AKUN,3,FALSE)="Db",SUMIF(JURN1,A49&TEXT(BLN,"mmmm"),JURN3)-SUMIF(JURN1,A49&TEXT(BLN,"mmmm"),JURN4),SUMIF(JURN1,A49&TEXT(BLN,"mmmm"),JURN4)-SUMIF(JURN1,A49&TEXT(BLN,"mmmm"),JURN3)),VALUE) -> 0 | E49: =C49+D49 -> 0
... A52: 5-111-006 | B52: =VLOOKUP(A52,DAF_AKUN,2,FALSE) -> Other Operating Cost - Exhibition | C52: =IF(ISERROR=TRUE,IF(VLOOKUP(A52,DAF_AKUN,3,FALSE)="Db",SUMIF(AKUN1,A52,AKUN2)+SUMIF(JURN2,"1"&A52,JURN3)-SUMIF(JURN2,"1"&A52,JURN4),SUMIF(AKUN1,A52,AKUN3)-SUMIF(JURN2,"1"&A52,JURN3)+SUMIF(JURN2,"1"&A52,JURN4)),VALUE) -> 0 | D52: =IF(ISERROR=TRUE,IF(VLOOKUP(A52,DAF_AKUN,3,FALSE)="Db",SUMIF(JURN1,A52&TEXT(BLN,"mmmm"),JURN3)-SUMIF(JURN1,A52&TEXT(BLN,"mmmm"),JURN4),SUMIF(JURN1,A52&TEXT(BLN,"mmmm"),JURN4)-SUMIF(JURN1,A52&TEXT(BLN,"mmmm"),JURN3)),VALUE) -> 0 | E52: =C52+D52 -> 0
B54: Jumlah Harga Pokok Penjualan | C54: =SUM(C38:C53) -> 36407618 | D54: =SUM(D38:D53) -> 10845635 | E54: =SUM(E38:E53) -> 47253253
A56: 6-100-000 | B56: =VLOOKUP(A56,DAF_AKUN,2,FALSE) -> Office Overhead | C56: =IF(ISERROR=TRUE,IF(VLOOKUP(A56,DAF_AKUN,3,FALSE)="Db",SUMIF(AKUN1,A56,AKUN2)+SUMIF(JURN2,"1"&A56,JURN3)-SUMIF(JURN2,"1"&A56,JURN4),SUMIF(AKUN1,A56,AKUN3)-SUMIF(JURN2,"1"&A56,JURN3)+SUMIF(JURN2,"1"&A56,JURN4)),VALUE) -> 0 | D56: =IF(ISERROR=TRUE,IF(VLOOKUP(A56,DAF_AKUN,3,FALSE)="Db",SUMIF(JURN1,A56&TEXT(BLN,"mmmm"),JURN3)-SUMIF(JURN1,A56&TEXT(BLN,"mmmm"),JURN4),SUMIF(JURN1,A56&TEXT(BLN,"mmmm"),JURN4)-SUMIF(JURN1,A56&TEXT(BLN,"mmmm"),JURN3)),VALUE) -> 0 | E56: =C56+D56 -> 0
A57: 6-101-000 | B57: =VLOOKUP(A57,DAF_AKUN,2,FALSE) -> Staff Cost | C57: =IF(ISERROR=TRUE,IF(VLOOKUP(A57,DAF_AKUN,3,FALSE)="Db",SUMIF(AKUN1,A57,AKUN2)+SUMIF(JURN2,"1"&A57,JURN3)-SUMIF(JURN2,"1"&A57,JURN4),SUMIF(AKUN1,A57,AKUN3)-SUMIF(JURN2,"1"&A57,JURN3)+SUMIF(JURN2,"1"&A57,JURN4)),VALUE) -> 0 | D57: =IF(ISERROR=TRUE,IF(VLOOKUP(A57,DAF_AKUN,3,FALSE)="Db",SUMIF(JURN1,A57&TEXT(BLN,"mmmm"),JURN3)-SUMIF(JURN1,A57&TEXT(BLN,"mmmm"),JURN4),SUMIF(JURN1,A57&TEXT(BLN,"mmmm"),JURN4)-SUMIF(JURN1,A57&TEXT(BLN,"mmmm"),JURN3)),VALUE) -> 0 | E57: =C57+D57 -> 0
A58: 6-101-001 | B58: =VLOOKUP(A58,DAF_AKUN,2,FALSE) -> Salary & Allowance | C58: =IF(ISERROR=TRUE,IF(VLOOKUP(A58,DAF_AKUN,3,FALSE)="Db",SUMIF(AKUN1,A58,AKUN2)+SUMIF(JURN2,"1"&A58,JURN3)-SUMIF(JURN2,"1"&A58,JURN4),SUMIF(AKUN1,A58,AKUN3)-SUMIF(JURN2,"1"&A58,JURN3)+SUMIF(JURN2,"1"&A58,JURN4)),VALUE) -> 0 | D58: =IF(ISERROR=TRUE,IF(VLOOKUP(A58,DAF_AKUN,3,FALSE)="Db",SUMIF(JURN1,A58&TEXT(BLN,"mmmm"),JURN3)-SUMIF(JURN1,A58&TEXT(BLN,"mmmm"),JURN4),SUMIF(JURN1,A58&TEXT(BLN,"mmmm"),JURN4)-SUMIF(JURN1,A58&TEXT(BLN,"mmmm"),JURN3)),VALUE) -> 0 | E58: =C58+D58 -> 0
A59: 6-101-002 | B59: =VLOOKUP(A59,DAF_AKUN,2,FALSE) -> 13th Month Salary | C59: =IF(ISERROR=TRUE,IF(VLOOKUP(A59,DAF_AKUN,3,FALSE)="Db",SUMIF(AKUN1,A59,AKUN2)+SUMIF(JURN2,"1"&A59,JURN3)-SUMIF(JURN2,"1"&A59,JURN4),SUMIF(AKUN1,A59,AKUN3)-SUMIF(JURN2,"1"&A59,JURN3)+SUMIF(JURN2,"1"&A59,JURN4)),VALUE) -> 0 | D59: =IF(ISERROR=TRUE,IF(VLOOKUP(A59,DAF_AKUN,3,FALSE)="Db",SUMIF(JURN1,A59&TEXT(BLN,"mmmm"),JURN3)-SUMIF(JURN1,A59&TEXT(BLN,"mmmm"),JURN4),SUMIF(JURN1,A59&TEXT(BLN,"mmmm"),JURN4)-SUMIF(JURN1,A59&TEXT(BLN,"mmmm"),JURN3)),VALUE) -> 0 | E59: =C59+D59 -> 0
A60: 6-101-003 | B60: =VLOOKUP(A60,DAF_AKUN,2,FALSE) -> Bonus | C60: =IF(ISERROR=TRUE,IF(VLOOKUP(A60,DAF_AKUN,3,FALSE)="Db",SUMIF(AKUN1,A60,AKUN2)+SUMIF(JURN2,"1"&A60,JURN3)-SUMIF(JURN2,"1"&A60,JURN4),SUMIF(AKUN1,A60,AKUN3)-SUMIF(JURN2,"1"&A60,JURN3)+SUMIF(JURN2,"1"&A60,JURN4)),VALUE) -> 0 | D60: =IF(ISERROR=TRUE,IF(VLOOKUP(A60,DAF_AKUN,3,FALSE)="Db",SUMIF(JURN1,A60&TEXT(BLN,"mmmm"),JURN3)-SUMIF(JURN1,A60&TEXT(BLN,"mmmm"),JURN4),SUMIF(JURN1,A60&TEXT(BLN,"mmmm"),JURN4)-SUMIF(JURN1,A60&TEXT(BLN,"mmmm"),JURN3)),VALUE) -> 0 | E60: =C60+D60 -> 0
A61: 6-101-004 | B61: =VLOOKUP(A61,DAF_AKUN,2,FALSE) -> Overtime | C61: =IF(ISERROR=TRUE,IF(VLOOKUP(A61,DAF_AKUN,3,FALSE)="Db",SUMIF(AKUN1,A61,AKUN2)+SUMIF(JURN2,"1"&A61,JURN3)-SUMIF(JURN2,"1"&A61,JURN4),SUMIF(AKUN1,A61,AKUN3)-SUMIF(JURN2,"1"&A61,JURN3)+SUMIF(JURN2,"1"&A61,JURN4)),VALUE) -> 0 | D61: =IF(ISERROR=TRUE,IF(VLOOKUP(A61,DAF_AKUN,3,FALSE)="Db",SUMIF(JURN1,A61&TEXT(BLN,"mmmm"),JURN3)-SUMIF(JURN1,A61&TEXT(BLN,"mmmm"),JURN4),SUMIF(JURN1,A61&TEXT(BLN,"mmmm"),JURN4)-SUMIF(JURN1,A61&TEXT(BLN,"mmmm"),JURN3)),VALUE) -> 0 | E61: =C61+D61 -> 0
A62: 6-101-005 | B62: =VLOOKUP(A62,DAF_AKUN,2,FALSE) -> Medical Allowance | C62: =IF(ISERROR=TRUE,IF(VLOOKUP(A62,DAF_AKUN,3,FALSE)="Db",SUMIF(AKUN1,A62,AKUN2)+SUMIF(JURN2,"1"&A62,JURN3)-SUMIF(JURN2,"1"&A62,JURN4),SUMIF(AKUN1,A62,AKUN3)-SUMIF(JURN2,"1"&A62,JURN3)+SUMIF(JURN2,"1"&A62,JURN4)),VALUE) -> 0 | D62: =IF(ISERROR=TRUE,IF(VLOOKUP(A62,DAF_AKUN,3,FALSE)="Db",SUMIF(JURN1,A62&TEXT(BLN,"mmmm"),JURN3)-SUMIF(JURN1,A62&TEXT(BLN,"mmmm"),JURN4),SUMIF(JURN1,A62&TEXT(BLN,"mmmm"),JURN4)-SUMIF(JURN1,A62&TEXT(BLN,"mmmm"),JURN3)),VALUE) -> 0 | E62: =C62+D62 -> 0
A63: 6-101-006 | B63: =VLOOKUP(A63,DAF_AKUN,2,FALSE) -> BPJS - Pension | C63: =IF(ISERROR=TRUE,IF(VLOOKUP(A63,DAF_AKUN,3,FALSE)="Db",SUMIF(AKUN1,A63,AKUN2)+SUMIF(JURN2,"1"&A63,JURN3)-SUMIF(JURN2,"1"&A63,JURN4),SUMIF(AKUN1,A63,AKUN3)-SUMIF(JURN2,"1"&A63,JURN3)+SUMIF(JURN2,"1"&A63,JURN4)),VALUE) -> 0 | D63: =IF(ISERROR=TRUE,IF(VLOOKUP(A63,DAF_AKUN,3,FALSE)="Db",SUMIF(JURN1,A63&TEXT(BLN,"mmmm"),JURN3)-SUMIF(JURN1,A63&TEXT(BLN,"mmmm"),JURN4),SUMIF(JURN1,A63&TEXT(BLN,"mmmm"),JURN4)-SUMIF(JURN1,A63&TEXT(BLN,"mmmm"),JURN3)),VALUE) -> 0 | E63: =C63+D63 -> 0
A64: 6-101-007 | B64: =VLOOKUP(A64,DAF_AKUN,2,FALSE) -> BPJS - Health | C64: =IF(ISERROR=TRUE,IF(VLOOKUP(A64,DAF_AKUN,3,FALSE)="Db",SUMIF(AKUN1,A64,AKUN2)+SUMIF(JURN2,"1"&A64,JURN3)-SUMIF(JURN2,"1"&A64,JURN4),SUMIF(AKUN1,A64,AKUN3)-SUMIF(JURN2,"1"&A64,JURN3)+SUMIF(JURN2,"1"&A64,JURN4)),VALUE) -> 0 | D64: =IF(ISERROR=TRUE,IF(VLOOKUP(A64,DAF_AKUN,3,FALSE)="Db",SUMIF(JURN1,A64&TEXT(BLN,"mmmm"),JURN3)-SUMIF(JURN1,A64&TEXT(BLN,"mmmm"),JURN4),SUMIF(JURN1,A64&TEXT(BLN,"mmmm"),JURN4)-SUMIF(JURN1,A64&TEXT(BLN,"mmmm"),JURN3)),VALUE) -> 0 | E64: =C64+D64 -> 0
A65: 6-101-020 | B65: =VLOOKUP(A65,DAF_AKUN,2,FALSE) -> PPh - 21 | C65: =IF(ISERROR=TRUE,IF(VLOOKUP(A65,DAF_AKUN,3,FALSE)="Db",SUMIF(AKUN1,A65,AKUN2)+SUMIF(JURN2,"1"&A65,JURN3)-SUMIF(JURN2,"1"&A65,JURN4),SUMIF(AKUN1,A65,AKUN3)-SUMIF(JURN2,"1"&A65,JURN3)+SUMIF(JURN2,"1"&A65,JURN4)),VALUE) -> 0 | D65: =IF(ISERROR=TRUE,IF(VLOOKUP(A65,DAF_AKUN,3,FALSE)="Db",SUMIF(JURN1,A65&TEXT(BLN,"mmmm"),JURN3)-SUMIF(JURN1,A65&TEXT(BLN,"mmmm"),JURN4),SUMIF(JURN1,A65&TEXT(BLN,"mmmm"),JURN4)-SUMIF(JURN1,A65&TEXT(BLN,"mmmm"),JURN3)),VALUE) -> 0 | E65: =C65+D65 -> 0
A66: 6-101-031 | B66: =VLOOKUP(A66,DAF_AKUN,2,FALSE) -> Recruitmen | C66: =IF(ISERROR=TRUE,IF(VLOOKUP(A66,DAF_AKUN,3,FALSE)="Db",SUMIF(AKUN1,A66,AKUN2)+SUMIF(JURN2,"1"&A66,JURN3)-SUMIF(JURN2,"1"&A66,JURN4),SUMIF(AKUN1,A66,AKUN3)-SUMIF(JURN2,"1"&A66,JURN3)+SUMIF(JURN2,"1"&A66,JURN4)),VALUE) -> 0 | D66: =IF(ISERROR=TRUE,IF(VLOOKUP(A66,DAF_AKUN,3,FALSE)="Db",SUMIF(JURN1,A66&TEXT(BLN,"mmmm"),JURN3)-SUMIF(JURN1,A66&TEXT(BLN,"mmmm"),JURN4),SUMIF(JURN1,A66&TEXT(BLN,"mmmm"),JURN4)-SUMIF(JURN1,A66&TEXT(BLN,"mmmm"),JURN3)),VALUE) -> 0 | E66: =C66+D66 -> 0
A67: 6-101-032 | B67: =VLOOKUP(A67,DAF_AKUN,2,FALSE) -> Training & Development | C67: =IF(ISERROR=TRUE,IF(VLOOKUP(A67,DAF_AKUN,3,FALSE)="Db",SUMIF(AKUN1,A67,AKUN2)+SUMIF(JURN2,"1"&A67,JURN3)-SUMIF(JURN2,"1"&A67,JURN4),SUMIF(AKUN1,A67,AKUN3)-SUMIF(JURN2,"1"&A67,JURN3)+SUMIF(JURN2,"1"&A67,JURN4)),VALUE) -> 0 | D67: =IF(ISERROR=TRUE,IF(VLOOKUP(A67,DAF_AKUN,3,FALSE)="Db",SUMIF(JURN1,A67&TEXT(BLN,"mmmm"),JURN3)-SUMIF(JURN1,A67&TEXT(BLN,"mmmm"),JURN4),SUMIF(JURN1,A67&TEXT(BLN,"mmmm"),JURN4)-SUMIF(JURN1,A67&TEXT(BLN,"mmmm"),JURN3)),VALUE) -> 0 | E67: =C67+D67 -> 0
... A123: 9-102-001 | B123: =VLOOKUP(A123,DAF_AKUN,2,FALSE) -> Dividend Expense | C123: =IF(ISERROR=TRUE,IF(VLOOKUP(A123,DAF_AKUN,3,FALSE)="Db",SUMIF(AKUN1,A123,AKUN2)+SUMIF(JURN2,"1"&A123,JURN3)-SUMIF(JURN2,"1"&A123,JURN4),SUMIF(AKUN1,A123,AKUN3)-SUMIF(JURN2,"1"&A123,JURN3)+SUMIF(JURN2,"1"&A123,JURN4)),VALUE) -> 0 | D123: =IF(ISERROR=TRUE,IF(VLOOKUP(A123,DAF_AKUN,3,FALSE)="Db",SUMIF(JURN1,A123&TEXT(BLN,"mmmm"),JURN3)-SUMIF(JURN1,A123&TEXT(BLN,"mmmm"),JURN4),SUMIF(JURN1,A123&TEXT(BLN,"mmmm"),JURN4)-SUMIF(JURN1,A123&TEXT(BLN,"mmmm"),JURN3)),VALUE) -> 0 | E123: =C123+D123 -> 0
B125: Jumlah Biaya | C125: =SUM(C56:C104)+SUM(C112:C123) -> 0 | D125: =SUM(D56:D104)+SUM(D112:D123) -> 0 | E125: =SUM(E56:E104)+SUM(E112:E123) -> 0
B127: Laba Bersih | C127: =C36-C54-C125+C106+C108+C110 -> 194953032 | D127: =D36-D54-D125+D106+D108+D110 -> 68632515 | E127: =E36-E54-E125+E106+E108+E110 -> 263585547

Sheet Neraca
A1: =NAMA -> ARYA USAHA TIRTA, CV
A2: NERACA
A3: ="Akhir Bulan : "&TEXT(BLN,"mmmm")&" "&THN -> Akhir Bulan : July 2026
A5: Kode | B5: Nama Akun | C5: Akhir Bulan | D5: Akhir Bulan
A6: Akun | C6: Lalu | D6: =BLN -> 183
A8: 100000000 | B8: =VLOOKUP(A8,DAF_AKUN,2,FALSE) -> AKTIVA | C8: =IF(ISERROR=TRUE,IF(AND(ISERROR=TRUE,VLOOKUP(A8,DAF_AKUN,3,FALSE)="Db"),SUMIF(AKUN1,A8,AKUN2)+SUMIF(JURN2,"1"&A8,JURN3)-SUMIF(JURN2,"1"&A8,JURN4),SUMIF(AKUN1,A8,AKUN3)-SUMIF(JURN2,"1"&A8,JURN3)+SUMIF(JURN2,"1"&A8,JURN4)),VALUE) -> 0 | D8: =IF(ISERROR=TRUE,IF(VLOOKUP(A8,DAF_AKUN,3,FALSE)="Db",SUMIF(AKUN1,A8,AKUN2)+SUMIF(JURN2,"1"&A8,JURN3)-SUMIF(JURN2,"1"&A8,JURN4)+SUMIF(JURN1,A8&TEXT(BLN,"mmmm"),JURN3)-SUMIF(JURN1,A8&TEXT(BLN,"mmmm"),JURN4),SUMIF(AKUN1,A8,AKUN3)-SUMIF(JURN2,"1"&A8,JURN3)+SUMIF(JURN2,"1"&A8,JURN4)+SUMIF(JURN1,A8&TEXT(BLN,"mmmm"),JURN4)-SUMIF(JURN1,A8&TEXT(BLN,"mmmm"),JURN3)),VALUE) -> 0
A9: 1-101-000 | B9: =VLOOKUP(A9,DAF_AKUN,2,FALSE) -> Kas dan Bank | C9: =IF(ISERROR=TRUE,IF(AND(ISERROR=TRUE,VLOOKUP(A9,DAF_AKUN,3,FALSE)="Db"),SUMIF(AKUN1,A9,AKUN2)+SUMIF(JURN2,"1"&A9,JURN3)-SUMIF(JURN2,"1"&A9,JURN4),SUMIF(AKUN1,A9,AKUN3)-SUMIF(JURN2,"1"&A9,JURN3)+SUMIF(JURN2,"1"&A9,JURN4)),VALUE) -> 0 | D9: =IF(ISERROR=TRUE,IF(VLOOKUP(A9,DAF_AKUN,3,FALSE)="Db",SUMIF(AKUN1,A9,AKUN2)+SUMIF(JURN2,"1"&A9,JURN3)-SUMIF(JURN2,"1"&A9,JURN4)+SUMIF(JURN1,A9&TEXT(BLN,"mmmm"),JURN3)-SUMIF(JURN1,A9&TEXT(BLN,"mmmm"),JURN4),SUMIF(AKUN1,A9,AKUN3)-SUMIF(JURN2,"1"&A9,JURN3)+SUMIF(JURN2,"1"&A9,JURN4)+SUMIF(JURN1,A9&TEXT(BLN,"mmmm"),JURN4)-SUMIF(JURN1,A9&TEXT(BLN,"mmmm"),JURN3)),VALUE) -> 0
A10: 1-101-001 | B10: =VLOOKUP(A10,DAF_AKUN,2,FALSE) -> Petty Cash | C10: =IF(ISERROR=TRUE,IF(AND(ISERROR=TRUE,VLOOKUP(A10,DAF_AKUN,3,FALSE)="Db"),SUMIF(AKUN1,A10,AKUN2)+SUMIF(JURN2,"1"&A10,JURN3)-SUMIF(JURN2,"1"&A10,JURN4),SUMIF(AKUN1,A10,AKUN3)-SUMIF(JURN2,"1"&A10,JURN3)+SUMIF(JURN2,"1"&A10,JURN4)),VALUE) -> 0 | D10: =IF(ISERROR=TRUE,IF(VLOOKUP(A10,DAF_AKUN,3,FALSE)="Db",SUMIF(AKUN1,A10,AKUN2)+SUMIF(JURN2,"1"&A10,JURN3)-SUMIF(JURN2,"1"&A10,JURN4)+SUMIF(JURN1,A10&TEXT(BLN,"mmmm"),JURN3)-SUMIF(JURN1,A10&TEXT(BLN,"mmmm"),JURN4),SUMIF(AKUN1,A10,AKUN3)-SUMIF(JURN2,"1"&A10,JURN3)+SUMIF(JURN2,"1"&A10,JURN4)+SUMIF(JURN1,A10&TEXT(BLN,"mmmm"),JURN4)-SUMIF(JURN1,A10&TEXT(BLN,"mmmm"),JURN3)),VALUE) -> 0
A11: 1-101-010 | B11: =VLOOKUP(A11,DAF_AKUN,2,FALSE) -> CIMB Niaga - Acc. No: 800171592300 | C11: =IF(ISERROR=TRUE,IF(AND(ISERROR=TRUE,VLOOKUP(A11,DAF_AKUN,3,FALSE)="Db"),SUMIF(AKUN1,A11,AKUN2)+SUMIF(JURN2,"1"&A11,JURN3)-SUMIF(JURN2,"1"&A11,JURN4),SUMIF(AKUN1,A11,AKUN3)-SUMIF(JURN2,"1"&A11,JURN3)+SUMIF(JURN2,"1"&A11,JURN4)),VALUE) -> 3043241 | D11: =IF(ISERROR=TRUE,IF(VLOOKUP(A11,DAF_AKUN,3,FALSE)="Db",SUMIF(AKUN1,A11,AKUN2)+SUMIF(JURN2,"1"&A11,JURN3)-SUMIF(JURN2,"1"&A11,JURN4)+SUMIF(JURN1,A11&TEXT(BLN,"mmmm"),JURN3)-SUMIF(JURN1,A11&TEXT(BLN,"mmmm"),JURN4),SUMIF(AKUN1,A11,AKUN3)-SUMIF(JURN2,"1"&A11,JURN3)+SUMIF(JURN2,"1"&A11,JURN4)+SUMIF(JURN1,A11&TEXT(BLN,"mmmm"),JURN4)-SUMIF(JURN1,A11&TEXT(BLN,"mmmm"),JURN3)),VALUE) -> 3043241 | F11: 3043241 | G11: =F11-D11 -> 0
A12: 1-101-011 | B12: =VLOOKUP(A12,DAF_AKUN,2,FALSE) -> Bank 2 | C12: =IF(ISERROR=TRUE,IF(AND(ISERROR=TRUE,VLOOKUP(A12,DAF_AKUN,3,FALSE)="Db"),SUMIF(AKUN1,A12,AKUN2)+SUMIF(JURN2,"1"&A12,JURN3)-SUMIF(JURN2,"1"&A12,JURN4),SUMIF(AKUN1,A12,AKUN3)-SUMIF(JURN2,"1"&A12,JURN3)+SUMIF(JURN2,"1"&A12,JURN4)),VALUE) -> 0 | D12: =IF(ISERROR=TRUE,IF(VLOOKUP(A12,DAF_AKUN,3,FALSE)="Db",SUMIF(AKUN1,A12,AKUN2)+SUMIF(JURN2,"1"&A12,JURN3)-SUMIF(JURN2,"1"&A12,JURN4)+SUMIF(JURN1,A12&TEXT(BLN,"mmmm"),JURN3)-SUMIF(JURN1,A12&TEXT(BLN,"mmmm"),JURN4),SUMIF(AKUN1,A12,AKUN3)-SUMIF(JURN2,"1"&A12,JURN3)+SUMIF(JURN2,"1"&A12,JURN4)+SUMIF(JURN1,A12&TEXT(BLN,"mmmm"),JURN4)-SUMIF(JURN1,A12&TEXT(BLN,"mmmm"),JURN3)),VALUE) -> 0
A13: 1-101-012 | B13: =VLOOKUP(A13,DAF_AKUN,2,FALSE) -> Bank 3 | C13: =IF(ISERROR=TRUE,IF(AND(ISERROR=TRUE,VLOOKUP(A13,DAF_AKUN,3,FALSE)="Db"),SUMIF(AKUN1,A13,AKUN2)+SUMIF(JURN2,"1"&A13,JURN3)-SUMIF(JURN2,"1"&A13,JURN4),SUMIF(AKUN1,A13,AKUN3)-SUMIF(JURN2,"1"&A13,JURN3)+SUMIF(JURN2,"1"&A13,JURN4)),VALUE) -> 0 | D13: =IF(ISERROR=TRUE,IF(VLOOKUP(A13,DAF_AKUN,3,FALSE)="Db",SUMIF(AKUN1,A13,AKUN2)+SUMIF(JURN2,"1"&A13,JURN3)-SUMIF(JURN2,"1"&A13,JURN4)+SUMIF(JURN1,A13&TEXT(BLN,"mmmm"),JURN3)-SUMIF(JURN1,A13&TEXT(BLN,"mmmm"),JURN4),SUMIF(AKUN1,A13,AKUN3)-SUMIF(JURN2,"1"&A13,JURN3)+SUMIF(JURN2,"1"&A13,JURN4)+SUMIF(JURN1,A13&TEXT(BLN,"mmmm"),JURN4)-SUMIF(JURN1,A13&TEXT(BLN,"mmmm"),JURN3)),VALUE) -> 0
A14: 1-101-013 | B14: =VLOOKUP(A14,DAF_AKUN,2,FALSE) -> BAnk 4 | C14: =IF(ISERROR=TRUE,IF(AND(ISERROR=TRUE,VLOOKUP(A14,DAF_AKUN,3,FALSE)="Db"),SUMIF(AKUN1,A14,AKUN2)+SUMIF(JURN2,"1"&A14,JURN3)-SUMIF(JURN2,"1"&A14,JURN4),SUMIF(AKUN1,A14,AKUN3)-SUMIF(JURN2,"1"&A14,JURN3)+SUMIF(JURN2,"1"&A14,JURN4)),VALUE) -> 0 | D14: =IF(ISERROR=TRUE,IF(VLOOKUP(A14,DAF_AKUN,3,FALSE)="Db",SUMIF(AKUN1,A14,AKUN2)+SUMIF(JURN2,"1"&A14,JURN3)-SUMIF(JURN2,"1"&A14,JURN4)+SUMIF(JURN1,A14&TEXT(BLN,"mmmm"),JURN3)-SUMIF(JURN1,A14&TEXT(BLN,"mmmm"),JURN4),SUMIF(AKUN1,A14,AKUN3)-SUMIF(JURN2,"1"&A14,JURN3)+SUMIF(JURN2,"1"&A14,JURN4)+SUMIF(JURN1,A14&TEXT(BLN,"mmmm"),JURN4)-SUMIF(JURN1,A14&TEXT(BLN,"mmmm"),JURN3)),VALUE) -> 0
A15: 1-101-100 | B15: =VLOOKUP(A15,DAF_AKUN,2,FALSE) -> Bank Deposit | C15: =IF(ISERROR=TRUE,IF(AND(ISERROR=TRUE,VLOOKUP(A15,DAF_AKUN,3,FALSE)="Db"),SUMIF(AKUN1,A15,AKUN2)+SUMIF(JURN2,"1"&A15,JURN3)-SUMIF(JURN2,"1"&A15,JURN4),SUMIF(AKUN1,A15,AKUN3)-SUMIF(JURN2,"1"&A15,JURN3)+SUMIF(JURN2,"1"&A15,JURN4)),VALUE) -> 0 | D15: =IF(ISERROR=TRUE,IF(VLOOKUP(A15,DAF_AKUN,3,FALSE)="Db",SUMIF(AKUN1,A15,AKUN2)+SUMIF(JURN2,"1"&A15,JURN3)-SUMIF(JURN2,"1"&A15,JURN4)+SUMIF(JURN1,A15&TEXT(BLN,"mmmm"),JURN3)-SUMIF(JURN1,A15&TEXT(BLN,"mmmm"),JURN4),SUMIF(AKUN1,A15,AKUN3)-SUMIF(JURN2,"1"&A15,JURN3)+SUMIF(JURN2,"1"&A15,JURN4)+SUMIF(JURN1,A15&TEXT(BLN,"mmmm"),JURN4)-SUMIF(JURN1,A15&TEXT(BLN,"mmmm"),JURN3)),VALUE) -> 0
A16: 1-101-101 | B16: =VLOOKUP(A16,DAF_AKUN,2,FALSE) -> Others Deposit | C16: =IF(ISERROR=TRUE,IF(AND(ISERROR=TRUE,VLOOKUP(A16,DAF_AKUN,3,FALSE)="Db"),SUMIF(AKUN1,A16,AKUN2)+SUMIF(JURN2,"1"&A16,JURN3)-SUMIF(JURN2,"1"&A16,JURN4),SUMIF(AKUN1,A16,AKUN3)-SUMIF(JURN2,"1"&A16,JURN3)+SUMIF(JURN2,"1"&A16,JURN4)),VALUE) -> 0 | D16: =IF(ISERROR=TRUE,IF(VLOOKUP(A16,DAF_AKUN,3,FALSE)="Db",SUMIF(AKUN1,A16,AKUN2)+SUMIF(JURN2,"1"&A16,JURN3)-SUMIF(JURN2,"1"&A16,JURN4)+SUMIF(JURN1,A16&TEXT(BLN,"mmmm"),JURN3)-SUMIF(JURN1,A16&TEXT(BLN,"mmmm"),JURN4),SUMIF(AKUN1,A16,AKUN3)-SUMIF(JURN2,"1"&A16,JURN3)+SUMIF(JURN2,"1"&A16,JURN4)+SUMIF(JURN1,A16&TEXT(BLN,"mmmm"),JURN4)-SUMIF(JURN1,A16&TEXT(BLN,"mmmm"),JURN3)),VALUE) -> 0
A17: 1-101-200 | B17: =VLOOKUP(A17,DAF_AKUN,2,FALSE) -> Cash In Transit | C17: =IF(ISERROR=TRUE,IF(AND(ISERROR=TRUE,VLOOKUP(A17,DAF_AKUN,3,FALSE)="Db"),SUMIF(AKUN1,A17,AKUN2)+SUMIF(JURN2,"1"&A17,JURN3)-SUMIF(JURN2,"1"&A17,JURN4),SUMIF(AKUN1,A17,AKUN3)-SUMIF(JURN2,"1"&A17,JURN3)+SUMIF(JURN2,"1"&A17,JURN4)),VALUE) -> 0 | D17: =IF(ISERROR=TRUE,IF(VLOOKUP(A17,DAF_AKUN,3,FALSE)="Db",SUMIF(AKUN1,A17,AKUN2)+SUMIF(JURN2,"1"&A17,JURN3)-SUMIF(JURN2,"1"&A17,JURN4)+SUMIF(JURN1,A17&TEXT(BLN,"mmmm"),JURN3)-SUMIF(JURN1,A17&TEXT(BLN,"mmmm"),JURN4),SUMIF(AKUN1,A17,AKUN3)-SUMIF(JURN2,"1"&A17,JURN3)+SUMIF(JURN2,"1"&A17,JURN4)+SUMIF(JURN1,A17&TEXT(BLN,"mmmm"),JURN4)-SUMIF(JURN1,A17&TEXT(BLN,"mmmm"),JURN3)),VALUE) -> 0
A18: 1-102-000 | B18: =VLOOKUP(A18,DAF_AKUN,2,FALSE) -> Account Receivable | C18: =IF(ISERROR=TRUE,IF(AND(ISERROR=TRUE,VLOOKUP(A18,DAF_AKUN,3,FALSE)="Db"),SUMIF(AKUN1,A18,AKUN2)+SUMIF(JURN2,"1"&A18,JURN3)-SUMIF(JURN2,"1"&A18,JURN4),SUMIF(AKUN1,A18,AKUN3)-SUMIF(JURN2,"1"&A18,JURN3)+SUMIF(JURN2,"1"&A18,JURN4)),VALUE) -> 0 | D18: =IF(ISERROR=TRUE,IF(VLOOKUP(A18,DAF_AKUN,3,FALSE)="Db",SUMIF(AKUN1,A18,AKUN2)+SUMIF(JURN2,"1"&A18,JURN3)-SUMIF(JURN2,"1"&A18,JURN4)+SUMIF(JURN1,A18&TEXT(BLN,"mmmm"),JURN3)-SUMIF(JURN1,A18&TEXT(BLN,"mmmm"),JURN4),SUMIF(AKUN1,A18,AKUN3)-SUMIF(JURN2,"1"&A18,JURN3)+SUMIF(JURN2,"1"&A18,JURN4)+SUMIF(JURN1,A18&TEXT(BLN,"mmmm"),JURN4)-SUMIF(JURN1,A18&TEXT(BLN,"mmmm"),JURN3)),VALUE) -> 0
A19: 1-102-001 | B19: =VLOOKUP(A19,DAF_AKUN,2,FALSE) -> Receivable - Trade | C19: =IF(ISERROR=TRUE,IF(AND(ISERROR=TRUE,VLOOKUP(A19,DAF_AKUN,3,FALSE)="Db"),SUMIF(AKUN1,A19,AKUN2)+SUMIF(JURN2,"1"&A19,JURN3)-SUMIF(JURN2,"1"&A19,JURN4),SUMIF(AKUN1,A19,AKUN3)-SUMIF(JURN2,"1"&A19,JURN3)+SUMIF(JURN2,"1"&A19,JURN4)),VALUE) -> 208502010 | D19: =IF(ISERROR=TRUE,IF(VLOOKUP(A19,DAF_AKUN,3,FALSE)="Db",SUMIF(AKUN1,A19,AKUN2)+SUMIF(JURN2,"1"&A19,JURN3)-SUMIF(JURN2,"1"&A19,JURN4)+SUMIF(JURN1,A19&TEXT(BLN,"mmmm"),JURN3)-SUMIF(JURN1,A19&TEXT(BLN,"mmmm"),JURN4),SUMIF(AKUN1,A19,AKUN3)-SUMIF(JURN2,"1"&A19,JURN3)+SUMIF(JURN2,"1"&A19,JURN4)+SUMIF(JURN1,A19&TEXT(BLN,"mmmm"),JURN4)-SUMIF(JURN1,A19&TEXT(BLN,"mmmm"),JURN3)),VALUE) -> 277134525
A20: 1-102-002 | B20: =VLOOKUP(A20,DAF_AKUN,2,FALSE) -> Employee Receivable | C20: =IF(ISERROR=TRUE,IF(AND(ISERROR=TRUE,VLOOKUP(A20,DAF_AKUN,3,FALSE)="Db"),SUMIF(AKUN1,A20,AKUN2)+SUMIF(JURN2,"1"&A20,JURN3)-SUMIF(JURN2,"1"&A20,JURN4),SUMIF(AKUN1,A20,AKUN3)-SUMIF(JURN2,"1"&A20,JURN3)+SUMIF(JURN2,"1"&A20,JURN4)),VALUE) -> 0 | D20: =IF(ISERROR=TRUE,IF(VLOOKUP(A20,DAF_AKUN,3,FALSE)="Db",SUMIF(AKUN1,A20,AKUN2)+SUMIF(JURN2,"1"&A20,JURN3)-SUMIF(JURN2,"1"&A20,JURN4)+SUMIF(JURN1,A20&TEXT(BLN,"mmmm"),JURN3)-SUMIF(JURN1,A20&TEXT(BLN,"mmmm"),JURN4),SUMIF(AKUN1,A20,AKUN3)-SUMIF(JURN2,"1"&A20,JURN3)+SUMIF(JURN2,"1"&A20,JURN4)+SUMIF(JURN1,A20&TEXT(BLN,"mmmm"),JURN4)-SUMIF(JURN1,A20&TEXT(BLN,"mmmm"),JURN3)),VALUE) -> 0
A21: 1-102-003 | B21: =VLOOKUP(A21,DAF_AKUN,2,FALSE) -> Prepayment / Uang Muka | C21: =IF(ISERROR=TRUE,IF(AND(ISERROR=TRUE,VLOOKUP(A21,DAF_AKUN,3,FALSE)="Db"),SUMIF(AKUN1,A21,AKUN2)+SUMIF(JURN2,"1"&A21,JURN3)-SUMIF(JURN2,"1"&A21,JURN4),SUMIF(AKUN1,A21,AKUN3)-SUMIF(JURN2,"1"&A21,JURN3)+SUMIF(JURN2,"1"&A21,JURN4)),VALUE) -> 0 | D21: =IF(ISERROR=TRUE,IF(VLOOKUP(A21,DAF_AKUN,3,FALSE)="Db",SUMIF(AKUN1,A21,AKUN2)+SUMIF(JURN2,"1"&A21,JURN3)-SUMIF(JURN2,"1"&A21,JURN4)+SUMIF(JURN1,A21&TEXT(BLN,"mmmm"),JURN3)-SUMIF(JURN1,A21&TEXT(BLN,"mmmm"),JURN4),SUMIF(AKUN1,A21,AKUN3)-SUMIF(JURN2,"1"&A21,JURN3)+SUMIF(JURN2,"1"&A21,JURN4)+SUMIF(JURN1,A21&TEXT(BLN,"mmmm"),JURN4)-SUMIF(JURN1,A21&TEXT(BLN,"mmmm"),JURN3)),VALUE) -> 0
A22: 1-102-004 | B22: =VLOOKUP(A22,DAF_AKUN,2,FALSE) -> Other Receivable | C22: =IF(ISERROR=TRUE,IF(AND(ISERROR=TRUE,VLOOKUP(A22,DAF_AKUN,3,FALSE)="Db"),SUMIF(AKUN1,A22,AKUN2)+SUMIF(JURN2,"1"&A22,JURN3)-SUMIF(JURN2,"1"&A22,JURN4),SUMIF(AKUN1,A22,AKUN3)-SUMIF(JURN2,"1"&A22,JURN3)+SUMIF(JURN2,"1"&A22,JURN4)),VALUE) -> 0 | D22: =IF(ISERROR=TRUE,IF(VLOOKUP(A22,DAF_AKUN,3,FALSE)="Db",SUMIF(AKUN1,A22,AKUN2)+SUMIF(JURN2,"1"&A22,JURN3)-SUMIF(JURN2,"1"&A22,JURN4)+SUMIF(JURN1,A22&TEXT(BLN,"mmmm"),JURN3)-SUMIF(JURN1,A22&TEXT(BLN,"mmmm"),JURN4),SUMIF(AKUN1,A22,AKUN3)-SUMIF(JURN2,"1"&A22,JURN3)+SUMIF(JURN2,"1"&A22,JURN4)+SUMIF(JURN1,A22&TEXT(BLN,"mmmm"),JURN4)-SUMIF(JURN1,A22&TEXT(BLN,"mmmm"),JURN3)),VALUE) -> 0
A23: 1-103-000 | B23: =VLOOKUP(A23,DAF_AKUN,2,FALSE) -> Persediaan | C23: =IF(ISERROR=TRUE,IF(AND(ISERROR=TRUE,VLOOKUP(A23,DAF_AKUN,3,FALSE)="Db"),SUMIF(AKUN1,A23,AKUN2)+SUMIF(JURN2,"1"&A23,JURN3)-SUMIF(JURN2,"1"&A23,JURN4),SUMIF(AKUN1,A23,AKUN3)-SUMIF(JURN2,"1"&A23,JURN3)+SUMIF(JURN2,"1"&A23,JURN4)),VALUE) -> 0 | D23: =IF(ISERROR=TRUE,IF(VLOOKUP(A23,DAF_AKUN,3,FALSE)="Db",SUMIF(AKUN1,A23,AKUN2)+SUMIF(JURN2,"1"&A23,JURN3)-SUMIF(JURN2,"1"&A23,JURN4)+SUMIF(JURN1,A23&TEXT(BLN,"mmmm"),JURN3)-SUMIF(JURN1,A23&TEXT(BLN,"mmmm"),JURN4),SUMIF(AKUN1,A23,AKUN3)-SUMIF(JURN2,"1"&A23,JURN3)+SUMIF(JURN2,"1"&A23,JURN4)+SUMIF(JURN1,A23&TEXT(BLN,"mmmm"),JURN4)-SUMIF(JURN1,A23&TEXT(BLN,"mmmm"),JURN3)),VALUE) -> 0
... A41: 1-10999 | B41: =VLOOKUP(A41,DAF_AKUN,2,FALSE) -> Mekari Pay Escrow Account | C41: =IF(ISERROR=TRUE,IF(AND(ISERROR=TRUE,VLOOKUP(A41,DAF_AKUN,3,FALSE)="Db"),SUMIF(AKUN1,A41,AKUN2)+SUMIF(JURN2,"1"&A41,JURN3)-SUMIF(JURN2,"1"&A41,JURN4),SUMIF(AKUN1,A41,AKUN3)-SUMIF(JURN2,"1"&A41,JURN3)+SUMIF(JURN2,"1"&A41,JURN4)),VALUE) -> 0 | D41: =IF(ISERROR=TRUE,IF(VLOOKUP(A41,DAF_AKUN,3,FALSE)="Db",SUMIF(AKUN1,A41,AKUN2)+SUMIF(JURN2,"1"&A41,JURN3)-SUMIF(JURN2,"1"&A41,JURN4)+SUMIF(JURN1,A41&TEXT(BLN,"mmmm"),JURN3)-SUMIF(JURN1,A41&TEXT(BLN,"mmmm"),JURN4),SUMIF(AKUN1,A41,AKUN3)-SUMIF(JURN2,"1"&A41,JURN3)+SUMIF(JURN2,"1"&A41,JURN4)+SUMIF(JURN1,A41&TEXT(BLN,"mmmm"),JURN4)-SUMIF(JURN1,A41&TEXT(BLN,"mmmm"),JURN3)),VALUE) -> 0
B42: Jumlah Aktiva Lancar | C42: =SUM(C8:C41) -> 211545251 | D42: =SUM(D8:D41) -> 280177766
A44: 1-120-000 | B44: =VLOOKUP(A44,DAF_AKUN,2,FALSE) -> Fixed Assets | C44: =IF(ISERROR=TRUE,IF(AND(ISERROR=TRUE,VLOOKUP(A44,DAF_AKUN,3,FALSE)="Db"),SUMIF(AKUN1,A44,AKUN2)+SUMIF(JURN2,"1"&A44,JURN3)-SUMIF(JURN2,"1"&A44,JURN4),SUMIF(AKUN1,A44,AKUN3)-SUMIF(JURN2,"1"&A44,JURN3)+SUMIF(JURN2,"1"&A44,JURN4)),VALUE) -> 0 | D44: =IF(ISERROR=TRUE,IF(VLOOKUP(A44,DAF_AKUN,3,FALSE)="Db",SUMIF(AKUN1,A44,AKUN2)+SUMIF(JURN2,"1"&A44,JURN3)-SUMIF(JURN2,"1"&A44,JURN4)+SUMIF(JURN1,A44&TEXT(BLN,"mmmm"),JURN3)-SUMIF(JURN1,A44&TEXT(BLN,"mmmm"),JURN4),SUMIF(AKUN1,A44,AKUN3)-SUMIF(JURN2,"1"&A44,JURN3)+SUMIF(JURN2,"1"&A44,JURN4)+SUMIF(JURN1,A44&TEXT(BLN,"mmmm"),JURN4)-SUMIF(JURN1,A44&TEXT(BLN,"mmmm"),JURN3)),VALUE) -> 0
A45: 1-120-001 | B45: =VLOOKUP(A45,DAF_AKUN,2,FALSE) -> Building | C45: =IF(ISERROR=TRUE,IF(AND(ISERROR=TRUE,VLOOKUP(A45,DAF_AKUN,3,FALSE)="Db"),SUMIF(AKUN1,A45,AKUN2)+SUMIF(JURN2,"1"&A45,JURN3)-SUMIF(JURN2,"1"&A45,JURN4),SUMIF(AKUN1,A45,AKUN3)-SUMIF(JURN2,"1"&A45,JURN3)+SUMIF(JURN2,"1"&A45,JURN4)),VALUE) -> 0 | D45: =IF(ISERROR=TRUE,IF(VLOOKUP(A45,DAF_AKUN,3,FALSE)="Db",SUMIF(AKUN1,A45,AKUN2)+SUMIF(JURN2,"1"&A45,JURN3)-SUMIF(JURN2,"1"&A45,JURN4)+SUMIF(JURN1,A45&TEXT(BLN,"mmmm"),JURN3)-SUMIF(JURN1,A45&TEXT(BLN,"mmmm"),JURN4),SUMIF(AKUN1,A45,AKUN3)-SUMIF(JURN2,"1"&A45,JURN3)+SUMIF(JURN2,"1"&A45,JURN4)+SUMIF(JURN1,A45&TEXT(BLN,"mmmm"),JURN4)-SUMIF(JURN1,A45&TEXT(BLN,"mmmm"),JURN3)),VALUE) -> 0
A46: 1-120-002 | B46: =VLOOKUP(A46,DAF_AKUN,2,FALSE) -> Building Improvement | C46: =IF(ISERROR=TRUE,IF(AND(ISERROR=TRUE,VLOOKUP(A46,DAF_AKUN,3,FALSE)="Db"),SUMIF(AKUN1,A46,AKUN2)+SUMIF(JURN2,"1"&A46,JURN3)-SUMIF(JURN2,"1"&A46,JURN4),SUMIF(AKUN1,A46,AKUN3)-SUMIF(JURN2,"1"&A46,JURN3)+SUMIF(JURN2,"1"&A46,JURN4)),VALUE) -> 0 | D46: =IF(ISERROR=TRUE,IF(VLOOKUP(A46,DAF_AKUN,3,FALSE)="Db",SUMIF(AKUN1,A46,AKUN2)+SUMIF(JURN2,"1"&A46,JURN3)-SUMIF(JURN2,"1"&A46,JURN4)+SUMIF(JURN1,A46&TEXT(BLN,"mmmm"),JURN3)-SUMIF(JURN1,A46&TEXT(BLN,"mmmm"),JURN4),SUMIF(AKUN1,A46,AKUN3)-SUMIF(JURN2,"1"&A46,JURN3)+SUMIF(JURN2,"1"&A46,JURN4)+SUMIF(JURN1,A46&TEXT(BLN,"mmmm"),JURN4)-SUMIF(JURN1,A46&TEXT(BLN,"mmmm"),JURN3)),VALUE) -> 0
A47: 1-120-003 | B47: =VLOOKUP(A47,DAF_AKUN,2,FALSE) -> Motor Vehicles | C47: =IF(ISERROR=TRUE,IF(AND(ISERROR=TRUE,VLOOKUP(A47,DAF_AKUN,3,FALSE)="Db"),SUMIF(AKUN1,A47,AKUN2)+SUMIF(JURN2,"1"&A47,JURN3)-SUMIF(JURN2,"1"&A47,JURN4),SUMIF(AKUN1,A47,AKUN3)-SUMIF(JURN2,"1"&A47,JURN3)+SUMIF(JURN2,"1"&A47,JURN4)),VALUE) -> 0 | D47: =IF(ISERROR=TRUE,IF(VLOOKUP(A47,DAF_AKUN,3,FALSE)="Db",SUMIF(AKUN1,A47,AKUN2)+SUMIF(JURN2,"1"&A47,JURN3)-SUMIF(JURN2,"1"&A47,JURN4)+SUMIF(JURN1,A47&TEXT(BLN,"mmmm"),JURN3)-SUMIF(JURN1,A47&TEXT(BLN,"mmmm"),JURN4),SUMIF(AKUN1,A47,AKUN3)-SUMIF(JURN2,"1"&A47,JURN3)+SUMIF(JURN2,"1"&A47,JURN4)+SUMIF(JURN1,A47&TEXT(BLN,"mmmm"),JURN4)-SUMIF(JURN1,A47&TEXT(BLN,"mmmm"),JURN3)),VALUE) -> 0
A48: 1-120-004 | B48: =VLOOKUP(A48,DAF_AKUN,2,FALSE) -> Office Furniture & Equipment | C48: =IF(ISERROR=TRUE,IF(AND(ISERROR=TRUE,VLOOKUP(A48,DAF_AKUN,3,FALSE)="Db"),SUMIF(AKUN1,A48,AKUN2)+SUMIF(JURN2,"1"&A48,JURN3)-SUMIF(JURN2,"1"&A48,JURN4),SUMIF(AKUN1,A48,AKUN3)-SUMIF(JURN2,"1"&A48,JURN3)+SUMIF(JURN2,"1"&A48,JURN4)),VALUE) -> 0 | D48: =IF(ISERROR=TRUE,IF(VLOOKUP(A48,DAF_AKUN,3,FALSE)="Db",SUMIF(AKUN1,A48,AKUN2)+SUMIF(JURN2,"1"&A48,JURN3)-SUMIF(JURN2,"1"&A48,JURN4)+SUMIF(JURN1,A48&TEXT(BLN,"mmmm"),JURN3)-SUMIF(JURN1,A48&TEXT(BLN,"mmmm"),JURN4),SUMIF(AKUN1,A48,AKUN3)-SUMIF(JURN2,"1"&A48,JURN3)+SUMIF(JURN2,"1"&A48,JURN4)+SUMIF(JURN1,A48&TEXT(BLN,"mmmm"),JURN4)-SUMIF(JURN1,A48&TEXT(BLN,"mmmm"),JURN3)),VALUE) -> 0
A49: 1-120-005 | B49: =VLOOKUP(A49,DAF_AKUN,2,FALSE) -> Electronics & IT Equipment | C49: =IF(ISERROR=TRUE,IF(AND(ISERROR=TRUE,VLOOKUP(A49,DAF_AKUN,3,FALSE)="Db"),SUMIF(AKUN1,A49,AKUN2)+SUMIF(JURN2,"1"&A49,JURN3)-SUMIF(JURN2,"1"&A49,JURN4),SUMIF(AKUN1,A49,AKUN3)-SUMIF(JURN2,"1"&A49,JURN3)+SUMIF(JURN2,"1"&A49,JURN4)),VALUE) -> 9550321 | D49: =IF(ISERROR=TRUE,IF(VLOOKUP(A49,DAF_AKUN,3,FALSE)="Db",SUMIF(AKUN1,A49,AKUN2)+SUMIF(JURN2,"1"&A49,JURN3)-SUMIF(JURN2,"1"&A49,JURN4)+SUMIF(JURN1,A49&TEXT(BLN,"mmmm"),JURN3)-SUMIF(JURN1,A49&TEXT(BLN,"mmmm"),JURN4),SUMIF(AKUN1,A49,AKUN3)-SUMIF(JURN2,"1"&A49,JURN3)+SUMIF(JURN2,"1"&A49,JURN4)+SUMIF(JURN1,A49&TEXT(BLN,"mmmm"),JURN4)-SUMIF(JURN1,A49&TEXT(BLN,"mmmm"),JURN3)),VALUE) -> 9550321
A50: 1-120-101 | B50: =VLOOKUP(A50,DAF_AKUN,2,FALSE) -> Acc. Depreciation - Land & Building | C50: =IF(ISERROR=TRUE,IF(AND(ISERROR=TRUE,VLOOKUP(A50,DAF_AKUN,3,FALSE)="Db"),SUMIF(AKUN1,A50,AKUN2)+SUMIF(JURN2,"1"&A50,JURN3)-SUMIF(JURN2,"1"&A50,JURN4),SUMIF(AKUN1,A50,AKUN3)-SUMIF(JURN2,"1"&A50,JURN3)+SUMIF(JURN2,"1"&A50,JURN4)),VALUE) -> 0 | D50: =IF(ISERROR=TRUE,IF(VLOOKUP(A50,DAF_AKUN,3,FALSE)="Db",SUMIF(AKUN1,A50,AKUN2)+SUMIF(JURN2,"1"&A50,JURN3)-SUMIF(JURN2,"1"&A50,JURN4)+SUMIF(JURN1,A50&TEXT(BLN,"mmmm"),JURN3)-SUMIF(JURN1,A50&TEXT(BLN,"mmmm"),JURN4),SUMIF(AKUN1,A50,AKUN3)-SUMIF(JURN2,"1"&A50,JURN3)+SUMIF(JURN2,"1"&A50,JURN4)+SUMIF(JURN1,A50&TEXT(BLN,"mmmm"),JURN4)-SUMIF(JURN1,A50&TEXT(BLN,"mmmm"),JURN3)),VALUE) -> 0
A51: 1-120-102 | B51: =VLOOKUP(A51,DAF_AKUN,2,FALSE) -> Acc. Depreciation - Building Improvement | C51: =IF(ISERROR=TRUE,IF(AND(ISERROR=TRUE,VLOOKUP(A51,DAF_AKUN,3,FALSE)="Db"),SUMIF(AKUN1,A51,AKUN2)+SUMIF(JURN2,"1"&A51,JURN3)-SUMIF(JURN2,"1"&A51,JURN4),SUMIF(AKUN1,A51,AKUN3)-SUMIF(JURN2,"1"&A51,JURN3)+SUMIF(JURN2,"1"&A51,JURN4)),VALUE) -> 0 | D51: =IF(ISERROR=TRUE,IF(VLOOKUP(A51,DAF_AKUN,3,FALSE)="Db",SUMIF(AKUN1,A51,AKUN2)+SUMIF(JURN2,"1"&A51,JURN3)-SUMIF(JURN2,"1"&A51,JURN4)+SUMIF(JURN1,A51&TEXT(BLN,"mmmm"),JURN3)-SUMIF(JURN1,A51&TEXT(BLN,"mmmm"),JURN4),SUMIF(AKUN1,A51,AKUN3)-SUMIF(JURN2,"1"&A51,JURN3)+SUMIF(JURN2,"1"&A51,JURN4)+SUMIF(JURN1,A51&TEXT(BLN,"mmmm"),JURN4)-SUMIF(JURN1,A51&TEXT(BLN,"mmmm"),JURN3)),VALUE) -> 0
A52: 1-120-103 | B52: =VLOOKUP(A52,DAF_AKUN,2,FALSE) -> Acc. Depreciation - Motor Vehicles | C52: =IF(ISERROR=TRUE,IF(AND(ISERROR=TRUE,VLOOKUP(A52,DAF_AKUN,3,FALSE)="Db"),SUMIF(AKUN1,A52,AKUN2)+SUMIF(JURN2,"1"&A52,JURN3)-SUMIF(JURN2,"1"&A52,JURN4),SUMIF(AKUN1,A52,AKUN3)-SUMIF(JURN2,"1"&A52,JURN3)+SUMIF(JURN2,"1"&A52,JURN4)),VALUE) -> 0 | D52: =IF(ISERROR=TRUE,IF(VLOOKUP(A52,DAF_AKUN,3,FALSE)="Db",SUMIF(AKUN1,A52,AKUN2)+SUMIF(JURN2,"1"&A52,JURN3)-SUMIF(JURN2,"1"&A52,JURN4)+SUMIF(JURN1,A52&TEXT(BLN,"mmmm"),JURN3)-SUMIF(JURN1,A52&TEXT(BLN,"mmmm"),JURN4),SUMIF(AKUN1,A52,AKUN3)-SUMIF(JURN2,"1"&A52,JURN3)+SUMIF(JURN2,"1"&A52,JURN4)+SUMIF(JURN1,A52&TEXT(BLN,"mmmm"),JURN4)-SUMIF(JURN1,A52&TEXT(BLN,"mmmm"),JURN3)),VALUE) -> 0
A53: 1-120-104 | B53: =VLOOKUP(A53,DAF_AKUN,2,FALSE) -> Acc. Depreciation - Office Furniture & Equipment | C53: =IF(ISERROR=TRUE,IF(AND(ISERROR=TRUE,VLOOKUP(A53,DAF_AKUN,3,FALSE)="Db"),SUMIF(AKUN1,A53,AKUN2)+SUMIF(JURN2,"1"&A53,JURN3)-SUMIF(JURN2,"1"&A53,JURN4),SUMIF(AKUN1,A53,AKUN3)-SUMIF(JURN2,"1"&A53,JURN3)+SUMIF(JURN2,"1"&A53,JURN4)),VALUE) -> 0 | D53: =IF(ISERROR=TRUE,IF(VLOOKUP(A53,DAF_AKUN,3,FALSE)="Db",SUMIF(AKUN1,A53,AKUN2)+SUMIF(JURN2,"1"&A53,JURN3)-SUMIF(JURN2,"1"&A53,JURN4)+SUMIF(JURN1,A53&TEXT(BLN,"mmmm"),JURN3)-SUMIF(JURN1,A53&TEXT(BLN,"mmmm"),JURN4),SUMIF(AKUN1,A53,AKUN3)-SUMIF(JURN2,"1"&A53,JURN3)+SUMIF(JURN2,"1"&A53,JURN4)+SUMIF(JURN1,A53&TEXT(BLN,"mmmm"),JURN4)-SUMIF(JURN1,A53&TEXT(BLN,"mmmm"),JURN3)),VALUE) -> 0
A54: 1-120-105 | B54: =VLOOKUP(A54,DAF_AKUN,2,FALSE) -> Acc. Depreciation - Electronics & IT Equipment | C54: =IF(ISERROR=TRUE,IF(AND(ISERROR=TRUE,VLOOKUP(A54,DAF_AKUN,3,FALSE)="Db"),SUMIF(AKUN1,A54,AKUN2)+SUMIF(JURN2,"1"&A54,JURN3)-SUMIF(JURN2,"1"&A54,JURN4),SUMIF(AKUN1,A54,AKUN3)-SUMIF(JURN2,"1"&A54,JURN3)+SUMIF(JURN2,"1"&A54,JURN4)),VALUE) -> -476032 | D54: =IF(ISERROR=TRUE,IF(VLOOKUP(A54,DAF_AKUN,3,FALSE)="Db",SUMIF(AKUN1,A54,AKUN2)+SUMIF(JURN2,"1"&A54,JURN3)-SUMIF(JURN2,"1"&A54,JURN4)+SUMIF(JURN1,A54&TEXT(BLN,"mmmm"),JURN3)-SUMIF(JURN1,A54&TEXT(BLN,"mmmm"),JURN4),SUMIF(AKUN1,A54,AKUN3)-SUMIF(JURN2,"1"&A54,JURN3)+SUMIF(JURN2,"1"&A54,JURN4)+SUMIF(JURN1,A54&TEXT(BLN,"mmmm"),JURN4)-SUMIF(JURN1,A54&TEXT(BLN,"mmmm"),JURN3)),VALUE) -> -476032
A55: 1-120-999 | B55: =VLOOKUP(A55,DAF_AKUN,2,FALSE) -> Other Asset | C55: =IF(ISERROR=TRUE,IF(AND(ISERROR=TRUE,VLOOKUP(A55,DAF_AKUN,3,FALSE)="Db"),SUMIF(AKUN1,A55,AKUN2)+SUMIF(JURN2,"1"&A55,JURN3)-SUMIF(JURN2,"1"&A55,JURN4),SUMIF(AKUN1,A55,AKUN3)-SUMIF(JURN2,"1"&A55,JURN3)+SUMIF(JURN2,"1"&A55,JURN4)),VALUE) -> 0 | D55: =IF(ISERROR=TRUE,IF(VLOOKUP(A55,DAF_AKUN,3,FALSE)="Db",SUMIF(AKUN1,A55,AKUN2)+SUMIF(JURN2,"1"&A55,JURN3)-SUMIF(JURN2,"1"&A55,JURN4)+SUMIF(JURN1,A55&TEXT(BLN,"mmmm"),JURN3)-SUMIF(JURN1,A55&TEXT(BLN,"mmmm"),JURN4),SUMIF(AKUN1,A55,AKUN3)-SUMIF(JURN2,"1"&A55,JURN3)+SUMIF(JURN2,"1"&A55,JURN4)+SUMIF(JURN1,A55&TEXT(BLN,"mmmm"),JURN4)-SUMIF(JURN1,A55&TEXT(BLN,"mmmm"),JURN3)),VALUE) -> 0
B56: Jumlah Aktiva Tetap | C56: =SUM(C44:C55) -> 9074289 | D56: =SUM(D44:D55) -> 9074289
B58: TOTAL AKTIVA | C58: =C42+C56 -> 220619540 | D58: =D42+D56 -> 289252055
A60: 2-130-000 | B60: =VLOOKUP(A60,DAF_AKUN,2,FALSE) -> Account Payable | C60: =IF(ISERROR=TRUE,IF(AND(ISERROR=TRUE,VLOOKUP(A60,DAF_AKUN,3,FALSE)="Db"),SUMIF(AKUN1,A60,AKUN2)+SUMIF(JURN2,"1"&A60,JURN3)-SUMIF(JURN2,"1"&A60,JURN4),SUMIF(AKUN1,A60,AKUN3)-SUMIF(JURN2,"1"&A60,JURN3)+SUMIF(JURN2,"1"&A60,JURN4)),VALUE) -> 0 | D60: =IF(ISERROR=TRUE,IF(VLOOKUP(A60,DAF_AKUN,3,FALSE)="Db",SUMIF(AKUN1,A60,AKUN2)+SUMIF(JURN2,"1"&A60,JURN3)-SUMIF(JURN2,"1"&A60,JURN4)+SUMIF(JURN1,A60&TEXT(BLN,"mmmm"),JURN3)-SUMIF(JURN1,A60&TEXT(BLN,"mmmm"),JURN4),SUMIF(AKUN1,A60,AKUN3)-SUMIF(JURN2,"1"&A60,JURN3)+SUMIF(JURN2,"1"&A60,JURN4)+SUMIF(JURN1,A60&TEXT(BLN,"mmmm"),JURN4)-SUMIF(JURN1,A60&TEXT(BLN,"mmmm"),JURN3)),VALUE) -> 0
A61: 2-130-001 | B61: =VLOOKUP(A61,DAF_AKUN,2,FALSE) -> Account Payable - Trade | C61: =IF(ISERROR=TRUE,IF(AND(ISERROR=TRUE,VLOOKUP(A61,DAF_AKUN,3,FALSE)="Db"),SUMIF(AKUN1,A61,AKUN2)+SUMIF(JURN2,"1"&A61,JURN3)-SUMIF(JURN2,"1"&A61,JURN4),SUMIF(AKUN1,A61,AKUN3)-SUMIF(JURN2,"1"&A61,JURN3)+SUMIF(JURN2,"1"&A61,JURN4)),VALUE) -> 0 | D61: =IF(ISERROR=TRUE,IF(VLOOKUP(A61,DAF_AKUN,3,FALSE)="Db",SUMIF(AKUN1,A61,AKUN2)+SUMIF(JURN2,"1"&A61,JURN3)-SUMIF(JURN2,"1"&A61,JURN4)+SUMIF(JURN1,A61&TEXT(BLN,"mmmm"),JURN3)-SUMIF(JURN1,A61&TEXT(BLN,"mmmm"),JURN4),SUMIF(AKUN1,A61,AKUN3)-SUMIF(JURN2,"1"&A61,JURN3)+SUMIF(JURN2,"1"&A61,JURN4)+SUMIF(JURN1,A61&TEXT(BLN,"mmmm"),JURN4)-SUMIF(JURN1,A61&TEXT(BLN,"mmmm"),JURN3)),VALUE) -> 0
A62: 2-140-000 | B62: =VLOOKUP(A62,DAF_AKUN,2,FALSE) -> Other Payable | C62: =IF(ISERROR=TRUE,IF(AND(ISERROR=TRUE,VLOOKUP(A62,DAF_AKUN,3,FALSE)="Db"),SUMIF(AKUN1,A62,AKUN2)+SUMIF(JURN2,"1"&A62,JURN3)-SUMIF(JURN2,"1"&A62,JURN4),SUMIF(AKUN1,A62,AKUN3)-SUMIF(JURN2,"1"&A62,JURN3)+SUMIF(JURN2,"1"&A62,JURN4)),VALUE) -> 0 | D62: =IF(ISERROR=TRUE,IF(VLOOKUP(A62,DAF_AKUN,3,FALSE)="Db",SUMIF(AKUN1,A62,AKUN2)+SUMIF(JURN2,"1"&A62,JURN3)-SUMIF(JURN2,"1"&A62,JURN4)+SUMIF(JURN1,A62&TEXT(BLN,"mmmm"),JURN3)-SUMIF(JURN1,A62&TEXT(BLN,"mmmm"),JURN4),SUMIF(AKUN1,A62,AKUN3)-SUMIF(JURN2,"1"&A62,JURN3)+SUMIF(JURN2,"1"&A62,JURN4)+SUMIF(JURN1,A62&TEXT(BLN,"mmmm"),JURN4)-SUMIF(JURN1,A62&TEXT(BLN,"mmmm"),JURN3)),VALUE) -> 0
A63: 2-140-001 | B63: =VLOOKUP(A63,DAF_AKUN,2,FALSE) -> Salary Payable | C63: =IF(ISERROR=TRUE,IF(AND(ISERROR=TRUE,VLOOKUP(A63,DAF_AKUN,3,FALSE)="Db"),SUMIF(AKUN1,A63,AKUN2)+SUMIF(JURN2,"1"&A63,JURN3)-SUMIF(JURN2,"1"&A63,JURN4),SUMIF(AKUN1,A63,AKUN3)-SUMIF(JURN2,"1"&A63,JURN3)+SUMIF(JURN2,"1"&A63,JURN4)),VALUE) -> 0 | D63: =IF(ISERROR=TRUE,IF(VLOOKUP(A63,DAF_AKUN,3,FALSE)="Db",SUMIF(AKUN1,A63,AKUN2)+SUMIF(JURN2,"1"&A63,JURN3)-SUMIF(JURN2,"1"&A63,JURN4)+SUMIF(JURN1,A63&TEXT(BLN,"mmmm"),JURN3)-SUMIF(JURN1,A63&TEXT(BLN,"mmmm"),JURN4),SUMIF(AKUN1,A63,AKUN3)-SUMIF(JURN2,"1"&A63,JURN3)+SUMIF(JURN2,"1"&A63,JURN4)+SUMIF(JURN1,A63&TEXT(BLN,"mmmm"),JURN4)-SUMIF(JURN1,A63&TEXT(BLN,"mmmm"),JURN3)),VALUE) -> 0
A64: 2-140-010 | B64: =VLOOKUP(A64,DAF_AKUN,2,FALSE) -> BPJS Payable | C64: =IF(ISERROR=TRUE,IF(AND(ISERROR=TRUE,VLOOKUP(A64,DAF_AKUN,3,FALSE)="Db"),SUMIF(AKUN1,A64,AKUN2)+SUMIF(JURN2,"1"&A64,JURN3)-SUMIF(JURN2,"1"&A64,JURN4),SUMIF(AKUN1,A64,AKUN3)-SUMIF(JURN2,"1"&A64,JURN3)+SUMIF(JURN2,"1"&A64,JURN4)),VALUE) -> 0 | D64: =IF(ISERROR=TRUE,IF(VLOOKUP(A64,DAF_AKUN,3,FALSE)="Db",SUMIF(AKUN1,A64,AKUN2)+SUMIF(JURN2,"1"&A64,JURN3)-SUMIF(JURN2,"1"&A64,JURN4)+SUMIF(JURN1,A64&TEXT(BLN,"mmmm"),JURN3)-SUMIF(JURN1,A64&TEXT(BLN,"mmmm"),JURN4),SUMIF(AKUN1,A64,AKUN3)-SUMIF(JURN2,"1"&A64,JURN3)+SUMIF(JURN2,"1"&A64,JURN4)+SUMIF(JURN1,A64&TEXT(BLN,"mmmm"),JURN4)-SUMIF(JURN1,A64&TEXT(BLN,"mmmm"),JURN3)),VALUE) -> 0
A65: 2-140-020 | B65: =VLOOKUP(A65,DAF_AKUN,2,FALSE) -> Accrued Expenses - General | C65: =IF(ISERROR=TRUE,IF(AND(ISERROR=TRUE,VLOOKUP(A65,DAF_AKUN,3,FALSE)="Db"),SUMIF(AKUN1,A65,AKUN2)+SUMIF(JURN2,"1"&A65,JURN3)-SUMIF(JURN2,"1"&A65,JURN4),SUMIF(AKUN1,A65,AKUN3)-SUMIF(JURN2,"1"&A65,JURN3)+SUMIF(JURN2,"1"&A65,JURN4)),VALUE) -> 0 | D65: =IF(ISERROR=TRUE,IF(VLOOKUP(A65,DAF_AKUN,3,FALSE)="Db",SUMIF(AKUN1,A65,AKUN2)+SUMIF(JURN2,"1"&A65,JURN3)-SUMIF(JURN2,"1"&A65,JURN4)+SUMIF(JURN1,A65&TEXT(BLN,"mmmm"),JURN3)-SUMIF(JURN1,A65&TEXT(BLN,"mmmm"),JURN4),SUMIF(AKUN1,A65,AKUN3)-SUMIF(JURN2,"1"&A65,JURN3)+SUMIF(JURN2,"1"&A65,JURN4)+SUMIF(JURN1,A65&TEXT(BLN,"mmmm"),JURN4)-SUMIF(JURN1,A65&TEXT(BLN,"mmmm"),JURN3)),VALUE) -> 0
A66: 2-140-021 | B66: =VLOOKUP(A66,DAF_AKUN,2,FALSE) -> Accrued Expenses - Project | C66: =IF(ISERROR=TRUE,IF(AND(ISERROR=TRUE,VLOOKUP(A66,DAF_AKUN,3,FALSE)="Db"),SUMIF(AKUN1,A66,AKUN2)+SUMIF(JURN2,"1"&A66,JURN3)-SUMIF(JURN2,"1"&A66,JURN4),SUMIF(AKUN1,A66,AKUN3)-SUMIF(JURN2,"1"&A66,JURN3)+SUMIF(JURN2,"1"&A66,JURN4)),VALUE) -> 0 | D66: =IF(ISERROR=TRUE,IF(VLOOKUP(A66,DAF_AKUN,3,FALSE)="Db",SUMIF(AKUN1,A66,AKUN2)+SUMIF(JURN2,"1"&A66,JURN3)-SUMIF(JURN2,"1"&A66,JURN4)+SUMIF(JURN1,A66&TEXT(BLN,"mmmm"),JURN3)-SUMIF(JURN1,A66&TEXT(BLN,"mmmm"),JURN4),SUMIF(AKUN1,A66,AKUN3)-SUMIF(JURN2,"1"&A66,JURN3)+SUMIF(JURN2,"1"&A66,JURN4)+SUMIF(JURN1,A66&TEXT(BLN,"mmmm"),JURN4)-SUMIF(JURN1,A66&TEXT(BLN,"mmmm"),JURN3)),VALUE) -> 0
A67: 2-140-030 | B67: =VLOOKUP(A67,DAF_AKUN,2,FALSE) -> Tax Payable - PPh Ps 21/26 | C67: =IF(ISERROR=TRUE,IF(AND(ISERROR=TRUE,VLOOKUP(A67,DAF_AKUN,3,FALSE)="Db"),SUMIF(AKUN1,A67,AKUN2)+SUMIF(JURN2,"1"&A67,JURN3)-SUMIF(JURN2,"1"&A67,JURN4),SUMIF(AKUN1,A67,AKUN3)-SUMIF(JURN2,"1"&A67,JURN3)+SUMIF(JURN2,"1"&A67,JURN4)),VALUE) -> 0 | D67: =IF(ISERROR=TRUE,IF(VLOOKUP(A67,DAF_AKUN,3,FALSE)="Db",SUMIF(AKUN1,A67,AKUN2)+SUMIF(JURN2,"1"&A67,JURN3)-SUMIF(JURN2,"1"&A67,JURN4)+SUMIF(JURN1,A67&TEXT(BLN,"mmmm"),JURN3)-SUMIF(JURN1,A67&TEXT(BLN,"mmmm"),JURN4),SUMIF(AKUN1,A67,AKUN3)-SUMIF(JURN2,"1"&A67,JURN3)+SUMIF(JURN2,"1"&A67,JURN4)+SUMIF(JURN1,A67&TEXT(BLN,"mmmm"),JURN4)-SUMIF(JURN1,A67&TEXT(BLN,"mmmm"),JURN3)),VALUE) -> 0
A68: 2-140-031 | B68: =VLOOKUP(A68,DAF_AKUN,2,FALSE) -> Tax Payable - PPh Ps 23 | C68: =IF(ISERROR=TRUE,IF(AND(ISERROR=TRUE,VLOOKUP(A68,DAF_AKUN,3,FALSE)="Db"),SUMIF(AKUN1,A68,AKUN2)+SUMIF(JURN2,"1"&A68,JURN3)-SUMIF(JURN2,"1"&A68,JURN4),SUMIF(AKUN1,A68,AKUN3)-SUMIF(JURN2,"1"&A68,JURN3)+SUMIF(JURN2,"1"&A68,JURN4)),VALUE) -> 0 | D68: =IF(ISERROR=TRUE,IF(VLOOKUP(A68,DAF_AKUN,3,FALSE)="Db",SUMIF(AKUN1,A68,AKUN2)+SUMIF(JURN2,"1"&A68,JURN3)-SUMIF(JURN2,"1"&A68,JURN4)+SUMIF(JURN1,A68&TEXT(BLN,"mmmm"),JURN3)-SUMIF(JURN1,A68&TEXT(BLN,"mmmm"),JURN4),SUMIF(AKUN1,A68,AKUN3)-SUMIF(JURN2,"1"&A68,JURN3)+SUMIF(JURN2,"1"&A68,JURN4)+SUMIF(JURN1,A68&TEXT(BLN,"mmmm"),JURN4)-SUMIF(JURN1,A68&TEXT(BLN,"mmmm"),JURN3)),VALUE) -> 0
A69: 2-140-032 | B69: =VLOOKUP(A69,DAF_AKUN,2,FALSE) -> Tax Payable - PPh Ps 29 | C69: =IF(ISERROR=TRUE,IF(AND(ISERROR=TRUE,VLOOKUP(A69,DAF_AKUN,3,FALSE)="Db"),SUMIF(AKUN1,A69,AKUN2)+SUMIF(JURN2,"1"&A69,JURN3)-SUMIF(JURN2,"1"&A69,JURN4),SUMIF(AKUN1,A69,AKUN3)-SUMIF(JURN2,"1"&A69,JURN3)+SUMIF(JURN2,"1"&A69,JURN4)),VALUE) -> 0 | D69: =IF(ISERROR=TRUE,IF(VLOOKUP(A69,DAF_AKUN,3,FALSE)="Db",SUMIF(AKUN1,A69,AKUN2)+SUMIF(JURN2,"1"&A69,JURN3)-SUMIF(JURN2,"1"&A69,JURN4)+SUMIF(JURN1,A69&TEXT(BLN,"mmmm"),JURN3)-SUMIF(JURN1,A69&TEXT(BLN,"mmmm"),JURN4),SUMIF(AKUN1,A69,AKUN3)-SUMIF(JURN2,"1"&A69,JURN3)+SUMIF(JURN2,"1"&A69,JURN4)+SUMIF(JURN1,A69&TEXT(BLN,"mmmm"),JURN4)-SUMIF(JURN1,A69&TEXT(BLN,"mmmm"),JURN3)),VALUE) -> 0
A70: 2-140-033 | B70: =VLOOKUP(A70,DAF_AKUN,2,FALSE) -> Tax Payable - PPh Ps 4 (2) | C70: =IF(ISERROR=TRUE,IF(AND(ISERROR=TRUE,VLOOKUP(A70,DAF_AKUN,3,FALSE)="Db"),SUMIF(AKUN1,A70,AKUN2)+SUMIF(JURN2,"1"&A70,JURN3)-SUMIF(JURN2,"1"&A70,JURN4),SUMIF(AKUN1,A70,AKUN3)-SUMIF(JURN2,"1"&A70,JURN3)+SUMIF(JURN2,"1"&A70,JURN4)),VALUE) -> 0 | D70: =IF(ISERROR=TRUE,IF(VLOOKUP(A70,DAF_AKUN,3,FALSE)="Db",SUMIF(AKUN1,A70,AKUN2)+SUMIF(JURN2,"1"&A70,JURN3)-SUMIF(JURN2,"1"&A70,JURN4)+SUMIF(JURN1,A70&TEXT(BLN,"mmmm"),JURN3)-SUMIF(JURN1,A70&TEXT(BLN,"mmmm"),JURN4),SUMIF(AKUN1,A70,AKUN3)-SUMIF(JURN2,"1"&A70,JURN3)+SUMIF(JURN2,"1"&A70,JURN4)+SUMIF(JURN1,A70&TEXT(BLN,"mmmm"),JURN4)-SUMIF(JURN1,A70&TEXT(BLN,"mmmm"),JURN3)),VALUE) -> 0
A71: 2-140-040 | B71: =VLOOKUP(A71,DAF_AKUN,2,FALSE) -> Dividend Payable | C71: =IF(ISERROR=TRUE,IF(AND(ISERROR=TRUE,VLOOKUP(A71,DAF_AKUN,3,FALSE)="Db"),SUMIF(AKUN1,A71,AKUN2)+SUMIF(JURN2,"1"&A71,JURN3)-SUMIF(JURN2,"1"&A71,JURN4),SUMIF(AKUN1,A71,AKUN3)-SUMIF(JURN2,"1"&A71,JURN3)+SUMIF(JURN2,"1"&A71,JURN4)),VALUE) -> 0 | D71: =IF(ISERROR=TRUE,IF(VLOOKUP(A71,DAF_AKUN,3,FALSE)="Db",SUMIF(AKUN1,A71,AKUN2)+SUMIF(JURN2,"1"&A71,JURN3)-SUMIF(JURN2,"1"&A71,JURN4)+SUMIF(JURN1,A71&TEXT(BLN,"mmmm"),JURN3)-SUMIF(JURN1,A71&TEXT(BLN,"mmmm"),JURN4),SUMIF(AKUN1,A71,AKUN3)-SUMIF(JURN2,"1"&A71,JURN3)+SUMIF(JURN2,"1"&A71,JURN4)+SUMIF(JURN1,A71&TEXT(BLN,"mmmm"),JURN4)-SUMIF(JURN1,A71&TEXT(BLN,"mmmm"),JURN3)),VALUE) -> 0
... A86: 2-170-006 | B86: =VLOOKUP(A86,DAF_AKUN,2,FALSE) -> PPN Keluaran | C86: =IF(ISERROR=TRUE,IF(AND(ISERROR=TRUE,VLOOKUP(A86,DAF_AKUN,3,FALSE)="Db"),SUMIF(AKUN1,A86,AKUN2)+SUMIF(JURN2,"1"&A86,JURN3)-SUMIF(JURN2,"1"&A86,JURN4),SUMIF(AKUN1,A86,AKUN3)-SUMIF(JURN2,"1"&A86,JURN3)+SUMIF(JURN2,"1"&A86,JURN4)),VALUE) -> 0 | D86: =IF(ISERROR=TRUE,IF(VLOOKUP(A86,DAF_AKUN,3,FALSE)="Db",SUMIF(AKUN1,A86,AKUN2)+SUMIF(JURN2,"1"&A86,JURN3)-SUMIF(JURN2,"1"&A86,JURN4)+SUMIF(JURN1,A86&TEXT(BLN,"mmmm"),JURN3)-SUMIF(JURN1,A86&TEXT(BLN,"mmmm"),JURN4),SUMIF(AKUN1,A86,AKUN3)-SUMIF(JURN2,"1"&A86,JURN3)+SUMIF(JURN2,"1"&A86,JURN4)+SUMIF(JURN1,A86&TEXT(BLN,"mmmm"),JURN4)-SUMIF(JURN1,A86&TEXT(BLN,"mmmm"),JURN3)),VALUE) -> 0
B87: Jumlah Kewajiban | C87: =SUM(C60:C86) -> 10000 | D87: =SUM(D60:D86) -> 10000
A89: 3-100-000 | B89: =VLOOKUP(A89,DAF_AKUN,2,FALSE) -> Equities & Retained Earnings | C89: =IF(ISERROR=TRUE,IF(AND(ISERROR=TRUE,VLOOKUP(A89,DAF_AKUN,3,FALSE)="Db"),SUMIF(AKUN1,A89,AKUN2)+SUMIF(JURN2,"1"&A89,JURN3)-SUMIF(JURN2,"1"&A89,JURN4),SUMIF(AKUN1,A89,AKUN3)-SUMIF(JURN2,"1"&A89,JURN3)+SUMIF(JURN2,"1"&A89,JURN4)),VALUE) -> 0 | D89: =IF(ISERROR=TRUE,IF(VLOOKUP(A89,DAF_AKUN,3,FALSE)="Db",SUMIF(AKUN1,A89,AKUN2)+SUMIF(JURN2,"1"&A89,JURN3)-SUMIF(JURN2,"1"&A89,JURN4)+SUMIF(JURN1,A89&TEXT(BLN,"mmmm"),JURN3)-SUMIF(JURN1,A89&TEXT(BLN,"mmmm"),JURN4),SUMIF(AKUN1,A89,AKUN3)-SUMIF(JURN2,"1"&A89,JURN3)+SUMIF(JURN2,"1"&A89,JURN4)+SUMIF(JURN1,A89&TEXT(BLN,"mmmm"),JURN4)-SUMIF(JURN1,A89&TEXT(BLN,"mmmm"),JURN3)),VALUE) -> 0
A90: 3-101-000 | B90: =VLOOKUP(A90,DAF_AKUN,2,FALSE) -> Shareholdership | C90: =IF(ISERROR=TRUE,IF(AND(ISERROR=TRUE,VLOOKUP(A90,DAF_AKUN,3,FALSE)="Db"),SUMIF(AKUN1,A90,AKUN2)+SUMIF(JURN2,"1"&A90,JURN3)-SUMIF(JURN2,"1"&A90,JURN4),SUMIF(AKUN1,A90,AKUN3)-SUMIF(JURN2,"1"&A90,JURN3)+SUMIF(JURN2,"1"&A90,JURN4)),VALUE) -> 0 | D90: =IF(ISERROR=TRUE,IF(VLOOKUP(A90,DAF_AKUN,3,FALSE)="Db",SUMIF(AKUN1,A90,AKUN2)+SUMIF(JURN2,"1"&A90,JURN3)-SUMIF(JURN2,"1"&A90,JURN4)+SUMIF(JURN1,A90&TEXT(BLN,"mmmm"),JURN3)-SUMIF(JURN1,A90&TEXT(BLN,"mmmm"),JURN4),SUMIF(AKUN1,A90,AKUN3)-SUMIF(JURN2,"1"&A90,JURN3)+SUMIF(JURN2,"1"&A90,JURN4)+SUMIF(JURN1,A90&TEXT(BLN,"mmmm"),JURN4)-SUMIF(JURN1,A90&TEXT(BLN,"mmmm"),JURN3)),VALUE) -> 0
A91: 3-101-001 | B91: =VLOOKUP(A91,DAF_AKUN,2,FALSE) -> Paid-up Capital | C91: =IF(ISERROR=TRUE,IF(AND(ISERROR=TRUE,VLOOKUP(A91,DAF_AKUN,3,FALSE)="Db"),SUMIF(AKUN1,A91,AKUN2)+SUMIF(JURN2,"1"&A91,JURN3)-SUMIF(JURN2,"1"&A91,JURN4),SUMIF(AKUN1,A91,AKUN3)-SUMIF(JURN2,"1"&A91,JURN3)+SUMIF(JURN2,"1"&A91,JURN4)),VALUE) -> 0 | D91: =IF(ISERROR=TRUE,IF(VLOOKUP(A91,DAF_AKUN,3,FALSE)="Db",SUMIF(AKUN1,A91,AKUN2)+SUMIF(JURN2,"1"&A91,JURN3)-SUMIF(JURN2,"1"&A91,JURN4)+SUMIF(JURN1,A91&TEXT(BLN,"mmmm"),JURN3)-SUMIF(JURN1,A91&TEXT(BLN,"mmmm"),JURN4),SUMIF(AKUN1,A91,AKUN3)-SUMIF(JURN2,"1"&A91,JURN3)+SUMIF(JURN2,"1"&A91,JURN4)+SUMIF(JURN1,A91&TEXT(BLN,"mmmm"),JURN4)-SUMIF(JURN1,A91&TEXT(BLN,"mmmm"),JURN3)),VALUE) -> 0
A92: 3-102-000 | B92: =VLOOKUP(A92,DAF_AKUN,2,FALSE) -> Retained Earnings | C92: =IF(ISERROR=TRUE,IF(AND(ISERROR=TRUE,VLOOKUP(A92,DAF_AKUN,3,FALSE)="Db"),SUMIF(AKUN1,A92,AKUN2)+SUMIF(JURN2,"1"&A92,JURN3)-SUMIF(JURN2,"1"&A92,JURN4),SUMIF(AKUN1,A92,AKUN3)-SUMIF(JURN2,"1"&A92,JURN3)+SUMIF(JURN2,"1"&A92,JURN4)),VALUE) -> 0 | D92: =IF(ISERROR=TRUE,IF(VLOOKUP(A92,DAF_AKUN,3,FALSE)="Db",SUMIF(AKUN1,A92,AKUN2)+SUMIF(JURN2,"1"&A92,JURN3)-SUMIF(JURN2,"1"&A92,JURN4)+SUMIF(JURN1,A92&TEXT(BLN,"mmmm"),JURN3)-SUMIF(JURN1,A92&TEXT(BLN,"mmmm"),JURN4),SUMIF(AKUN1,A92,AKUN3)-SUMIF(JURN2,"1"&A92,JURN3)+SUMIF(JURN2,"1"&A92,JURN4)+SUMIF(JURN1,A92&TEXT(BLN,"mmmm"),JURN4)-SUMIF(JURN1,A92&TEXT(BLN,"mmmm"),JURN3)),VALUE) -> 0
A93: 3-102-001 | B93: =VLOOKUP(A93,DAF_AKUN,2,FALSE) -> Accumulated Profit/(Loss) | C93: =IF(ISERROR=TRUE,IF(AND(ISERROR=TRUE,VLOOKUP(A93,DAF_AKUN,3,FALSE)="Db"),SUMIF(AKUN1,A93,AKUN2)+SUMIF(JURN2,"1"&A93,JURN3)-SUMIF(JURN2,"1"&A93,JURN4),SUMIF(AKUN1,A93,AKUN3)-SUMIF(JURN2,"1"&A93,JURN3)+SUMIF(JURN2,"1"&A93,JURN4)),VALUE) -> 4315514 | D93: =IF(ISERROR=TRUE,IF(VLOOKUP(A93,DAF_AKUN,3,FALSE)="Db",SUMIF(AKUN1,A93,AKUN2)+SUMIF(JURN2,"1"&A93,JURN3)-SUMIF(JURN2,"1"&A93,JURN4)+SUMIF(JURN1,A93&TEXT(BLN,"mmmm"),JURN3)-SUMIF(JURN1,A93&TEXT(BLN,"mmmm"),JURN4),SUMIF(AKUN1,A93,AKUN3)-SUMIF(JURN2,"1"&A93,JURN3)+SUMIF(JURN2,"1"&A93,JURN4)+SUMIF(JURN1,A93&TEXT(BLN,"mmmm"),JURN4)-SUMIF(JURN1,A93&TEXT(BLN,"mmmm"),JURN3)),VALUE) -> 4315514
A94: 3-102-002 | B94: =VLOOKUP(A94,DAF_AKUN,2,FALSE) -> Prior Year's Adjustment | C94: ='Neraca Lajur'!E85 -> 1677186 | D94: =IF(ISERROR=TRUE,IF(VLOOKUP(A94,DAF_AKUN,3,FALSE)="Db",SUMIF(AKUN1,A94,AKUN2)+SUMIF(JURN2,"1"&A94,JURN3)-SUMIF(JURN2,"1"&A94,JURN4)+SUMIF(JURN1,A94&TEXT(BLN,"mmmm"),JURN3)-SUMIF(JURN1,A94&TEXT(BLN,"mmmm"),JURN4),SUMIF(AKUN1,A94,AKUN3)-SUMIF(JURN2,"1"&A94,JURN3)+SUMIF(JURN2,"1"&A94,JURN4)+SUMIF(JURN1,A94&TEXT(BLN,"mmmm"),JURN4)-SUMIF(JURN1,A94&TEXT(BLN,"mmmm"),JURN3)),VALUE) -> 1677186
A95: 3-102-003 | B95: =VLOOKUP(A95,DAF_AKUN,2,FALSE) -> Current Year Profit/(Loss) | C95: ='Laba Rugi'!C127 -> 194953032 | D95: ='Laba Rugi'!E127 -> 263585547
A96: 3-102-004 | B96: =VLOOKUP(A96,DAF_AKUN,2,FALSE) -> Ekuitas Lainnya | C96: ='Neraca Lajur'!E87 -> 19663808 | D96: =IF(ISERROR=TRUE,IF(VLOOKUP(A96,DAF_AKUN,3,FALSE)="Db",SUMIF(AKUN1,A96,AKUN2)+SUMIF(JURN2,"1"&A96,JURN3)-SUMIF(JURN2,"1"&A96,JURN4)+SUMIF(JURN1,A96&TEXT(BLN,"mmmm"),JURN3)-SUMIF(JURN1,A96&TEXT(BLN,"mmmm"),JURN4),SUMIF(AKUN1,A96,AKUN3)-SUMIF(JURN2,"1"&A96,JURN3)+SUMIF(JURN2,"1"&A96,JURN4)+SUMIF(JURN1,A96&TEXT(BLN,"mmmm"),JURN4)-SUMIF(JURN1,A96&TEXT(BLN,"mmmm"),JURN3)),VALUE) -> 19663808
B97: Jumlah Ekuitas | C97: =SUM(C89:C96) -> 220609540 | D97: =SUM(D89:D96) -> 289242055
B99: TOTAL KEWAJIBAN & EKUITAS | C99: =C87+C97 -> 220619540 | D99: =D87+D97 -> 289252055
C101: =C58-C99 -> 0 | D101: =D58-D99 -> 0

Sheet BB Pembantu
A1: =NAMA -> ARYA USAHA TIRTA, CV
A2: BUKU BESAR PEMBANTU
A3: ="Tahun : "&THN -> Tahun : 2026
A5: Kode Pembantu | F5: Status : | G5: =VLOOKUP(C5,DAF_KODE,3,FALSE) -> #N/A
A6: Nama Relasi | C6: =VLOOKUP(C5,DAF_KODE,2,FALSE) -> #N/A | F6: Saldo Awal : | G6: =VLOOKUP(C5,DAF_KODE,4,FALSE) -> #N/A
A8: No | B8: Tanggal | C8: Bukti | D8: Keterangan | E8: Debet | F8: Kredit | G8: Saldo
A10: =A9+1 -> 1 | B10: =IF(OR(ISERROR=FALSE,ISERROR(VLOOKUP(A10&C$5,JU_KODE,4,FALSE))=TRUE),TEXT,VLOOKUP(A10&C$5,JU_KODE,4,FALSE)) -> - | C10: =IF(OR(ISERROR=FALSE,ISERROR(VLOOKUP(A10&C$5,JU_KODE,5,FALSE))=TRUE),TEXT,VLOOKUP(A10&C$5,JU_KODE,5,FALSE)) -> - | D10: =IF(OR(ISERROR=FALSE,ISERROR(VLOOKUP(A10&C$5,JU_KODE,6,FALSE))=TRUE),TEXT,VLOOKUP(A10&C$5,JU_KODE,6,FALSE)) -> - | E10: =IF(OR(ISERROR=FALSE,ISERROR(VLOOKUP(A10&C$5,JU_KODE,10,FALSE))=TRUE),TEXT,VLOOKUP(A10&C$5,JU_KODE,10,FALSE)) -> - | F10: =IF(OR(ISERROR=FALSE,ISERROR(VLOOKUP(A10&C$5,JU_KODE,11,FALSE))=TRUE),TEXT,VLOOKUP(A10&C$5,JU_KODE,11,FALSE)) -> - | G10: =IF(AND(E10=TEXT,F10=TEXT),VALUE,IF($G$5="Piutang",$G$6+SUM($E$10:E10)-SUM($F$10:F10),$G$6-SUM($E$10:E10)+SUM($F$10:F10))) -> 0
A11: =A10+1 -> 2 | B11: =IF(OR(ISERROR=FALSE,ISERROR(VLOOKUP(A11&C$5,JU_KODE,4,FALSE))=TRUE),TEXT,VLOOKUP(A11&C$5,JU_KODE,4,FALSE)) -> - | C11: =IF(OR(ISERROR=FALSE,ISERROR(VLOOKUP(A11&C$5,JU_KODE,5,FALSE))=TRUE),TEXT,VLOOKUP(A11&C$5,JU_KODE,5,FALSE)) -> - | D11: =IF(OR(ISERROR=FALSE,ISERROR(VLOOKUP(A11&C$5,JU_KODE,6,FALSE))=TRUE),TEXT,VLOOKUP(A11&C$5,JU_KODE,6,FALSE)) -> - | E11: =IF(OR(ISERROR=FALSE,ISERROR(VLOOKUP(A11&C$5,JU_KODE,10,FALSE))=TRUE),TEXT,VLOOKUP(A11&C$5,JU_KODE,10,FALSE)) -> - | F11: =IF(OR(ISERROR=FALSE,ISERROR(VLOOKUP(A11&C$5,JU_KODE,11,FALSE))=TRUE),TEXT,VLOOKUP(A11&C$5,JU_KODE,11,FALSE)) -> - | G11: =IF(AND(E11=TEXT,F11=TEXT),VALUE,IF($G$5="Piutang",$G$6+SUM($E$10:E11)-SUM($F$10:F11),$G$6-SUM($E$10:E11)+SUM($F$10:F11))) -> 0
A12: =A11+1 -> 3 | B12: =IF(OR(ISERROR=FALSE,ISERROR(VLOOKUP(A12&C$5,JU_KODE,4,FALSE))=TRUE),TEXT,VLOOKUP(A12&C$5,JU_KODE,4,FALSE)) -> - | C12: =IF(OR(ISERROR=FALSE,ISERROR(VLOOKUP(A12&C$5,JU_KODE,5,FALSE))=TRUE),TEXT,VLOOKUP(A12&C$5,JU_KODE,5,FALSE)) -> - | D12: =IF(OR(ISERROR=FALSE,ISERROR(VLOOKUP(A12&C$5,JU_KODE,6,FALSE))=TRUE),TEXT,VLOOKUP(A12&C$5,JU_KODE,6,FALSE)) -> - | E12: =IF(OR(ISERROR=FALSE,ISERROR(VLOOKUP(A12&C$5,JU_KODE,10,FALSE))=TRUE),TEXT,VLOOKUP(A12&C$5,JU_KODE,10,FALSE)) -> - | F12: =IF(OR(ISERROR=FALSE,ISERROR(VLOOKUP(A12&C$5,JU_KODE,11,FALSE))=TRUE),TEXT,VLOOKUP(A12&C$5,JU_KODE,11,FALSE)) -> - | G12: =IF(AND(E12=TEXT,F12=TEXT),VALUE,IF($G$5="Piutang",$G$6+SUM($E$10:E12)-SUM($F$10:F12),$G$6-SUM($E$10:E12)+SUM($F$10:F12))) -> 0
A13: =A12+1 -> 4 | B13: =IF(OR(ISERROR=FALSE,ISERROR(VLOOKUP(A13&C$5,JU_KODE,4,FALSE))=TRUE),TEXT,VLOOKUP(A13&C$5,JU_KODE,4,FALSE)) -> - | C13: =IF(OR(ISERROR=FALSE,ISERROR(VLOOKUP(A13&C$5,JU_KODE,5,FALSE))=TRUE),TEXT,VLOOKUP(A13&C$5,JU_KODE,5,FALSE)) -> - | D13: =IF(OR(ISERROR=FALSE,ISERROR(VLOOKUP(A13&C$5,JU_KODE,6,FALSE))=TRUE),TEXT,VLOOKUP(A13&C$5,JU_KODE,6,FALSE)) -> - | E13: =IF(OR(ISERROR=FALSE,ISERROR(VLOOKUP(A13&C$5,JU_KODE,10,FALSE))=TRUE),TEXT,VLOOKUP(A13&C$5,JU_KODE,10,FALSE)) -> - | F13: =IF(OR(ISERROR=FALSE,ISERROR(VLOOKUP(A13&C$5,JU_KODE,11,FALSE))=TRUE),TEXT,VLOOKUP(A13&C$5,JU_KODE,11,FALSE)) -> - | G13: =IF(AND(E13=TEXT,F13=TEXT),VALUE,IF($G$5="Piutang",$G$6+SUM($E$10:E13)-SUM($F$10:F13),$G$6-SUM($E$10:E13)+SUM($F$10:F13))) -> 0
A14: =A13+1 -> 5 | B14: =IF(OR(ISERROR=FALSE,ISERROR(VLOOKUP(A14&C$5,JU_KODE,4,FALSE))=TRUE),TEXT,VLOOKUP(A14&C$5,JU_KODE,4,FALSE)) -> - | C14: =IF(OR(ISERROR=FALSE,ISERROR(VLOOKUP(A14&C$5,JU_KODE,5,FALSE))=TRUE),TEXT,VLOOKUP(A14&C$5,JU_KODE,5,FALSE)) -> - | D14: =IF(OR(ISERROR=FALSE,ISERROR(VLOOKUP(A14&C$5,JU_KODE,6,FALSE))=TRUE),TEXT,VLOOKUP(A14&C$5,JU_KODE,6,FALSE)) -> - | E14: =IF(OR(ISERROR=FALSE,ISERROR(VLOOKUP(A14&C$5,JU_KODE,10,FALSE))=TRUE),TEXT,VLOOKUP(A14&C$5,JU_KODE,10,FALSE)) -> - | F14: =IF(OR(ISERROR=FALSE,ISERROR(VLOOKUP(A14&C$5,JU_KODE,11,FALSE))=TRUE),TEXT,VLOOKUP(A14&C$5,JU_KODE,11,FALSE)) -> - | G14: =IF(AND(E14=TEXT,F14=TEXT),VALUE,IF($G$5="Piutang",$G$6+SUM($E$10:E14)-SUM($F$10:F14),$G$6-SUM($E$10:E14)+SUM($F$10:F14))) -> 0
A15: =A14+1 -> 6 | B15: =IF(OR(ISERROR=FALSE,ISERROR(VLOOKUP(A15&C$5,JU_KODE,4,FALSE))=TRUE),TEXT,VLOOKUP(A15&C$5,JU_KODE,4,FALSE)) -> - | C15: =IF(OR(ISERROR=FALSE,ISERROR(VLOOKUP(A15&C$5,JU_KODE,5,FALSE))=TRUE),TEXT,VLOOKUP(A15&C$5,JU_KODE,5,FALSE)) -> - | D15: =IF(OR(ISERROR=FALSE,ISERROR(VLOOKUP(A15&C$5,JU_KODE,6,FALSE))=TRUE),TEXT,VLOOKUP(A15&C$5,JU_KODE,6,FALSE)) -> - | E15: =IF(OR(ISERROR=FALSE,ISERROR(VLOOKUP(A15&C$5,JU_KODE,10,FALSE))=TRUE),TEXT,VLOOKUP(A15&C$5,JU_KODE,10,FALSE)) -> - | F15: =IF(OR(ISERROR=FALSE,ISERROR(VLOOKUP(A15&C$5,JU_KODE,11,FALSE))=TRUE),TEXT,VLOOKUP(A15&C$5,JU_KODE,11,FALSE)) -> - | G15: =IF(AND(E15=TEXT,F15=TEXT),VALUE,IF($G$5="Piutang",$G$6+SUM($E$10:E15)-SUM($F$10:F15),$G$6-SUM($E$10:E15)+SUM($F$10:F15))) -> 0
A16: =A15+1 -> 7 | B16: =IF(OR(ISERROR=FALSE,ISERROR(VLOOKUP(A16&C$5,JU_KODE,4,FALSE))=TRUE),TEXT,VLOOKUP(A16&C$5,JU_KODE,4,FALSE)) -> - | C16: =IF(OR(ISERROR=FALSE,ISERROR(VLOOKUP(A16&C$5,JU_KODE,5,FALSE))=TRUE),TEXT,VLOOKUP(A16&C$5,JU_KODE,5,FALSE)) -> - | D16: =IF(OR(ISERROR=FALSE,ISERROR(VLOOKUP(A16&C$5,JU_KODE,6,FALSE))=TRUE),TEXT,VLOOKUP(A16&C$5,JU_KODE,6,FALSE)) -> - | E16: =IF(OR(ISERROR=FALSE,ISERROR(VLOOKUP(A16&C$5,JU_KODE,10,FALSE))=TRUE),TEXT,VLOOKUP(A16&C$5,JU_KODE,10,FALSE)) -> - | F16: =IF(OR(ISERROR=FALSE,ISERROR(VLOOKUP(A16&C$5,JU_KODE,11,FALSE))=TRUE),TEXT,VLOOKUP(A16&C$5,JU_KODE,11,FALSE)) -> - | G16: =IF(AND(E16=TEXT,F16=TEXT),VALUE,IF($G$5="Piutang",$G$6+SUM($E$10:E16)-SUM($F$10:F16),$G$6-SUM($E$10:E16)+SUM($F$10:F16))) -> 0
A17: =A16+1 -> 8 | B17: =IF(OR(ISERROR=FALSE,ISERROR(VLOOKUP(A17&C$5,JU_KODE,4,FALSE))=TRUE),TEXT,VLOOKUP(A17&C$5,JU_KODE,4,FALSE)) -> - | C17: =IF(OR(ISERROR=FALSE,ISERROR(VLOOKUP(A17&C$5,JU_KODE,5,FALSE))=TRUE),TEXT,VLOOKUP(A17&C$5,JU_KODE,5,FALSE)) -> - | D17: =IF(OR(ISERROR=FALSE,ISERROR(VLOOKUP(A17&C$5,JU_KODE,6,FALSE))=TRUE),TEXT,VLOOKUP(A17&C$5,JU_KODE,6,FALSE)) -> - | E17: =IF(OR(ISERROR=FALSE,ISERROR(VLOOKUP(A17&C$5,JU_KODE,10,FALSE))=TRUE),TEXT,VLOOKUP(A17&C$5,JU_KODE,10,FALSE)) -> - | F17: =IF(OR(ISERROR=FALSE,ISERROR(VLOOKUP(A17&C$5,JU_KODE,11,FALSE))=TRUE),TEXT,VLOOKUP(A17&C$5,JU_KODE,11,FALSE)) -> - | G17: =IF(AND(E17=TEXT,F17=TEXT),VALUE,IF($G$5="Piutang",$G$6+SUM($E$10:E17)-SUM($F$10:F17),$G$6-SUM($E$10:E17)+SUM($F$10:F17))) -> 0
A18: =A17+1 -> 9 | B18: =IF(OR(ISERROR=FALSE,ISERROR(VLOOKUP(A18&C$5,JU_KODE,4,FALSE))=TRUE),TEXT,VLOOKUP(A18&C$5,JU_KODE,4,FALSE)) -> - | C18: =IF(OR(ISERROR=FALSE,ISERROR(VLOOKUP(A18&C$5,JU_KODE,5,FALSE))=TRUE),TEXT,VLOOKUP(A18&C$5,JU_KODE,5,FALSE)) -> - | D18: =IF(OR(ISERROR=FALSE,ISERROR(VLOOKUP(A18&C$5,JU_KODE,6,FALSE))=TRUE),TEXT,VLOOKUP(A18&C$5,JU_KODE,6,FALSE)) -> - | E18: =IF(OR(ISERROR=FALSE,ISERROR(VLOOKUP(A18&C$5,JU_KODE,10,FALSE))=TRUE),TEXT,VLOOKUP(A18&C$5,JU_KODE,10,FALSE)) -> - | F18: =IF(OR(ISERROR=FALSE,ISERROR(VLOOKUP(A18&C$5,JU_KODE,11,FALSE))=TRUE),TEXT,VLOOKUP(A18&C$5,JU_KODE,11,FALSE)) -> - | G18: =IF(AND(E18=TEXT,F18=TEXT),VALUE,IF($G$5="Piutang",$G$6+SUM($E$10:E18)-SUM($F$10:F18),$G$6-SUM($E$10:E18)+SUM($F$10:F18))) -> 0
A19: =A18+1 -> 10 | B19: =IF(OR(ISERROR=FALSE,ISERROR(VLOOKUP(A19&C$5,JU_KODE,4,FALSE))=TRUE),TEXT,VLOOKUP(A19&C$5,JU_KODE,4,FALSE)) -> - | C19: =IF(OR(ISERROR=FALSE,ISERROR(VLOOKUP(A19&C$5,JU_KODE,5,FALSE))=TRUE),TEXT,VLOOKUP(A19&C$5,JU_KODE,5,FALSE)) -> - | D19: =IF(OR(ISERROR=FALSE,ISERROR(VLOOKUP(A19&C$5,JU_KODE,6,FALSE))=TRUE),TEXT,VLOOKUP(A19&C$5,JU_KODE,6,FALSE)) -> - | E19: =IF(OR(ISERROR=FALSE,ISERROR(VLOOKUP(A19&C$5,JU_KODE,10,FALSE))=TRUE),TEXT,VLOOKUP(A19&C$5,JU_KODE,10,FALSE)) -> - | F19: =IF(OR(ISERROR=FALSE,ISERROR(VLOOKUP(A19&C$5,JU_KODE,11,FALSE))=TRUE),TEXT,VLOOKUP(A19&C$5,JU_KODE,11,FALSE)) -> - | G19: =IF(AND(E19=TEXT,F19=TEXT),VALUE,IF($G$5="Piutang",$G$6+SUM($E$10:E19)-SUM($F$10:F19),$G$6-SUM($E$10:E19)+SUM($F$10:F19))) -> 0
A20: =A19+1 -> 11 | B20: =IF(OR(ISERROR=FALSE,ISERROR(VLOOKUP(A20&C$5,JU_KODE,4,FALSE))=TRUE),TEXT,VLOOKUP(A20&C$5,JU_KODE,4,FALSE)) -> - | C20: =IF(OR(ISERROR=FALSE,ISERROR(VLOOKUP(A20&C$5,JU_KODE,5,FALSE))=TRUE),TEXT,VLOOKUP(A20&C$5,JU_KODE,5,FALSE)) -> - | D20: =IF(OR(ISERROR=FALSE,ISERROR(VLOOKUP(A20&C$5,JU_KODE,6,FALSE))=TRUE),TEXT,VLOOKUP(A20&C$5,JU_KODE,6,FALSE)) -> - | E20: =IF(OR(ISERROR=FALSE,ISERROR(VLOOKUP(A20&C$5,JU_KODE,10,FALSE))=TRUE),TEXT,VLOOKUP(A20&C$5,JU_KODE,10,FALSE)) -> - | F20: =IF(OR(ISERROR=FALSE,ISERROR(VLOOKUP(A20&C$5,JU_KODE,11,FALSE))=TRUE),TEXT,VLOOKUP(A20&C$5,JU_KODE,11,FALSE)) -> - | G20: =IF(AND(E20=TEXT,F20=TEXT),VALUE,IF($G$5="Piutang",$G$6+SUM($E$10:E20)-SUM($F$10:F20),$G$6-SUM($E$10:E20)+SUM($F$10:F20))) -> 0
A21: =A20+1 -> 12 | B21: =IF(OR(ISERROR=FALSE,ISERROR(VLOOKUP(A21&C$5,JU_KODE,4,FALSE))=TRUE),TEXT,VLOOKUP(A21&C$5,JU_KODE,4,FALSE)) -> - | C21: =IF(OR(ISERROR=FALSE,ISERROR(VLOOKUP(A21&C$5,JU_KODE,5,FALSE))=TRUE),TEXT,VLOOKUP(A21&C$5,JU_KODE,5,FALSE)) -> - | D21: =IF(OR(ISERROR=FALSE,ISERROR(VLOOKUP(A21&C$5,JU_KODE,6,FALSE))=TRUE),TEXT,VLOOKUP(A21&C$5,JU_KODE,6,FALSE)) -> - | E21: =IF(OR(ISERROR=FALSE,ISERROR(VLOOKUP(A21&C$5,JU_KODE,10,FALSE))=TRUE),TEXT,VLOOKUP(A21&C$5,JU_KODE,10,FALSE)) -> - | F21: =IF(OR(ISERROR=FALSE,ISERROR(VLOOKUP(A21&C$5,JU_KODE,11,FALSE))=TRUE),TEXT,VLOOKUP(A21&C$5,JU_KODE,11,FALSE)) -> - | G21: =IF(AND(E21=TEXT,F21=TEXT),VALUE,IF($G$5="Piutang",$G$6+SUM($E$10:E21)-SUM($F$10:F21),$G$6-SUM($E$10:E21)+SUM($F$10:F21))) -> 0
... A59: =A58+1 -> 50 | B59: =IF(OR(ISERROR=FALSE,ISERROR(VLOOKUP(A59&C$5,JU_KODE,4,FALSE))=TRUE),TEXT,VLOOKUP(A59&C$5,JU_KODE,4,FALSE)) -> - | C59: =IF(OR(ISERROR=FALSE,ISERROR(VLOOKUP(A59&C$5,JU_KODE,5,FALSE))=TRUE),TEXT,VLOOKUP(A59&C$5,JU_KODE,5,FALSE)) -> - | D59: =IF(OR(ISERROR=FALSE,ISERROR(VLOOKUP(A59&C$5,JU_KODE,6,FALSE))=TRUE),TEXT,VLOOKUP(A59&C$5,JU_KODE,6,FALSE)) -> - | E59: =IF(OR(ISERROR=FALSE,ISERROR(VLOOKUP(A59&C$5,JU_KODE,10,FALSE))=TRUE),TEXT,VLOOKUP(A59&C$5,JU_KODE,10,FALSE)) -> - | F59: =IF(OR(ISERROR=FALSE,ISERROR(VLOOKUP(A59&C$5,JU_KODE,11,FALSE))=TRUE),TEXT,VLOOKUP(A59&C$5,JU_KODE,11,FALSE)) -> - | G59: =IF(AND(E59=TEXT,F59=TEXT),VALUE,IF($G$5="Piutang",$G$6+SUM($E$10:E59)-SUM($F$10:F59),$G$6-SUM($E$10:E59)+SUM($F$10:F59))) -> 0

Sheet NRC_2025
B1: =Neraca!A1 -> ARYA USAHA TIRTA, CV
B2: BALANCE SHEET
B3: For the period ended | C3: =Neraca!D6 -> 183 | D3: 2025
E5: 2025
B6: ASSET
B7: Current Asset
B8: Cash & Bank
B9: Kas Operasional-BNI Uceng | E9: 0
B10: Kas Operasional-Subang | E10: 0
B11: Kas Operasional-Jakarta | E11: 0
B12: Bank | E12: 0
B13: =Neraca!B10 -> Petty Cash | E13: =Neraca!D10 -> 0
B14: =Neraca!B11 -> CIMB Niaga - Acc. No: 800171592300 | E14: =Neraca!D11 -> 3043241
B15: =Neraca!B12 -> Bank 2 | E15: =Neraca!D12 -> 0
B16: =Neraca!B13 -> Bank 3 | E16: =Neraca!D13 -> 0
B17: =Neraca!B14 -> BAnk 4 | E17: =Neraca!D14 -> 0
B18: =Neraca!B15 -> Bank Deposit | E18: =Neraca!D15 -> 0
B19: =Neraca!B16 -> Others Deposit | E19: =Neraca!D16 -> 0
B20: =Neraca!B17 -> Cash In Transit | E20: =Neraca!D17 -> 0
B21: =Neraca!B18 -> Account Receivable | E21: =Neraca!D18 -> 0
B22: =Neraca!B19 -> Receivable - Trade | E22: =Neraca!D19 -> 277134525
B23: =Neraca!B20 -> Employee Receivable | E23: =Neraca!D20 -> 0
B24: Goods Inventory | E24: =Neraca!D21 -> 0
B25: Inventory | E25: =Neraca!D22 -> 0
B26: =Neraca!B23 -> Persediaan | E26: =Neraca!D23 -> 0
B27: =Neraca!B24 -> Shareholder's - Receivable | E27: =Neraca!D24 -> 0
B28: =Neraca!B25 -> Due To/From Subsidiary/Affiliate Company | E28: =Neraca!D25 -> 0
B29: =Neraca!B26 -> Jaya Impian Abadi PT | E29: =Neraca!D26 -> 0
B30: =Neraca!B27 -> Citra Perkasa CV | E30: =Neraca!D27 -> 0
B31: =Neraca!B28 -> Prepaid Expenses | E31: =Neraca!D28 -> 0
B32: =Neraca!B29 -> Work In Progress | E32: =Neraca!D29 -> 0
B33: =Neraca!B30 -> Prepaid Insurance | E33: =Neraca!D30 -> 0
B34: =Neraca!B31 -> Prepaid Office Rental | E34: =Neraca!D31 -> 0
B35: =Neraca!B32 -> Prepaid - Others | E35: =Neraca!D32 -> 0
B36: =Neraca!B33 -> Prepaid Taxes | E36: =Neraca!D33 -> 0
B37: =Neraca!B34 -> Prepaid PPh 22 | E37: =Neraca!D34 -> 0
... B44: =Neraca!B41 -> Mekari Pay Escrow Account | E44: =Neraca!D41 -> 0
B45: Total Current Asset | E45: =SUM(E13:E44) -> 280177766
B47: Fixed Asset
B48: =Neraca!B45 -> Building | E48: =Neraca!D45 -> 0
B49: =Neraca!B46 -> Building Improvement | E49: =Neraca!D46 -> 0
B50: =Neraca!B47 -> Motor Vehicles | E50: =Neraca!D47 -> 0
B51: =Neraca!B48 -> Office Furniture & Equipment | E51: =Neraca!D48 -> 0
B52: =Neraca!B49 -> Electronics & IT Equipment | E52: =Neraca!D49 -> 9550321
B53: =Neraca!B50 -> Acc. Depreciation - Land & Building | E53: =Neraca!D50 -> 0
B54: =Neraca!B51 -> Acc. Depreciation - Building Improvement | E54: =Neraca!D51 -> 0
B55: =Neraca!B52 -> Acc. Depreciation - Motor Vehicles | E55: =Neraca!D52 -> 0
B56: =Neraca!B53 -> Acc. Depreciation - Office Furniture & Equipment | E56: =Neraca!D53 -> 0
B57: =Neraca!B54 -> Acc. Depreciation - Electronics & IT Equipment | E57: =Neraca!D54 -> -476032
B58: Total Fixed Asset | E58: =SUM(E48:E57) -> 9074289
B59: =Neraca!B55 -> Other Asset | E59: =Neraca!D55 -> 0
B60: TOTAL ASSET | G60: =E45+E58+E59 -> 289252055
B62: LIALIBILITIES
B63: =Neraca!B60 -> Account Payable
B64: =Neraca!B61 -> Account Payable - Trade | E64: =Neraca!D61 -> 0
B65: =Neraca!B62 -> Other Payable | E65: =Neraca!D62 -> 0
B66: =Neraca!B63 -> Salary Payable | E66: =Neraca!D63 -> 0
B67: =Neraca!B64 -> BPJS Payable | E67: =Neraca!D64 -> 0
B68: =Neraca!B65 -> Accrued Expenses - General | E68: =Neraca!D65 -> 0
B69: =Neraca!B66 -> Accrued Expenses - Project | E69: =Neraca!D66 -> 0
B70: =Neraca!B67 -> Tax Payable - PPh Ps 21/26 | E70: =Neraca!D67 -> 0
B71: =Neraca!B68 -> Tax Payable - PPh Ps 23 | E71: =Neraca!D68 -> 0
B72: =Neraca!B69 -> Tax Payable - PPh Ps 29 | E72: =Neraca!D69 -> 0
B73: =Neraca!B70 -> Tax Payable - PPh Ps 4 (2) | E73: =Neraca!D70 -> 0
B74: =Neraca!B71 -> Dividend Payable | E74: =Neraca!D71 -> 0
B75: =Neraca!B72 -> Interest Payable | E75: =Neraca!D72 -> 0
... B87: =Neraca!B84 -> Fin. Institution 2 | E87: =Neraca!D84 -> 0
B88: Outstanding Payable | E88: =Neraca!D85 -> 0
B89: VAT - Out | E89: =Neraca!D86 -> 0
B90: TOTAL PAYABLE | E90: =SUM(E64:E89) -> 10000
B92: EQUITIES & RETAINED EARNING
B93: =Neraca!B90 -> Shareholdership
B94: =Neraca!B91 -> Paid-up Capital | E94: =Neraca!D91 -> 0
B95: =Neraca!B92 -> Retained Earnings
B96: =Neraca!B93 -> Accumulated Profit/(Loss) | E96: =Neraca!D93 -> 4315514
B97: =Neraca!B94 -> Prior Year's Adjustment | E97: =Neraca!D94 -> 1677186
B98: =Neraca!B96 -> Ekuitas Lainnya | E98: =Neraca!D96 -> 19663808
B99: Total Equities | E99: =SUM(E93:E98) -> 25656508
B101: TOTAL LIABILITIES & EQUITIES | G101: =E90+E99 -> 25666508
G103: Acknowledged by,
G107: Jilmi Astina Anif
G108: President Director

Sheet NRC_2025 (1-12)
B1: =NRC_2025!B1 -> ARYA USAHA TIRTA, CV
B2: BALANCE SHEET
B3: For the period ended | C3: =Neraca!D6 -> 183 | D3: 2025
E5: 2025 | H5: Jan | I5: Feb | J5: Mar | K5: Apr | L5: May | M5: Jun | N5: Jul | O5: Aug | P5: Sep | Q5: Oct | R5: Nov | S5: Dec
B6: ASSET
B7: Current Asset
B8: Cash & Bank
B9: Kas Operasional-BNI Uceng | E9: 0
B10: Kas Operasional-Subang | E10: 0
B11: Kas Operasional-Jakarta | E11: 0
B12: Bank | E12: 0
B13: =Neraca!B10 -> Petty Cash | E13: =Neraca!D10 -> 0 | H13: 0 | I13: 0 | J13: 0 | K13: 0 | L13: 0 | M13: 0 | N13: 0 | O13: 0 | P13: 0 | Q13: 0 | R13: 0 | S13: 0
B14: =Neraca!B11 -> CIMB Niaga - Acc. No: 800171592300 | E14: =Neraca!D11 -> 3043241 | H14: 1276132 | I14: 12744067 | J14: 1785455 | K14: 3305447 | L14: 6662277 | M14: 7254802 | N14: 5465689 | O14: 22841947 | P14: 19995513 | Q14: 32286768 | R14: 1789329 | S14: 3043241
B15: =Neraca!B12 -> Bank 2 | E15: =Neraca!D12 -> 0 | H15: 0 | I15: 0 | J15: 0 | K15: 0 | L15: 0 | M15: 0 | N15: 0 | O15: 0 | P15: 0 | Q15: 0 | R15: 0 | S15: 0
B16: =Neraca!B13 -> Bank 3 | E16: =Neraca!D13 -> 0 | H16: 0 | I16: 0 | J16: 0 | K16: 0 | L16: 0 | M16: 0 | N16: 0 | O16: 0 | P16: 0 | Q16: 0 | R16: 0 | S16: 0
B17: =Neraca!B14 -> BAnk 4 | E17: =Neraca!D14 -> 0 | H17: 0 | I17: 0 | J17: 0 | K17: 0 | L17: 0 | M17: 0 | N17: 0 | O17: 0 | P17: 0 | Q17: 0 | R17: 0 | S17: 0
B18: =Neraca!B15 -> Bank Deposit | E18: =Neraca!D15 -> 0 | H18: 0 | I18: 0 | J18: 0 | K18: 0 | L18: 0 | M18: 0 | N18: 0 | O18: 0 | P18: 0 | Q18: 0 | R18: 0 | S18: 0
B19: =Neraca!B16 -> Others Deposit | E19: =Neraca!D16 -> 0 | H19: 0 | I19: 0 | J19: 0 | K19: 0 | L19: 0 | M19: 0 | N19: 0 | O19: 0 | P19: 0 | Q19: 0 | R19: 0 | S19: 0
B20: =Neraca!B17 -> Cash In Transit | E20: =Neraca!D17 -> 0 | H20: 4872000 | I20: 9872000 | J20: 14072000 | K20: 19382000 | L20: 47768000 | M20: 70680408 | N20: 73952408 | O20: 78624408 | P20: 82996406 | Q20: 87668406 | R20: 87668406 | S20: 92340406
B21: =Neraca!B18 -> Account Receivable | E21: =Neraca!D18 -> 0 | H21: 0 | I21: 0 | J21: 0 | K21: 0 | L21: 0 | M21: 0 | N21: 0 | O21: 0 | P21: 0 | Q21: 0 | R21: 0 | S21: 0
B22: =Neraca!B19 -> Receivable - Trade | E22: =Neraca!D19 -> 277134525 | H22: 0 | I22: 0 | J22: 0 | K22: 0 | L22: 0 | M22: 0 | N22: 0 | O22: 0 | P22: 0 | Q22: 0 | R22: 0 | S22: 0
B23: =Neraca!B20 -> Employee Receivable | E23: =Neraca!D20 -> 0 | H23: 0 | I23: 0 | J23: 0 | K23: 0 | L23: 0 | M23: 0 | N23: 0 | O23: 0 | P23: 0 | Q23: 200000 | R23: 1950000 | S23: 1950000
B24: Goods Inventory | E24: =Neraca!D21 -> 0 | H24: 0 | I24: 0 | J24: 0 | K24: 0 | L24: 0 | M24: 0 | N24: 0 | O24: 0 | P24: 0 | Q24: 0 | R24: 0 | S24: 0
B25: Inventory | E25: =Neraca!D22 -> 0 | H25: 0 | I25: 0 | J25: 0 | K25: 0 | L25: 0 | M25: 0 | N25: 0 | O25: 0 | P25: 0 | Q25: 0 | R25: 0 | S25: 0
B26: =Neraca!B23 -> Persediaan | E26: =Neraca!D23 -> 0 | H26: 0 | I26: 0 | J26: 0 | K26: 0 | L26: 0 | M26: 0 | N26: 0 | O26: 0 | P26: 0 | Q26: 0 | R26: 0 | S26: 0
B27: =Neraca!B24 -> Shareholder's - Receivable | E27: =Neraca!D24 -> 0 | H27: 5312626.9 | I27: 5312626.9 | J27: 5312626.9 | K27: 5312626.9 | L27: 5312626.9 | M27: 5812626.9 | N27: 6105126.9 | O27: 6105126.9 | P27: 6105126.9 | Q27: 6705126.9 | R27: 6705126.9 | S27: 6705126.9
B28: =Neraca!B25 -> Due To/From Subsidiary/Affiliate Company | E28: =Neraca!D25 -> 0 | H28: 0 | I28: 0 | P28: 0
B29: =Neraca!B26 -> Jaya Impian Abadi PT | E29: =Neraca!D26 -> 0 | H29: 15587435 | I29: 15587435 | P29: 73617280
B30: =Neraca!B27 -> Citra Perkasa CV | E30: =Neraca!D27 -> 0 | H30: 0 | I30: 0 | P30: -37053800
B31: =Neraca!B28 -> Prepaid Expenses | E31: =Neraca!D28 -> 0 | H31: 0 | I31: 0 | P31: 0
B32: =Neraca!B29 -> Work In Progress | E32: =Neraca!D29 -> 0 | H32: 0 | I32: 0 | P32: 0
B33: =Neraca!B30 -> Prepaid Insurance | E33: =Neraca!D30 -> 0 | H33: 0 | I33: 0 | P33: 0
B34: =Neraca!B31 -> Prepaid Office Rental | E34: =Neraca!D31 -> 0 | H34: 0 | I34: 0 | P34: 0
B35: =Neraca!B32 -> Prepaid - Others | E35: =Neraca!D32 -> 0 | H35: 0 | I35: 0 | P35: 0
B36: =Neraca!B33 -> Prepaid Taxes | E36: =Neraca!D33 -> 0 | H36: 0 | I36: 0 | P36: 0
B37: =Neraca!B34 -> Prepaid PPh 22 | E37: =Neraca!D34 -> 0 | H37: 0 | I37: 0 | P37: 0
B38: =Neraca!B35 -> Prepaid PPh 23 | E38: =Neraca!D35 -> 0 | H38: 0 | I38: 0 | P38: 0
B39: =Neraca!B36 -> Prepaid PPh 25 | E39: =Neraca!D36 -> 0 | H39: 0 | P39: 0
B40: =Neraca!B37 -> Value Added Tax | E40: =Neraca!D37 -> 0 | H40: 0 | P40: 0
B41: =Neraca!B38 -> Input | E41: =Neraca!D38 -> 0 | H41: 0 | I41: 0 | J41: 0 | K41: 0 | L41: 0 | M41: 0 | N41: 0 | O41: 0 | P41: 0 | Q41: 0
B42: =Neraca!B39 -> Output | E42: =Neraca!D39 -> 0 | H42: 0 | I42: 0 | J42: 0 | K42: 0 | L42: 0 | M42: 0 | N42: 0 | O42: 0 | P42: 0 | Q42: 0
B43: =Neraca!B40 -> Investment | E43: =Neraca!D40 -> 0 | H43: 0 | I43: 0 | J43: 0 | K43: 0 | L43: 0 | M43: 0 | N43: 0 | O43: 0 | P43: 0 | Q43: 0
B44: =Neraca!B41 -> Mekari Pay Escrow Account | E44: =Neraca!D41 -> 0 | H44: 0 | I44: 0 | J44: 0 | K44: 0 | L44: 0 | M44: 0 | N44: 0 | O44: 0 | P44: 0 | Q44: 0
B45: Total Current Asset | E45: =SUM(E13:E44) -> 280177766 | H45: =SUM(H13:H44) -> 27048194 | I45: =SUM(I13:I44) -> 43516129 | J45: =SUM(J13:J44) -> 21170082 | K45: =SUM(K13:K44) -> 28000074 | L45: =SUM(L13:L44) -> 59742904 | M45: =SUM(M13:M44) -> 83747837 | N45: =SUM(N13:N44) -> 85523224 | O45: =SUM(O13:O44) -> 1.0757148e+08 | ... S45: =SUM(S13:S44) -> 1.0403877e+08
B47: Fixed Asset
B48: =Neraca!B45 -> Building | E48: =Neraca!D45 -> 0 | H48: 0 | I48: 0 | J48: 0 | K48: 0 | L48: 0 | M48: 0 | N48: 0 | O48: 0 | P48: 0 | Q48: 0 | R48: 0 | S48: 0
B49: =Neraca!B46 -> Building Improvement | E49: =Neraca!D46 -> 0 | H49: 0 | I49: 0 | J49: 0 | K49: 0 | L49: 0 | M49: 0 | N49: 0 | O49: 0 | P49: 0 | Q49: 0 | R49: 0 | S49: 0
B50: =Neraca!B47 -> Motor Vehicles | E50: =Neraca!D47 -> 0 | H50: 0 | I50: 0 | J50: 0 | K50: 0 | L50: 0 | M50: 0 | N50: 0 | O50: 0 | P50: 0 | Q50: 0 | R50: 0 | S50: 0
B51: =Neraca!B48 -> Office Furniture & Equipment | E51: =Neraca!D48 -> 0 | P51: 0
B52: =Neraca!B49 -> Electronics & IT Equipment | E52: =Neraca!D49 -> 9550321 | P52: 3749000 | Q52: 9550321 | R52: 9550321 | S52: 9550321
B53: =Neraca!B50 -> Acc. Depreciation - Land & Building | E53: =Neraca!D50 -> 0 | P53: 0
B54: =Neraca!B51 -> Acc. Depreciation - Building Improvement | E54: =Neraca!D51 -> 0 | P54: 0
B55: =Neraca!B52 -> Acc. Depreciation - Motor Vehicles | E55: =Neraca!D52 -> 0 | P55: 0
B56: =Neraca!B53 -> Acc. Depreciation - Office Furniture & Equipment | E56: =Neraca!D53 -> 0 | P56: 0
B57: =Neraca!B54 -> Acc. Depreciation - Electronics & IT Equipment | E57: =Neraca!D54 -> -476032 | H57: 0 | I57: 0 | J57: 0 | K57: 0 | L57: 0 | M57: 0 | N57: 0 | O57: 0 | P57: 0 | Q57: 0 | R57: 0 | S57: 0
B58: Total Fixed Asset | E58: =SUM(E48:E57) -> 9074289 | H58: =SUM(H48:H57) -> 0 | I58: =SUM(I48:I57) -> 0 | J58: =SUM(J48:J57) -> 0 | K58: =SUM(K48:K57) -> 0 | L58: =SUM(L48:L57) -> 0 | M58: =SUM(M48:M57) -> 0 | N58: =SUM(N48:N57) -> 0 | O58: =SUM(O48:O57) -> 0 | ... S58: =SUM(S48:S57) -> 9550321
B59: =Neraca!B55 -> Other Asset | E59: =Neraca!D55 -> 0 | H59: 0 | I59: 0 | J59: 0 | K59: 0 | L59: 0 | M59: 0 | N59: 0 | O59: 0 | P59: 0 | Q59: 0
B60: TOTAL ASSET | G60: =E45+E58+E59 -> 289252055 | H60: =H45+H58+H59 -> 27048194 | I60: =I45+I58+I59 -> 43516129 | J60: =J45+J58+J59 -> 21170082 | K60: =K45+K58+K59 -> 28000074 | L60: =L45+L58+L59 -> 59742904 | M60: =M45+M58+M59 -> 83747837 | N60: =N45+N58+N59 -> 85523224 | O60: =O45+O58+O59 -> 1.0757148e+08 | ... S60: =S45+S58+S59 -> 1.1358909e+08
B62: LIALIBILITIES
B63: =Neraca!B60 -> Account Payable
B64: =Neraca!B61 -> Account Payable - Trade | E64: =Neraca!D61 -> 0 | H64: 0 | I64: 0 | J64: 0 | K64: 0 | L64: 0 | M64: 0 | N64: 0 | O64: 0 | P64: 0 | Q64: 0 | R64: 0 | S64: 0
B65: =Neraca!B62 -> Other Payable | E65: =Neraca!D62 -> 0 | H65: 0 | I65: 0 | J65: 0 | K65: 0 | L65: 0 | M65: 0 | N65: 0 | O65: 0 | P65: 0 | Q65: 0 | R65: 0 | S65: 0
B66: =Neraca!B63 -> Salary Payable | E66: =Neraca!D63 -> 0 | H66: 0 | I66: 0 | J66: 0 | K66: 0 | L66: 0 | M66: 0 | N66: 0 | O66: 0 | P66: 0 | Q66: 0 | R66: 0 | S66: 0
B67: =Neraca!B64 -> BPJS Payable | E67: =Neraca!D64 -> 0 | H67: 0 | I67: 0 | J67: 0 | K67: 0 | L67: 0 | M67: 0 | N67: 0 | O67: 0 | P67: 0 | Q67: 0 | R67: 0 | S67: 0
B68: =Neraca!B65 -> Accrued Expenses - General | E68: =Neraca!D65 -> 0 | H68: 0 | I68: 0 | J68: 0 | K68: 0 | L68: 0 | M68: 0 | N68: 0 | O68: 0 | P68: 0 | Q68: 0 | R68: 0 | S68: 0
B69: =Neraca!B66 -> Accrued Expenses - Project | E69: =Neraca!D66 -> 0 | H69: 0 | I69: 0 | J69: 0 | K69: 0 | L69: 0 | M69: 0 | N69: 0 | O69: 0 | P69: 0 | Q69: 0 | R69: 0 | S69: 0
B70: =Neraca!B67 -> Tax Payable - PPh Ps 21/26 | E70: =Neraca!D67 -> 0 | H70: 0 | I70: 0 | J70: 0 | K70: 0 | L70: 0 | M70: 0 | N70: 0 | O70: 0 | P70: 0 | Q70: 0 | R70: 0 | S70: 0
B71: =Neraca!B68 -> Tax Payable - PPh Ps 23 | E71: =Neraca!D68 -> 0 | H71: 0 | I71: 0 | J71: 0 | K71: 0 | L71: 0 | M71: 0 | N71: 0 | O71: 0 | P71: 0 | Q71: 0 | R71: 0 | S71: 0
B72: =Neraca!B69 -> Tax Payable - PPh Ps 29 | E72: =Neraca!D69 -> 0 | H72: 0 | I72: 0 | J72: 0 | K72: 0 | L72: 0 | M72: 0 | N72: 0 | O72: 0 | P72: 0 | Q72: 0 | R72: 0 | S72: 0
B73: =Neraca!B70 -> Tax Payable - PPh Ps 4 (2) | E73: =Neraca!D70 -> 0 | H73: 0 | I73: 0 | J73: 0 | K73: 0 | L73: 0 | M73: 0 | N73: 0 | O73: 0 | P73: 0 | Q73: 0 | R73: 0 | S73: 0
B74: =Neraca!B71 -> Dividend Payable | E74: =Neraca!D71 -> 0 | H74: 0 | I74: 0 | J74: 0 | K74: 0 | L74: 0 | M74: 0 | N74: 0 | O74: 0 | P74: 0 | Q74: 0 | R74: 0 | S74: 0
B75: =Neraca!B72 -> Interest Payable | E75: =Neraca!D72 -> 0 | H75: 0 | I75: 0 | J75: 0 | K75: 0 | L75: 0 | M75: 0 | N75: 0 | O75: 0 | P75: 0 | Q75: 0 | R75: 0 | S75: 0
... B83: =Neraca!B80 -> Bank & Financial Institution Loan | E83: =Neraca!D80 -> 0 | H83: 0 | I83: 0 | J83: 0 | K83: 0 | L83: 0 | M83: 0 | N83: 0 | O83: 0 | P83: 0 | Q83: 0 | R83: 0 | S83: 0
B84: =Neraca!B81 -> Bank BRI | E84: =Neraca!D81 -> 0
B85: =Neraca!B82 -> Bank 2 | E85: =Neraca!D82 -> 0
B86: =Neraca!B83 -> Fin. Institution 1 | E86: =Neraca!D83 -> 0
B87: =Neraca!B84 -> Fin. Institution 2 | E87: =Neraca!D84 -> 0
B88: Outstanding Payable | E88: =Neraca!D85 -> 0
B89: VAT - Out | E89: =Neraca!D86 -> 0
B90: TOTAL PAYABLE | E90: =SUM(E64:E89) -> 10000 | H90: =SUM(H64:H89) -> 10000 | I90: =SUM(I64:I89) -> 10000 | J90: =SUM(J64:J89) -> 10000 | K90: =SUM(K64:K89) -> 10000 | L90: =SUM(L64:L89) -> 10000 | M90: =SUM(M64:M89) -> 10000 | N90: =SUM(N64:N89) -> 10000 | O90: =SUM(O64:O89) -> 10000 | ... S90: =SUM(S64:S89) -> 10000
B92: EQUITIES & RETAINED EARNING
B93: =Neraca!B90 -> Shareholdership
B94: =Neraca!B91 -> Paid-up Capital | E94: =Neraca!D91 -> 0
B95: =Neraca!B92 -> Retained Earnings
B96: =Neraca!B93 -> Accumulated Profit/(Loss) | E96: =Neraca!D93 -> 4315514 | H96: 8553020.9 | I96: 8553020.9 | J96: 8553020.9 | K96: 8553020.9 | L96: 8553020.9 | M96: 8553020.9 | N96: 8553020.9 | O96: 8553020.9 | P96: 8553020.9 | Q96: 8553020.9 | R96: 8553020.9 | S96: 8553020.9
B97: =Neraca!B94 -> Prior Year's Adjustment | E97: =Neraca!D94 -> 1677186 | I97: 0 | J97: 0 | K97: 0 | L97: 0 | M97: 0 | N97: 0 | O97: 0 | P97: 0 | Q97: 0 | R97: 0 | S97: 0
B98: =Neraca!B96 -> Ekuitas Lainnya | E98: =Neraca!D96 -> 19663808 | H98: 18485173 | I98: 34953108 | J98: 45194496 | K98: 56724488 | L98: 88467318 | M98: 108722251 | N98: 110637638 | O98: 133571941 | P98: 140846505 | Q98: 164411081 | R98: 160963642 | S98: 166889554
B99: Total Equities | E99: =SUM(E93:E98) -> 25656508 | H99: =SUM(H93:H98) -> 27038194 | I99: =SUM(I93:I98) -> 43506129 | J99: =SUM(J93:J98) -> 53747517 | K99: =SUM(K93:K98) -> 65277509 | L99: =SUM(L93:L98) -> 97020339 | M99: =SUM(M93:M98) -> 1.1727527e+08 | N99: =SUM(N93:N98) -> 1.1919066e+08 | O99: =SUM(O93:O98) -> 1.4212496e+08 | ... S99: =SUM(S93:S98) -> 1.7544257e+08
B101: TOTAL LIABILITIES & EQUITIES | G101: =E90+E99 -> 25666508 | H101: =H90+H99 -> 27048194 | I101: =I90+I99 -> 43516129 | J101: =J90+J99 -> 53757517 | K101: =K90+K99 -> 65287509 | L101: =L90+L99 -> 97030339 | M101: =M90+M99 -> 1.1728527e+08 | N101: =N90+N99 -> 1.1920066e+08 | O101: =O90+O99 -> 1.4213496e+08 | ... S101: =S90+S99 -> 1.7545257e+08
G103: Acknowledged by,
G107: Jilmi Astina Anif
G108: President Director

Sheet LR_2025
B1: ='Laba Rugi'!A1 -> ARYA USAHA TIRTA, CV
B2: INCOME STATEMENT
B3: For the period ended | C3: =Neraca!D6 -> 183 | D3: 2025
E5: 2025
B6: REVENUE
B8: ='Laba Rugi'!B8 -> Total Revenue | E8: ='Laba Rugi'!D36 -> 79478150
B9: Total Revenue | E9: =SUM(E8:E8) -> 79478150
B11: Cost of Sales
B12: ='Laba Rugi'!B39 -> Total Sales Cost ASC
B13: ='Laba Rugi'!B40 -> Operational Cost | E13: ='Laba Rugi'!D40 -> 0
B14: ='Laba Rugi'!B41 -> Tour & Surfing Cost | E14: ='Laba Rugi'!D41 -> 0
B15: ='Laba Rugi'!B42 -> Transaction Cost | E15: ='Laba Rugi'!D42 -> 10845635
B16: ='Laba Rugi'!B43 -> Licence & Permit Cost | E16: ='Laba Rugi'!D43 -> 0
B17: ='Laba Rugi'!B44 -> Product Purchase Cost | E17: ='Laba Rugi'!D44 -> 0
B18: ='Laba Rugi'!B45 -> Other Operating Cost | E18: ='Laba Rugi'!D45 -> 0
B19: ='Laba Rugi'!B46 -> Total Exhibition & Conference Cost | E19: ='Laba Rugi'!D46 -> 0
B20: ='Laba Rugi'!B47 -> Space Rental - Exhibition | E20: ='Laba Rugi'!D47 -> 0
B21: ='Laba Rugi'!B48 -> Shell Scheme Rental - Exhibition | E21: ='Laba Rugi'!D48 -> 0
B22: ='Laba Rugi'!B49 -> Conference Cost | E22: ='Laba Rugi'!D49 -> 0
B23: ='Laba Rugi'!B50 -> Man Power Cost - Exhibiton | E23: ='Laba Rugi'!D50 -> 0
B24: ='Laba Rugi'!B51 -> Sponsorship Cost | E24: ='Laba Rugi'!D51 -> 0
B25: ='Laba Rugi'!B52 -> Other Operating Cost - Exhibition | E25: ='Laba Rugi'!D52 -> 0
B26: Total Cost Of Sales | E26: =SUM(E12:E25) -> 10845635
B27: Operating Profit | F27: =E9-E26 -> 68632515
B29: EXPENSES
B30: ='Laba Rugi'!B56 -> Office Overhead
B31: ='Laba Rugi'!B57 -> Staff Cost
B32: ='Laba Rugi'!B58 -> Salary & Allowance | E32: ='Laba Rugi'!D58 -> 0
B33: ='Laba Rugi'!B59 -> 13th Month Salary | E33: ='Laba Rugi'!D59 -> 0
B34: ='Laba Rugi'!B60 -> Bonus | E34: ='Laba Rugi'!D60 -> 0
B35: ='Laba Rugi'!B61 -> Overtime | E35: ='Laba Rugi'!D61 -> 0
B36: ='Laba Rugi'!B62 -> Medical Allowance | E36: ='Laba Rugi'!D62 -> 0
B37: ='Laba Rugi'!B63 -> BPJS - Pension | E37: ='Laba Rugi'!D63 -> 0
B38: ='Laba Rugi'!B64 -> BPJS - Health | E38: ='Laba Rugi'!D64 -> 0
B39: ='Laba Rugi'!B65 -> PPh - 21 | E39: ='Laba Rugi'!D65 -> 0
B40: ='Laba Rugi'!B66 -> Recruitmen | E40: ='Laba Rugi'!D66 -> 0
B41: ='Laba Rugi'!B67 -> Training & Development | E41: ='Laba Rugi'!D67 -> 0
B42: ='Laba Rugi'!B68 -> Uniform | E42: ='Laba Rugi'!D68 -> 0
B43: ='Laba Rugi'!B69 -> Meals (Food & Snack) | E43: ='Laba Rugi'!D69 -> 0
... B77: ='Laba Rugi'!B103 -> Depr. Expenses - IT Equipment | E77: ='Laba Rugi'!D103 -> 0
B78: Disposable Goods | E78: ='Laba Rugi'!D104 -> 0
B80: Total Expenses | E80: =SUM(E30:E79) -> 0
B82: OTHER INCOME AND EXPENSES
B84: ='Laba Rugi'!B105 -> Non operating Income
B85: ='Laba Rugi'!B106 -> Interest Income | E85: =-'Laba Rugi'!D106 -> 0
B86: ='Laba Rugi'!B107 -> Profit From Forex | E86: ='Laba Rugi'!D107 -> 0
B87: ='Laba Rugi'!B108 -> Profit from disposal/sales of fixed assets | E87: =-'Laba Rugi'!D108 -> 0
B88: ='Laba Rugi'!B109 -> Rounding | E88: ='Laba Rugi'!D109 -> 0
B89: Other Income | E89: =-'Laba Rugi'!D110 -> 0
B90: ='Laba Rugi'!B111 -> Non operating Expenses | E90: ='Laba Rugi'!D111 -> 0
B91: ='Laba Rugi'!B112 -> Bank Admin Charges | E91: ='Laba Rugi'!D112 -> 0
B92: ='Laba Rugi'!B113 -> Bank Provisional Cost | E92: ='Laba Rugi'!D113 -> 0
B93: ='Laba Rugi'!B114 -> Tax on interest earned | E93: ='Laba Rugi'!D114 -> 0
B94: ='Laba Rugi'!B115 -> Interest Expenses | E94: ='Laba Rugi'!D115 -> 0
B95: ='Laba Rugi'!B116 -> Loss from disposal of assets | E95: ='Laba Rugi'!D116 -> 0
B96: ='Laba Rugi'!B117 -> Loss from forex | E96: ='Laba Rugi'!D117 -> 0
B97: ='Laba Rugi'!B118 -> Other Tax and Retribution | E97: ='Laba Rugi'!D118 -> 0
B98: Inventory Adjustment | E98: ='Laba Rugi'!D119 -> 0
B99: ='Laba Rugi'!B120 -> Corporate Income Tax | E99: ='Laba Rugi'!D120 -> 0
B100: ='Laba Rugi'!B121 -> Income Tax - PPh Ps 29 | E100: ='Laba Rugi'!D121 -> 0
B101: ='Laba Rugi'!B122 -> Dividend | E101: ='Laba Rugi'!D122 -> 0
B102: ='Laba Rugi'!B123 -> Dividend Expense | E102: ='Laba Rugi'!D123 -> 0
B103: Total Other income and expenses | E103: =SUM(E85:E102) -> 0
B105: Nett Profit / Loss Before Tax | F105: =F27-E80-E103 -> 68632515
B107: PPh | F107: 0
B109: Nett Profit / Loss | F109: =F105-F107 -> 68632515
F112: Acknowledged by,
F116: Jilmi Astina Anif
F117: President Director

Sheet LR_2025 (1-12)
B1: =LR_2025!B1 -> ARYA USAHA TIRTA, CV
B2: INCOME STATEMENT
B3: For the period ended | C3: =LR_2025!C3 -> 183 | D3: 2025
B6: REVENUE | G6: January | H6: February | I6: March | J6: April | K6: May | L6: June | M6: July | N6: August | O6: September | P6: October | Q6: November | R6: December | S6: Up to Dec 2025
B8: ='Laba Rugi'!B8 -> Total Revenue | E8: ='Laba Rugi'!D36 -> 79478150 | G8: 21598978 | H8: 20072114 | I8: 23001605 | J8: 38333955 | K8: 56880930 | L8: 36046401 | M8: 33846824 | N8: 47151440 | O8: 62375365 | P8: 65978518 | Q8: 44405300 | R8: 21086765 | S8: =SUM(G8:R8) -> 470778195
B9: Total Revenue | E9: =SUM(E8:E8) -> 79478150 | G9: =SUM(G8:G8) -> 21598978 | H9: =SUM(H8:H8) -> 20072114 | I9: =SUM(I8:I8) -> 23001605 | J9: =SUM(J8:J8) -> 38333955 | K9: =SUM(K8:K8) -> 56880930 | L9: =SUM(L8:L8) -> 36046401 | M9: =SUM(M8:M8) -> 33846824 | N9: =SUM(N8:N8) -> 47151440 | ... S9: =SUM(S8:S8) -> 470778195
B11: Cost of Sales
B12: ='Laba Rugi'!B39 -> Total Sales Cost ASC
B13: ='Laba Rugi'!B40 -> Operational Cost | E13: ='Laba Rugi'!D40 -> 0 | G13: 1950000 | H13: 3063500 | I13: 3114281 | J13: 15706670 | K13: 13223133 | L13: 9975000 | M13: 6184100 | N13: 14211100 | O13: 21961800 | P13: 8409816 | Q13: 14472628 | R13: 4300000 | S13: =SUM(G13:R13) -> 116572028
B14: ='Laba Rugi'!B41 -> Tour & Surfing Cost | E14: ='Laba Rugi'!D41 -> 0 | I14: 0 | J14: 6200000 | K14: 0 | L14: 0 | M14: 0 | N14: 0 | P14: 4750000 | Q14: 1200000 | R14: 4845000 | S14: =SUM(G14:R14) -> 16995000
B15: ='Laba Rugi'!B42 -> Transaction Cost | E15: ='Laba Rugi'!D42 -> 10845635 | I15: 0 | J15: 0 | K15: 0 | L15: 0 | M15: 0 | N15: 0 | P15: 0 | Q15: 0 | R15: 0 | S15: =SUM(G15:R15) -> 0
B16: ='Laba Rugi'!B43 -> Licence & Permit Cost | E16: ='Laba Rugi'!D43 -> 0 | I16: 0 | J16: 1300000 | K16: 0 | L16: 0 | M16: 0 | N16: 5000000 | P16: 0 | Q16: 0 | S16: =SUM(G16:R16) -> 6300000
B17: ='Laba Rugi'!B44 -> Product Purchase Cost | E17: ='Laba Rugi'!D44 -> 0 | I17: 0 | J17: 0 | K17: 0 | L17: 0 | M17: 2500000 | N17: 0 | P17: 0 | Q17: 0 | S17: =SUM(G17:R17) -> 2500000
B18: ='Laba Rugi'!B45 -> Other Operating Cost | E18: ='Laba Rugi'!D45 -> 0 | I18: 0 | J18: 0 | K18: 0 | L18: 0 | M18: 0 | N18: 0 | P18: 0 | Q18: 0 | S18: =SUM(G18:R18) -> 0
B19: ='Laba Rugi'!B46 -> Total Exhibition & Conference Cost | E19: ='Laba Rugi'!D46 -> 0 | I19: 0 | J19: 0 | K19: 0 | L19: 0 | M19: 0 | N19: 0 | P19: 0 | Q19: 0 | S19: =SUM(G19:R19) -> 0
B20: ='Laba Rugi'!B47 -> Space Rental - Exhibition | E20: ='Laba Rugi'!D47 -> 0 | I20: 0 | J20: 0 | K20: 0 | L20: 0 | M20: 0 | N20: 0 | P20: 0 | Q20: 0 | S20: =SUM(G20:R20) -> 0
B21: ='Laba Rugi'!B48 -> Shell Scheme Rental - Exhibition | E21: ='Laba Rugi'!D48 -> 0 | I21: 0 | J21: 0 | K21: 0 | L21: 0 | M21: 0 | N21: 0 | P21: 0 | Q21: 0 | S21: =SUM(G21:R21) -> 0
B22: ='Laba Rugi'!B49 -> Conference Cost | E22: ='Laba Rugi'!D49 -> 0 | I22: 0 | J22: 0 | K22: 0 | L22: 0 | M22: 0 | N22: 0 | P22: 0 | Q22: 0 | S22: =SUM(G22:R22) -> 0
B23: ='Laba Rugi'!B50 -> Man Power Cost - Exhibiton | E23: ='Laba Rugi'!D50 -> 0 | I23: 0 | J23: 0 | K23: 0 | L23: 0 | M23: 0 | N23: 0 | P23: 0 | Q23: 0 | S23: =SUM(G23:R23) -> 0
B24: ='Laba Rugi'!B51 -> Sponsorship Cost | E24: ='Laba Rugi'!D51 -> 0 | G24: 0 | H24: 0 | I24: 0 | J24: 0 | K24: 0 | L24: 0 | M24: 0 | N24: 0 | O24: 0 | P24: 0 | S24: =SUM(G24:R24) -> 0
B25: =LR_2025!B18 -> Other Operating Cost | E25: ='Laba Rugi'!D52 -> 0 | G25: 0 | H25: 0 | I25: 0 | J25: 0 | K25: 0 | L25: 0 | M25: 0 | N25: 0 | O25: 0 | P25: 0 | S25: 6000000
B26: Total Cost Of Sales | E26: =SUM(E12:E25) -> 10845635 | G26: =SUM(G12:G25) -> 1950000 | H26: =SUM(H12:H25) -> 3063500 | I26: =SUM(I12:I25) -> 3114281 | J26: =SUM(J12:J25) -> 23206670 | K26: =SUM(K12:K25) -> 13223133 | L26: =SUM(L12:L25) -> 9975000 | M26: =SUM(M12:M25) -> 8684100 | N26: =SUM(N12:N25) -> 19211100 | ... S26: =SUM(S12:S25) -> 148367028 | U26: =S26/S9 -> 0.31515272
B27: Operating Profit | E27: =E9-E26 -> 68632515 | G27: =G9-G26 -> 19648978 | H27: =H9-H26 -> 17008614 | I27: =I9-I26 -> 19887324 | J27: =J9-J26 -> 15127285 | K27: =K9-K26 -> 43657797 | L27: =L9-L26 -> 26071401 | M27: =M9-M26 -> 25162724 | N27: =N9-N26 -> 27940340 | ... S27: =S9-S26 -> 322411167 | U27: =S27/S9 -> 0.68484728
B29: EXPENSES
B30: ='Laba Rugi'!B56 -> Office Overhead
B31: ='Laba Rugi'!B57 -> Staff Cost
B32: ='Laba Rugi'!B58 -> Salary & Allowance | E32: ='Laba Rugi'!D58 -> 0 | I32: 9577436 | K32: 8577435 | L32: 3948438 | M32: 8977435 | N32: 0 | O32: 24573322 | P32: 14192325 | Q32: 14878997 | S32: =SUM(G32:R32) -> 84725388
B33: ='Laba Rugi'!B59 -> 13th Month Salary | E33: ='Laba Rugi'!D59 -> 0 | L33: 0 | M33: 0 | N33: 0 | O33: 0 | P33: 0 | Q33: 0 | S33: =SUM(G33:R33) -> 0
B34: ='Laba Rugi'!B60 -> Bonus | E34: ='Laba Rugi'!D60 -> 0 | L34: 0 | M34: 0 | N34: 0 | O34: 0 | P34: 0 | Q34: 0 | S34: =SUM(G34:R34) -> 0
B35: ='Laba Rugi'!B61 -> Overtime | E35: ='Laba Rugi'!D61 -> 0 | L35: 0 | M35: 0 | N35: 0 | O35: 0 | P35: 0 | Q35: 0 | S35: =SUM(G35:R35) -> 0
B36: ='Laba Rugi'!B62 -> Medical Allowance | E36: ='Laba Rugi'!D62 -> 0 | L36: 0 | M36: 0 | N36: 0 | O36: 0 | P36: 0 | Q36: 0 | S36: =SUM(G36:R36) -> 0
B37: ='Laba Rugi'!B63 -> BPJS - Pension | E37: ='Laba Rugi'!D63 -> 0 | G37: 668886 | J37: 2006660 | L37: 668886 | M37: 334442 | N37: 334442 | O37: 775892 | P37: 601981 | Q37: 601979 | R37: 601979 | S37: =SUM(G37:R37) -> 6595147
B38: ='Laba Rugi'!B64 -> BPJS - Health | E38: ='Laba Rugi'!D64 -> 0 | L38: 0 | M38: 0 | N38: 0 | O38: 0 | P38: 0 | Q38: 0 | S38: =SUM(G38:R38) -> 0
B39: ='Laba Rugi'!B65 -> PPh - 21 | E39: ='Laba Rugi'!D65 -> 0 | J39: 474650 | L39: 0 | M39: 0 | N39: 0 | O39: 0 | P39: 0 | Q39: 0 | S39: =SUM(G39:R39) -> 474650
B40: ='Laba Rugi'!B66 -> Recruitmen | E40: ='Laba Rugi'!D66 -> 0 | L40: 0 | M40: 0 | N40: 500000 | O40: 0 | P40: 0 | Q40: 0 | S40: =SUM(G40:R40) -> 500000
B41: ='Laba Rugi'!B67 -> Training & Development | E41: ='Laba Rugi'!D67 -> 0 | L41: 0 | M41: 0 | N41: 0 | O41: 0 | P41: 0 | Q41: 0 | S41: =SUM(G41:R41) -> 0
B42: ='Laba Rugi'!B68 -> Uniform | E42: ='Laba Rugi'!D68 -> 0 | L42: 0 | M42: 0 | N42: 0 | O42: 0 | P42: 0 | Q42: 0 | S42: =SUM(G42:R42) -> 0
B43: ='Laba Rugi'!B69 -> Meals (Food & Snack) | E43: ='Laba Rugi'!D69 -> 0 | L43: 0 | M43: 0 | N43: 0 | O43: 0 | P43: 0 | Q43: 0 | S43: =SUM(G43:R43) -> 0
B44: ='Laba Rugi'!B70 -> Staff Party | E44: ='Laba Rugi'!D70 -> 0 | L44: 0 | M44: 0 | N44: 0 | O44: 0 | P44: 0 | Q44: 0 | S44: =SUM(G44:R44) -> 0
B45: ='Laba Rugi'!B71 -> Retreat/Outing | E45: ='Laba Rugi'!D71 -> 0 | L45: 0 | M45: 0 | N45: 0 | O45: 0 | P45: 0 | Q45: 0 | S45: =SUM(G45:R45) -> 0
B46: ='Laba Rugi'!B72 -> Office Cost | E46: ='Laba Rugi'!D72 -> 0 | L46: 0 | M46: 0 | N46: 0 | O46: 0 | P46: 0 | Q46: 0 | S46: =SUM(G46:R46) -> 0
B47: ='Laba Rugi'!B73 -> Office Rental | E47: ='Laba Rugi'!D73 -> 0 | L47: 0 | M47: 0 | N47: 0 | O47: 0 | P47: 0 | Q47: 0 | S47: =SUM(G47:R47) -> 0
B48: ='Laba Rugi'!B74 -> Service Charge | E48: ='Laba Rugi'!D74 -> 0 | L48: 0 | M48: 0 | N48: 0 | O48: 0 | P48: 0 | Q48: 0 | S48: =SUM(G48:R48) -> 0
B49: ='Laba Rugi'!B75 -> Building repair & maintenance | E49: ='Laba Rugi'!D75 -> 0 | L49: 0 | M49: 1450000 | N49: 1134500 | O49: 0 | P49: 1801000 | Q49: 4312226 | S49: =SUM(G49:R49) -> 8697726
B50: ='Laba Rugi'!B76 -> Office equipment repair & maintenance | E50: ='Laba Rugi'!D76 -> 0 | L50: 0 | M50: 0 | N50: 0 | O50: 0 | P50: 0 | Q50: 0 | R50: 960000 | S50: =SUM(G50:R50) -> 960000
B51: ='Laba Rugi'!B77 -> Cleaning, garbage pickup & security | E51: ='Laba Rugi'!D77 -> 0 | K51: 832559 | L51: 0 | M51: 0 | N51: 0 | O51: 564433 | P51: 450000 | Q51: 300000 | R51: 0 | S51: =SUM(G51:R51) -> 2146992
B52: ='Laba Rugi'!B78 -> Electricity & Water | E52: ='Laba Rugi'!D78 -> 0 | G52: 435419 | H52: 474679 | J52: 314073 | K52: 2399973 | L52: 1114144 | M52: 1037053 | N52: 1901295 | O52: 919582 | P52: 2702052 | Q52: 2650978 | R52: 2663874 | S52: =SUM(G52:R52) -> 16613122
B53: ='Laba Rugi'!B79 -> Internet & Telephone | E53: ='Laba Rugi'!D79 -> 0 | J53: 0 | L53: 0 | M53: 1634530 | N53: 183300 | O53: 0 | P53: 100000 | Q53: 670150 | R53: 450000 | S53: =SUM(G53:R53) -> 3037980
B54: ='Laba Rugi'!B80 -> Postage, Courier & Stamp Duty | E54: ='Laba Rugi'!D80 -> 0 | J54: 711910 | L54: 0 | M54: 0 | N54: 0 | O54: 0 | P54: 0 | Q54: 0 | R54: 0 | S54: =SUM(G54:R54) -> 711910
B55: ='Laba Rugi'!B81 -> Office Supplies & Printing | E55: ='Laba Rugi'!D81 -> 0 | L55: 0 | M55: 0 | N55: 0 | O55: 0 | P55: 0 | Q55: 0 | R55: 0 | S55: =SUM(G55:R55) -> 0
B56: ='Laba Rugi'!B82 -> Petrol,Tol, Parking & repair/service | E56: ='Laba Rugi'!D82 -> 0 | L56: 0 | M56: 4654377 | N56: 0 | O56: 4845772 | P56: 5827500 | Q56: 500000 | R56: 600000 | S56: =SUM(G56:R56) -> 16427649
B57: ='Laba Rugi'!B83 -> Meals & Groceries | E57: ='Laba Rugi'!D83 -> 0 | L57: 0 | M57: 0 | N57: 340000 | O57: 1280000 | P57: 3184268 | Q57: 7992281 | R57: 350000 | S57: =SUM(G57:R57) -> 13146549
B58: ='Laba Rugi'!B84 -> Travel & Accomodation | E58: ='Laba Rugi'!D84 -> 0 | L58: 0 | M58: 0 | N58: 0 | O58: 0 | P58: 0 | Q58: 0 | R58: 0 | S58: =SUM(G58:R58) -> 0
B59: ='Laba Rugi'!B85 -> Donation | E59: ='Laba Rugi'!D85 -> 0 | L59: 0 | M59: 2520000 | N59: 500000 | O59: 0 | P59: 200000 | Q59: 150000 | R59: 300000 | S59: =SUM(G59:R59) -> 3670000
B60: ='Laba Rugi'!B86 -> Insurance | E60: ='Laba Rugi'!D86 -> 0 | L60: 0 | M60: 0 | N60: 0 | O60: 0 | P60: 0 | Q60: 0 | R60: 0 | S60: =SUM(G60:R60) -> 0
B61: ='Laba Rugi'!B87 -> Entertaiment/Marketing | E61: ='Laba Rugi'!D87 -> 0 | L61: 0 | M61: 0 | N61: 0 | O61: 0 | P61: 0 | Q61: 0 | R61: 0 | S61: =SUM(G61:R61) -> 0
B62: ='Laba Rugi'!B88 -> Moving Expenses | E62: ='Laba Rugi'!D88 -> 0 | L62: 0 | M62: 0 | N62: 0 | O62: 0 | P62: 0 | Q62: 0 | R62: 0 | S62: =SUM(G62:R62) -> 0
B63: ='Laba Rugi'!B89 -> Miscellaneous Expenses | E63: ='Laba Rugi'!D89 -> 0 | L63: 0 | M63: 0 | N63: 0 | O63: 0 | P63: 0 | Q63: 0 | R63: 0 | S63: =SUM(G63:R63) -> 0
B64: ='Laba Rugi'!B90 -> Professional & Finance Cost | E64: ='Laba Rugi'!D90 -> 0 | L64: 0 | M64: 0 | N64: 0 | O64: 0 | P64: 0 | Q64: 0 | R64: 0 | S64: =SUM(G64:R64) -> 0
B65: ='Laba Rugi'!B91 -> Legal Expenses | E65: ='Laba Rugi'!D91 -> 0 | L65: 0 | M65: 2500000 | N65: 0 | O65: 0 | P65: 0 | Q65: 0 | R65: 0 | S65: =SUM(G65:R65) -> 2500000
B66: ='Laba Rugi'!B92 -> Tax / Business Consultancy | E66: ='Laba Rugi'!D92 -> 0 | L66: 0 | M66: 0 | N66: 0 | O66: 0 | P66: 0 | Q66: 0 | R66: 0 | S66: =SUM(G66:R66) -> 0
B67: ='Laba Rugi'!B93 -> Accounting Services/System | E67: ='Laba Rugi'!D93 -> 0 | L67: 0 | M67: 0 | N67: 0 | O67: 0 | P67: 0 | Q67: 0 | R67: 0 | S67: =SUM(G67:R67) -> 0
B68: ='Laba Rugi'!B94 -> Association Fee | E68: ='Laba Rugi'!D94 -> 0 | G68: 0 | H68: 0 | I68: 0 | J68: 0 | K68: 0 | L68: 0 | M68: 0 | N68: 0 | O68: 0 | P68: 0 | Q68: 0 | R68: 0 | S68: =SUM(G68:R68) -> 0
B69: ='Laba Rugi'!B95 -> Debt collection fee | E69: ='Laba Rugi'!D95 -> 0 | G69: 0 | H69: 0 | I69: 0 | J69: 0 | K69: 0 | L69: 0 | M69: 0 | N69: 0 | O69: 0 | P69: 0 | Q69: 0 | R69: 0 | S69: =SUM(G69:R69) -> 0
B70: ='Laba Rugi'!B96 -> Advertisement cost | E70: ='Laba Rugi'!D96 -> 0 | G70: 0 | H70: 0 | I70: 0 | J70: 0 | K70: 0 | L70: 0 | M70: 0 | N70: 0 | O70: 0 | P70: 0 | Q70: 0 | R70: 0 | S70: =SUM(G70:R70) -> 0
B71: ='Laba Rugi'!B97 -> Bad Debt expenses | E71: ='Laba Rugi'!D97 -> 0 | G71: 0 | H71: 0 | I71: 0 | J71: 0 | K71: 0 | L71: 0 | M71: 0 | N71: 0 | O71: 0 | P71: 0 | Q71: 0 | R71: 0 | S71: =SUM(G71:R71) -> 0
B72: ='Laba Rugi'!B98 -> Depreciation & Amortization | E72: ='Laba Rugi'!D98 -> 0 | G72: 0 | H72: 0 | I72: 0 | J72: 0 | K72: 0 | L72: 0 | M72: 0 | N72: 0 | O72: 0 | P72: 0 | Q72: 0 | R72: 0 | S72: =SUM(G72:R72) -> 0
B73: ='Laba Rugi'!B99 -> Depr. Expenses - Builidng | E73: ='Laba Rugi'!D99 -> 0 | G73: 0 | H73: 0 | I73: 0 | J73: 0 | K73: 0 | L73: 0 | M73: 0 | N73: 0 | O73: 0 | P73: 0 | Q73: 0 | R73: 0 | S73: =SUM(G73:R73) -> 0
B74: ='Laba Rugi'!B100 -> Depr. Expenses - Building Improvement | E74: ='Laba Rugi'!D100 -> 0 | G74: 0 | H74: 0 | I74: 0 | J74: 0 | K74: 0 | L74: 0 | M74: 0 | N74: 0 | O74: 0 | P74: 0 | Q74: 0 | R74: 0 | S74: =SUM(G74:R74) -> 0
B75: ='Laba Rugi'!B101 -> Depr. Expenses - Motor Vehicles | E75: ='Laba Rugi'!D101 -> 0 | G75: 0 | H75: 0 | I75: 0 | J75: 0 | K75: 0 | L75: 0 | M75: 0 | N75: 0 | O75: 0 | P75: 0 | Q75: 0 | R75: 0 | S75: =SUM(G75:R75) -> 0
B76: ='Laba Rugi'!B102 -> Depr. Expenses - Office Furniture | E76: ='Laba Rugi'!D102 -> 0 | G76: 0 | H76: 0 | I76: 0 | J76: 0 | K76: 0 | L76: 0 | M76: 0 | N76: 0 | O76: 0 | P76: 0 | Q76: 0 | R76: 0 | S76: =SUM(G76:R76) -> 0
B77: ='Laba Rugi'!B103 -> Depr. Expenses - IT Equipment | E77: ='Laba Rugi'!D103 -> 0 | G77: 0 | H77: 0 | I77: 0 | J77: 0 | K77: 0 | L77: 0 | M77: 0 | N77: 0 | O77: 0 | P77: 0 | Q77: 0 | R77: 0 | S77: =SUM(G77:R77) -> 0
B78: ='Laba Rugi'!B104 -> Pengeluaran Barang Rusak | E78: ='Laba Rugi'!D104 -> 0 | G78: 0 | H78: 0 | I78: 0 | J78: 0 | K78: 0 | L78: 0 | M78: 0 | N78: 0 | O78: 0 | P78: 0 | Q78: 0 | R78: 0 | S78: =SUM(G78:R78) -> 0
B80: Total Expenses | E80: =SUM(E30:E79) -> 0 | G80: =SUM(G30:G79) -> 1104305 | H80: =SUM(H30:H79) -> 474679 | I80: =SUM(I30:I79) -> 9577436 | J80: =SUM(J30:J79) -> 3507293 | K80: =SUM(K30:K79) -> 11809967 | L80: =SUM(L30:L79) -> 5731468 | M80: =SUM(M30:M79) -> 23107837 | N80: =SUM(N30:N79) -> 4893537 | ... S80: =SUM(S30:S79) -> 160207113
B82: OTHER INCOME AND EXPENSES
B84: ='Laba Rugi'!B105 -> Non operating Income
B85: ='Laba Rugi'!B106 -> Interest Income | E85: ='Laba Rugi'!D106 -> 0 | G85: 0 | I85: 0 | S85: =SUM(G85:R85) -> 0
B86: ='Laba Rugi'!B107 -> Profit From Forex | E86: ='Laba Rugi'!D107 -> 0 | G86: 0 | I86: 0 | S86: =SUM(G86:R86) -> 0
B87: ='Laba Rugi'!B108 -> Profit from disposal/sales of fixed assets | E87: ='Laba Rugi'!D108 -> 0 | G87: 0 | I87: 0 | S87: =SUM(G87:R87) -> 0
B88: ='Laba Rugi'!B109 -> Rounding | E88: ='Laba Rugi'!D109 -> 0 | G88: 0 | I88: 0 | S88: =SUM(G88:R88) -> 0
B89: ='Laba Rugi'!B110 -> Pendapatan Lain - lain | E89: ='Laba Rugi'!D110 -> 0 | G89: 0 | I89: 0 | S89: =SUM(G89:R89) -> 0
B90: ='Laba Rugi'!B111 -> Non operating Expenses | E90: ='Laba Rugi'!D111 -> 0 | G90: 0 | I90: 0 | S90: =SUM(G90:R90) -> 0
B91: ='Laba Rugi'!B112 -> Bank Admin Charges | E91: ='Laba Rugi'!D112 -> 0 | G91: 59500 | H91: 66000 | I91: 68500 | J91: 90000 | K91: 105000 | L91: 85000 | M91: 139500 | N91: 112500 | O91: 180000 | P91: 195000 | Q91: 123500 | R91: 90000 | S91: =SUM(G91:R91) -> 1314500
B92: ='Laba Rugi'!B113 -> Bank Provisional Cost | E92: ='Laba Rugi'!D113 -> 0 | G92: 0 | I92: 0 | S92: =SUM(G92:R92) -> 0
B93: ='Laba Rugi'!B114 -> Tax on interest earned | E93: ='Laba Rugi'!D114 -> 0 | G93: 0 | I93: 0 | S93: =SUM(G93:R93) -> 0
B94: ='Laba Rugi'!B115 -> Interest Expenses | E94: ='Laba Rugi'!D115 -> 0 | G94: 0 | I94: 0 | S94: =SUM(G94:R94) -> 0
B95: ='Laba Rugi'!B116 -> Loss from disposal of assets | E95: ='Laba Rugi'!D116 -> 0 | G95: 0 | I95: 0 | S95: =SUM(G95:R95) -> 0
B96: ='Laba Rugi'!B117 -> Loss from forex | E96: ='Laba Rugi'!D117 -> 0 | G96: 0 | I96: 0 | S96: =SUM(G96:R96) -> 0
B97: ='Laba Rugi'!B118 -> Other Tax and Retribution | E97: ='Laba Rugi'!D118 -> 0 | G97: 0 | I97: 0 | S97: =SUM(G97:R97) -> 0
B98: ='Laba Rugi'!B119 -> Penyesuaian Persediaan | E98: ='Laba Rugi'!D119 -> 0 | G98: 0 | H98: 0 | I98: 0 | J98: 0 | K98: 0 | L98: 0 | M98: 0 | N98: 0 | O98: 0 | P98: 0 | S98: =SUM(G98:R98) -> 0
B99: ='Laba Rugi'!B120 -> Corporate Income Tax | E99: ='Laba Rugi'!D120 -> 0 | G99: 0 | H99: 0 | I99: 0 | J99: 0 | K99: 0 | L99: 0 | M99: 0 | N99: 0 | O99: 0 | P99: 0 | S99: =SUM(G99:R99) -> 0
B100: ='Laba Rugi'!B121 -> Income Tax - PPh Ps 29 | E100: ='Laba Rugi'!D121 -> 0 | G100: 0 | H100: 0 | I100: 0 | J100: 0 | K100: 0 | L100: 0 | M100: 0 | N100: 0 | O100: 0 | P100: 0 | S100: =SUM(G100:R100) -> 0
B101: ='Laba Rugi'!B122 -> Dividend | E101: ='Laba Rugi'!D122 -> 0 | G101: 0 | H101: 0 | I101: 0 | J101: 0 | K101: 0 | L101: 0 | M101: 0 | N101: 0 | O101: 0 | P101: 0 | S101: =SUM(G101:R101) -> 0
B102: ='Laba Rugi'!B123 -> Dividend Expense | E102: ='Laba Rugi'!D123 -> 0 | G102: 0 | H102: 0 | I102: 0 | J102: 0 | K102: 0 | L102: 0 | M102: 0 | N102: 0 | O102: 0 | P102: 0 | S102: =SUM(G102:R102) -> 0
B103: Total Other income and expenses | E103: =SUM(E85:E102) -> 0 | G103: =SUM(G85:G102) -> 59500 | H103: =SUM(H85:H102) -> 66000 | I103: =SUM(I85:I102) -> 68500 | J103: =SUM(J85:J102) -> 90000 | K103: =SUM(K85:K102) -> 105000 | L103: =SUM(L85:L102) -> 85000 | M103: =SUM(M85:M102) -> 139500 | N103: =SUM(N85:N102) -> 112500 | ... S103: =SUM(S85:S102) -> 1314500
B105: Nett Profit / Loss Before Tax | E105: =E27-E80-E103 -> 68632515 | G105: =G27-G80-G103 -> 18485173 | H105: =H27-H80-H103 -> 16467935 | I105: =I27-I80-I103 -> 10241388 | J105: =J27-J80-J103 -> 11529992 | K105: =K27-K80-K103 -> 31742830 | L105: =L27-L80-L103 -> 20254933 | M105: =M27-M80-M103 -> 1915387 | N105: =N27-N80-N103 -> 22934303 | ... S105: =S27-S80-S103 -> 160889554
B107: PPh | E107: 0 | G107: 0
B109: Nett Profit / Loss | E109: =E105-E107 -> 68632515 | G109: =G105-G107 -> 18485173 | H109: =H105-H107 -> 16467935 | I109: =I105-I107 -> 10241388 | J109: =J105-J107 -> 11529992 | K109: =K105-K107 -> 31742830 | L109: =L105-L107 -> 20254933 | M109: =M105-M107 -> 1915387 | N109: =N105-N107 -> 22934303 | ... S109: =S105-S107 -> 160889554
S110: =S109/S9 -> 0.34175235
F112: Acknowledged by, | S112: =S109*11% -> 17697851 | T112: PPh Badan
...

Sheet LR_2025 (1-12) (SPT)
B1: =LR_2025!B1 -> ARYA USAHA TIRTA, CV
B2: INCOME STATEMENT
B3: For the period ended | C3: =LR_2025!C3 -> 183 | D3: 2025
B6: REVENUE | G6: January | H6: February | I6: March | J6: April | K6: May | L6: June | M6: July | N6: August | O6: September | P6: October | Q6: November | R6: December | S6: Up to Dec 2025 | U6: Additional | V6: Koreksi
B8: ='Laba Rugi'!B8 -> Total Revenue | E8: ='Laba Rugi'!D36 -> 79478150 | G8: 21598978 | H8: 20072114 | I8: 23001605 | J8: 38333955 | K8: 56880930 | L8: 36046401 | M8: 33846824 | N8: 47151440 | O8: 62375365 | P8: 65978518 | Q8: 44405300 | R8: 21086765 | S8: =SUM(G8:R8) -> 470778195
B9: Total Revenue | E9: =SUM(E8:E8) -> 79478150 | G9: =SUM(G8:G8) -> 21598978 | H9: =SUM(H8:H8) -> 20072114 | I9: =SUM(I8:I8) -> 23001605 | J9: =SUM(J8:J8) -> 38333955 | K9: =SUM(K8:K8) -> 56880930 | L9: =SUM(L8:L8) -> 36046401 | M9: =SUM(M8:M8) -> 33846824 | N9: =SUM(N8:N8) -> 47151440 | ... S9: =SUM(S8:S8) -> 470778195
B11: Cost of Sales
B12: ='Laba Rugi'!B39 -> Total Sales Cost ASC
B13: ='Laba Rugi'!B40 -> Operational Cost | E13: ='Laba Rugi'!D40 -> 0 | G13: 1950000 | H13: 3063500 | I13: 3114281 | J13: 15706670 | K13: 13223133 | L13: 9975000 | M13: 6184100 | N13: 14211100 | O13: 21961800 | P13: 8409816 | Q13: 14472628 | R13: 4300000 | S13: =SUM(G13:R13) -> 116572028
B14: ='Laba Rugi'!B41 -> Tour & Surfing Cost | E14: ='Laba Rugi'!D41 -> 0 | I14: 0 | J14: 6200000 | K14: 0 | L14: 0 | M14: 0 | N14: 0 | P14: 4750000 | Q14: 1200000 | R14: 4845000 | S14: =SUM(G14:R14) -> 16995000
B15: ='Laba Rugi'!B42 -> Transaction Cost | E15: ='Laba Rugi'!D42 -> 10845635 | G15: 5576635 | H15: 6312394 | I15: 7966045 | J15: 10768070 | K15: 7527600 | L15: 6516176 | M15: 8354561 | N15: 6743169 | O15: 7724030 | P15: 6049659 | Q15: 2959935 | R15: 3941022 | S15: =SUM(G15:R15) -> 80439296 | U15: 13548978
B16: ='Laba Rugi'!B43 -> Licence & Permit Cost | E16: ='Laba Rugi'!D43 -> 0 | I16: 0 | J16: 1300000 | K16: 0 | L16: 0 | M16: 0 | N16: 5000000 | P16: 0 | Q16: 0 | S16: =SUM(G16:R16) -> 6300000
B17: ='Laba Rugi'!B44 -> Product Purchase Cost | E17: ='Laba Rugi'!D44 -> 0 | I17: 0 | J17: 0 | K17: 0 | L17: 0 | M17: 2500000 | N17: 0 | P17: 0 | Q17: 0 | S17: =SUM(G17:R17) -> 2500000
B18: ='Laba Rugi'!B45 -> Other Operating Cost | E18: ='Laba Rugi'!D45 -> 0 | I18: 0 | J18: 0 | K18: 0 | L18: 0 | M18: 0 | N18: 0 | P18: 0 | Q18: 0 | S18: =SUM(G18:R18) -> 0
B19: ='Laba Rugi'!B46 -> Total Exhibition & Conference Cost | E19: ='Laba Rugi'!D46 -> 0 | I19: 0 | J19: 0 | K19: 0 | L19: 0 | M19: 0 | N19: 0 | P19: 0 | Q19: 0 | S19: =SUM(G19:R19) -> 0
B20: ='Laba Rugi'!B47 -> Space Rental - Exhibition | E20: ='Laba Rugi'!D47 -> 0 | I20: 0 | J20: 0 | K20: 0 | L20: 0 | M20: 0 | N20: 0 | P20: 0 | Q20: 0 | S20: =SUM(G20:R20) -> 0
B21: ='Laba Rugi'!B48 -> Shell Scheme Rental - Exhibition | E21: ='Laba Rugi'!D48 -> 0 | I21: 0 | J21: 0 | K21: 0 | L21: 0 | M21: 0 | N21: 0 | P21: 0 | Q21: 0 | S21: =SUM(G21:R21) -> 0
B22: ='Laba Rugi'!B49 -> Conference Cost | E22: ='Laba Rugi'!D49 -> 0 | I22: 0 | J22: 0 | K22: 0 | L22: 0 | M22: 0 | N22: 0 | P22: 0 | Q22: 0 | S22: =SUM(G22:R22) -> 0
B23: ='Laba Rugi'!B50 -> Man Power Cost - Exhibiton | E23: ='Laba Rugi'!D50 -> 0 | I23: 0 | J23: 0 | K23: 0 | L23: 0 | M23: 0 | N23: 0 | P23: 0 | Q23: 0 | S23: =SUM(G23:R23) -> 0
B24: ='Laba Rugi'!B51 -> Sponsorship Cost | E24: ='Laba Rugi'!D51 -> 0 | G24: 0 | H24: 0 | I24: 0 | J24: 0 | K24: 0 | L24: 0 | M24: 0 | N24: 0 | O24: 0 | P24: 0 | S24: =SUM(G24:R24) -> 0
B25: ='LR_2025 (1-12)'!B25 -> Other Operating Cost | E25: ='Laba Rugi'!D52 -> 0 | G25: 0 | H25: 0 | I25: 0 | J25: 0 | K25: 0 | L25: 0 | M25: 0 | N25: 0 | O25: 0 | P25: 0 | S25: 3600000 | U25: =300000*12 -> 3600000
B26: Total Cost Of Sales | E26: =SUM(E12:E25) -> 10845635 | G26: =SUM(G12:G25) -> 7526635 | H26: =SUM(H12:H25) -> 9375894 | I26: =SUM(I12:I25) -> 11080326 | J26: =SUM(J12:J25) -> 33974740 | K26: =SUM(K12:K25) -> 20750733 | L26: =SUM(L12:L25) -> 16491176 | M26: =SUM(M12:M25) -> 17038661 | N26: =SUM(N12:N25) -> 25954269 | ... S26: =SUM(S12:S25) -> 226406324
